Workbook

Sheet CASES
C4: WHEN MORATORIUM,EMI AND SALE BILL IN SAME YEAR
C5: First year 12 month period
C6: Moratorium period | D6: 0
B7: CASE 1 | C7: Moratorium Interest | D7: 0
C8: EMI period | D8: 12
C9: Sale bill period | D9: 12
C11: First year 12 month period
C12: Moratorium period | D12: 3
B13: CASE 2 | C13: Moratorium Interest | D13: 3
C14: EMI period | D14: 9
C15: Sale bill period | D15: 12
C18: WHEN MORATORIUM,EMI AND SALE BILL IN 2 YEARS
C19: First year 6 month period | F19: Balance covered in 2nd year
C20: Moratorium period | D20: 0 | F20: Moratorium period | H20: 0
B21: CASE 3 | C21: Moratorium Interest | D21: 0 | F21: Moratorium Interest | H21: 0
C22: EMI period | D22: 3 | F22: EMI period | H22: 12
C23: Sale bill period | D23: 3 | F23: Sale bill period | H23: 12
C25: First year 6 month period | F25: Balance covered in 2nd year
C26: Moratorium period | D26: 6 | F26: Moratorium period | H26: 0
B27: CASE 4 | C27: Moratorium Interest | D27: 6 | F27: Moratorium Interest | H27: 0
C28: EMI period | D28: 0 | F28: EMI period | H28: 12
C29: Sale bill period | D29: 6 | F29: Sale bill period | H29: 12
C31: First year 6 month period | F31: Balance covered in 2nd year
C32: Moratorium period | D32: 6 | F32: Moratorium period | H32: 0
B33: CASE 5 | C33: Moratorium Interest | D33: 6 | F33: Moratorium Interest | H33: 0
C34: EMI period | D34: 0 | F34: EMI period | H34: 12
C35: Sale bill period | D35: 0 | F35: Sale bill period | H35: 12
C38: WHEN MORATORIUM,EMI AND SALE BILL IN 2 YEARS
C39: First year 3 month period | F39: Balance covered in 2nd year
C40: Moratorium period | D40: 0 | F40: Moratorium period | H40: 0
B41: CASE 6 | C41: Moratorium Interest | D41: 0 | F41: Moratorium Interest | H41: 0
C42: EMI period | D42: 3 | F42: EMI period | H42: 12
C43: Sale bill period | D43: 3 | F43: Sale bill period | H43: 12
C45: First year 3 month period | F45: Balance covered in 2nd year
C46: Moratorium period | D46: 6(3) | F46: Moratorium period | H46: 12(3)
B47: CASE 7 | C47: Moratorium Interest | D47: 6(3) | F47: Moratorium Interest | H47: 12(3)
C48: EMI period | D48: 0 | F48: EMI period | H48: 9
C49: Sale bill period | D49: 3 | F49: Sale bill period | H49: 12
C51: First year 6 month period | F51: Balance covered in 2nd year
C52: Moratorium period | D52: 6(3) | F52: Moratorium period | H52: 12(3)
B53: CASE 8 | C53: Moratorium Interest | D53: 6(3) | F53: Moratorium Interest | H53: 12(3)
C54: EMI period | D54: 0 | F54: EMI period | H54: 9
C55: Sale bill period | D55: 0 | F55: Sale bill period | H55: 12
B59: When there is No sale in financial year ,
C60: Profit and Loss figures:
C61: Direct Material and Expenses | E61: 0 | F61: Purchases to be increased in Third year for uniformity
C62: Closing Stock | E62: 0
C63: Gross profit | E63: 0
C64: EBT | E64: Negative
C66: Balance sheet figures:
C67: Cash and cash Equivalents | E67: 0
C68: Recievables / Debtors | E68: 0
C70: First year columns will be deleted from Ratio Analysis.
C71: Step 3 first year column in step 3 to be zero
C72: First year column in step 2 calculations can be ignored (They turn negative and can be ignored since not relevant)
C73: First year column in sheets "MPBF" and "Nayak" to be blank
C74: First year coloumn in BEP to be blank
B77: When there is Moratorium period given by banker
C79: Only interest amount will be paid during moratorium period . No EMI will be paid , So Loan outstanding will reduced to the extent principal amount paid.
B82: Break even point calculation is only for manufacturing units

Sheet Assumptions
B2: Section | C2: Question | I2: Answer | K2: Paticulars
D6: Question Type | E6: Editable | F6: Min and Max | G6: Options
B7: General information | C7: Status of Concern | D7: Dropdown Option to be provided | E7: No | G7: Sole Proprietorship / Partnership Firm / Private limited Company,LLP,Society,Trust,Federation | I7: Sole Proprietorship
C8: Name of proprietor / Managing Partner / Managing Director | D8: Manual entry | E8: No | I8: John Doe
C9: Mobile Number of proprietor / Managing Partner / Managing Director | D9: Manual entry | E9: No | I9: 9876543210
C10: Adhar number(Optional) | D10: Manual entry | E10: No | I10: 123456789012
C11: PAN of proprietor / Managing Partner / Managing Director(Optional) | D11: Manual entry | E11: No | I11: ABCDE1234F
C12: Age of Proprietorship / Managing Partner / Managing Director | D12: Manual entry | E12: No | I12: 35
C13: Gender | D13: Dropdown Option to be provided | E13: No | G13: Male,Female,Others | I13: Male
C14: Sector | D14: Dropdown Option to be provided | E14: No | G14: Manufacturing sector / Service Sector (With stock) / Service sector (Without stock) | I14: Manufacturing sector | K14: Applicable to Manufacturing or Service Sector (With Stock)
C15: Nature of Business | D15: Manual entry | E15: No | I15: Textile Manufacturing
C16: Address of office/Factory | D16: Manual entry | E16: No | I16: 123 Industrial Area, City
C17: Name of Firm / Company (Optional) | D17: Manual entry | E17: No | I17: Doe Textiles
C18: PAN of Firm / Company (Optional) | D18: Manual entry | E18: No | I18: ABCDE1234F
C19: Education Qualification | D19: Dropdown Option to be provided | E19: No | G19: Below 8th,Above 8th,SSC 10th+2,Graduate,Post Graduate | I19: Graduate
C20: Project covered under which Scheme | D20: Dropdown Option to be provided | E20: No | G20: AP IDP 4.0,Industrial park Land Allotment,PMEGP,Mudra,Other MSME | I20: PMEGP
C21: Caste | D21: Dropdown Option to be provided | E21: No | G21: OC,SC,ST,BC,Minority | I21: OC
C22: Unit location | D22: Dropdown Option to be provided | E22: No | G22: Rural,Urban | I22: Urban
J23: Salary per Month
B24: Expected Employment Generation : | C24: Skilled employees | D24: Manual entry | E24: Yes | I24: 5 | J24: 15000
C25: Semi Skilled Employees | D25: Manual entry | E25: Yes | I25: 3 | J25: 12000
C26: Unskiled Employees | D26: Manual entry | E26: Yes | I26: 2 | J26: 10000
I27: Rs in Lacs | K27: Loan % (Manual entry) | L27: Loan Amount(Rs in lacs)
B28: Cost of Project details | C28: Plant and Machinery | D28: Manual entry | E28: Yes | I28: =F134 -> 70000 | K28: 90 | L28: =K28/100*I28 -> 63000
C29: Service Equipment | D29: Manual entry | E29: Yes | I29: =F144 -> 0 | L29: =K29/100*I29 -> 0
C30: Shed Construction and Civil works | D30: Manual entry | E30: Yes | I30: =F154 -> 0 | L30: =K30/100*I30 -> 0
C31: Land | D31: Manual entry | E31: Yes | I31: =F164 -> 0 | L31: =K31/100*I31 -> 0
C32: Electrical Items & fittings | D32: Manual entry | E32: Yes | I32: =F167 -> 0 | L32: =K32/100*I32 -> 0
C33: Electronic Items | D33: Manual entry | E33: Yes | I33: =F177 -> 0 | L33: =K33/100*I33 -> 0
A34: STEP 1 | C34: Furniture and Fittings | D34: Manual entry | E34: Yes | I34: =F187 -> 5000 | L34: =K34/100*I34 -> 0
C35: Vehicles | D35: Manual entry | E35: Yes | I35: =F197 -> 0 | L35: =K35/100*I35 -> 0
C36: Live stock | D36: Manual entry | E36: Yes | I36: =F206 -> 0 | L36: =K36/100*I36 -> 0
C37: Other Assets | D37: Manual entry | E37: Yes | I37: =F216 -> 0 | L37: =K37/100*I37 -> 0
C38: Other Assets (Nil Depreciation) | D38: Manual entry | E38: Yes | I38: =F226 -> 0 | L38: =K38/100*I38 -> 0
C39: Non Current Assets (Deposits , Advances etc) | D39: Manual entry | E39: Yes | I39: =F235 -> 0 | L39: =K39/100*I39 -> 0
C40: Working capital Requirement | D40: Manual entry | E40: Yes | I40: 500000 | K40: 90 | L40: =K40/100*I40 -> 450000
C41: Total Project Cost | D41: Autogenerated | E41: Not applicable since Autogenrated | I41: =SUM(I28:J40) -> 575000 | L41: =SUM(L28:L40) -> 513000
B43: Means of Finance details | C43: Eligible Term Loan amount | D43: Autogenerated and also manually edited | E43: Yes | I43: =SUM(L28:L39) -> 63000 | K43: Lacs
C44: Margin money amount for Fixed Assets | D44: Manual entry | E44: Yes | I44: =SUM(I28:J39)-SUM(L28:L39) -> 12000 | K44: Lacs
C45: Term Loan Rate of Interest | D45: Manual entry | E45: Yes | H45: 10.5 | I45: =H45/100 -> 0.105
C46: Installment period | D46: Dropdown Option to be provided | E46: Yes | G46: Monthly / Quarterly / Half yearly / Yearly | I46: Per month
C47: Term Loan Tenure | D47: Manual entry | E47: Yes | I47: 60 | K47: months
C48: EMI or Principal Amount shared Equally over loan Term period | D48: Dropdown Option to be provided | E48: Yes | G48: 1.EMI shared equally over loan period, 2. Principal amount shared Equally over Loan Term period | I48: 1. EMI shared equally over loan Term period
C49: Moratorium period , if any (In months) | D49: Manual entry | E49: Yes | I49: 6 | K49: months
C50: Margin money for Working capital requirement | D50: Manual entry | E50: Yes | H50: 25 | I50: =H50/100 -> 0.25
C51: Eligible Working Capital Loan | D51: Autogenerated and also manually edited | E51: Yes | I51: =L40 -> 450000 | K51: Lacs
C52: Working capital Loan Rate of Interest | D52: Manual entry | E52: Yes | H52: 12 | I52: =H52/100 -> 0.12
C53: Processing fees rate | D53: Manual entry | E53: Yes | H53: 1 | I53: =(H53+H53*18/100)/100 -> 0.0118 | K53: of loan amount
C54: Total Loan amount (Term loan + Working capital Loan) | D54: Autogenerated | E54: No | I54: =L41 -> 513000 | K54: Lacs
C55: Capital Required(Own Funds) | D55: Autogenerated | E55: No | I55: =I41-L41 -> 62000 | K55: Lacs
C56: Total Project cost | D56: Autogenerated | E56: No | I56: =I54+I55 -> 575000 | K56: Lacs
B58: Other Details of the project | C58: From which month first EMI (Term Loan) will be paid | D58: Dropdown Option to be provided | E58: Yes | I58: 45383 | K58: month
C59: No of Months EMI paid in 1st financial year | D59: Manual entry | E59: Yes | I59: 12 | K59: months
C60: No of Months EMI paid in Next financial year | D60: Manual entry | E60: Yes | I60: 12 | K60: months
C61: In which month first sale bill will be generated | D61: Dropdown Option to be provided | E61: Yes | I61: 45444 | K61: month
C62: No of months Turnover done in first Financial year | D62: Manual entry | E62: Yes | I62: 10 | K62: months
C63: No of months Turnover done in Next Financial year | D63: Manual entry | E63: Yes | I63: 12 | K63: months
C64: INDIRECT EXPENSES :
C65: =B270 -> Employee Related Expenses | D65: Manual entry | E65: Yes | I65: =F270 -> 131000
C66: =B249 -> Administrative & Office Expenses | D66: Manual entry | E66: Yes | I66: =F249 -> 0 | K66: per month
C67: =B278 -> Selling and Distribution Expenses | D67: Manual entry | E67: Yes | I67: =F278 -> 0 | K67: per month
C68: =B290 -> General Overheads | D68: Manual entry | E68: Yes | I68: =F290 -> 0 | K68: per month
C69: =B298 -> Miscellaneous Expenses | D69: Manual entry | E69: Yes | I69: =F298 -> 0
C70: INDIRECT EXPENSES INCREAMENT:
C71: =C65 -> Employee Related Expenses | D71: Manual entry | E71: Yes | H71: 5 | I71: =(1+1*H71/100) -> 1.05 | K71: Of previous year
C72: =C66 -> Administrative & Office Expenses | D72: Manual entry | E72: Yes | H72: 5 | I72: =(1+1*H72/100) -> 1.05 | K72: Of previous year
C73: =C67 -> Selling and Distribution Expenses | D73: Manual entry | E73: Yes | H73: 5 | I73: =(1+1*H73/100) -> 1.05 | K73: Of previous year
C74: =C68 -> General Overheads | D74: Manual entry | E74: Yes | H74: 5 | I74: =(1+1*H74/100) -> 1.05 | K74: Of previous year
C75: =C69 -> Miscellaneous Expenses | D75: Manual entry | E75: Yes | H75: 5 | I75: =(1+1*H75/100) -> 1.05 | K75: Of previous year
C76: Average DSCR ratio required | D76: Manual entry | E76: Yes | I76: 2.5
B78: Financial years | C78: 1st Financial Year | D78: Dropdown Option to be provided | E78: Yes | I78: 2024-25 | J78: Estimated
C79: 2nd Financial Year | D79: Dropdown Option to be provided | E79: Yes | I79: 2025-26 | J79: Projected
C80: 3rd Financial Year | D80: Dropdown Option to be provided | E80: Yes | I80: 2026-27 | J80: Projected
C81: 4th Financial Year | D81: Dropdown Option to be provided | E81: Yes | I81: 2027-28 | J81: Projected
C82: 5th Financial Year | D82: Dropdown Option to be provided | E82: Yes | I82: 2028-29 | J82: Projected
C83: 6th Financial Year | D83: Dropdown Option to be provided | E83: Yes | I83: 2029-30 | J83: Projected
C84: 7th Financial Year | D84: Dropdown Option to be provided | E84: Yes | I84: 2030-31 | J84: Projected
C85: 8th Financial Year | D85: Dropdown Option to be provided | E85: Yes | I85: 2031-32 | J85: Projected
B87: ASSUMPTIONS (NOT TO BE VISIBLE TO CUSTOMER) | C87: MULTIPLYING FACTOR | D87: Predefined or Autogenerated , Hence Not Editable
C88: 1st year multiplying factor | F88: 1.75
C89: Next year Multifying factor | F89: 2
C90: Debtors as a % of Sale
C91: 1st Financial Year | F91: 0.09
C92: 2nd Financial Year | F92: 0.1
C93: 3rd Financial Year | F93: 0.11
C94: 4th Financial Year | F94: 0.12
C95: 5th Financial Year | F95: 0.13
C96: 6th Financial Year | F96: 0.14
C97: 7th Financial Year | F97: 0.15
C98: 8th Financial Year | F98: 0.16
C99: Cash& Cash Equivalents as a % of Sales
C100: 1st Financial Year | F100: =0.09+0.08 -> 0.17
A101: Back ground Verfication ( Not to be visible to customer) | C101: 2nd Financial Year | F101: =0.15+0.08 -> 0.23
C102: 3rd Financial Year | F102: =0.23+0.08 -> 0.31
C103: 4th Financial Year | F103: =0.3+0.08 -> 0.38
C104: 5th Financial Year | F104: =0.37+0.08 -> 0.45
C105: 6th Financial Year | F105: =0.45+0.08 -> 0.53
C106: 7th Financial Year | F106: =0.53+0.08 -> 0.61
C107: 8th Financial Year | F107: =0.6+0.08 -> 0.68
C108: DEPRECIATION RATES
...

Sheet Workings for PL BS 1
A1: STEP 2 : BACK GROUND CALCULATION . NOT TO BE VISIBLE TO CUSTOMER
A2: WORKINGS FOR PROFIT AND LOSS ACCOUNT ,BALANCE SHEET , EXPENDITURE AND INTEREST
A3: PARTICULARS
D4: =Assumptions!I78 -> 2024-25 | E4: =Assumptions!I79 -> 2025-26 | F4: =Assumptions!I80 -> 2026-27 | G4: =Assumptions!I81 -> 2027-28 | H4: =Assumptions!I82 -> 2028-29 | I4: =Assumptions!I83 -> 2029-30 | J4: =Assumptions!I84 -> 2030-31 | K4: =Assumptions!I85 -> 2031-32
A8: Gross Revenue | D8: =D17+D16 -> 27534148125 | E8: =E17+E16 -> -8.5736031e+09 | F8: =F17+F16 -> 4.475018e+10 | G8: =G17+G16 -> 4.6822652e+10 | H8: =H17+H16 -> 4.88953e+10 | I8: =I17+I16 -> 5.0967902e+10 | J8: =J17+J16 -> 5.3040456e+10 | K8: =K17+K16 -> 5.5112963e+10
A9: Opening Stock | D9: 0 | E9: =D11 -> #REF! | F9: =E11 -> #REF! | G9: =F11 -> #REF! | H9: =G11 -> #REF! | I9: =H11 -> #REF! | J9: =I11 -> #REF! | K9: =J11 -> #REF!
A10: Direct expenses | D10: =D6*Assumptions!#REF! -> #REF! | E10: =E6*Assumptions!#REF! -> #REF! | F10: =F6*Assumptions!#REF! -> #REF! | G10: =G6*Assumptions!#REF! -> #REF! | H10: =H6*Assumptions!#REF! -> #REF! | I10: =I6*Assumptions!#REF! -> #REF! | J10: =J6*Assumptions!#REF! -> #REF! | K10: =J10*Assumptions!#REF! -> #REF! | AE10: =#REF! -> #REF! | AF10: =#REF! -> #REF! | AG10: =#REF! -> #REF! | AH10: =#REF! -> #REF! | AI10: =#REF! -> #REF! | AJ10: =#REF! -> #REF! | AK10: =#REF! -> #REF!
A11: Closing Stock | D11: =Assumptions!#REF!*D6 -> #REF! | E11: =Assumptions!#REF!*E6 -> #REF! | F11: =Assumptions!#REF!*F6 -> #REF! | G11: =Assumptions!#REF!*G6 -> #REF! | H11: =Assumptions!#REF!*H6 -> #REF! | I11: =Assumptions!#REF!*I6 -> #REF! | J11: =Assumptions!#REF!*J6 -> #REF! | K11: =Assumptions!#REF!*K6 -> #REF! | AE11: =#REF!/D6*100 -> #REF! | AF11: =#REF!/E6*100 -> #REF! | AG11: =#REF!/F6*100 -> #REF! | AH11: =#REF!/G6*100 -> #REF! | AI11: =#REF!/H6*100 -> #REF! | AJ11: =#REF!/I6*100 -> #REF! | AK11: =#REF!/J6*100 -> #REF!
A12: Opening Stock | D12: 0 | E12: =D14 -> 6.6697626e+09 | F12: =E14 -> 58500000000 | G12: =F14 -> 59085000000 | H12: =G14 -> 59675850000 | I12: =H14 -> 60272608500 | J12: =I14 -> 60875334585 | K12: =J14 -> 6.1484088e+10
A13: Purchases | D13: =D17*Assumptions!F125 -> 2.2232542e+10 | E13: =IF(AND(Assumptions!I62=0,Assumptions!I63=0),0, IF(AND(Assumptions!I62=0,Assumptions!I63>0,Assumptions!I63<7),E17*65/28,E17*65/35)) -> 2.8116812e+10 | F13: =F17*Assumptions!F125 -> 2.9467867e+10 | G13: =G17*Assumptions!F125 -> 3.0818776e+10 | H13: =H17*Assumptions!F125 -> 3.2169838e+10 | I13: =I17*Assumptions!F125 -> 3.3520908e+10 | J13: =J17*Assumptions!F125 -> 3.4871986e+10 | K13: =K17*Assumptions!F125 -> 3.6223072e+10
A14: Closing stock | D14: =MIN(D53,D55) -> 6.6697626e+09 | E14: =D54 -> 58500000000 | F14: =E14*Assumptions!F123 -> 59085000000 | G14: =F14*Assumptions!F123 -> 59675850000 | H14: =G14*Assumptions!F123 -> 60272608500 | I14: =H14*Assumptions!F123 -> 60875334585 | J14: =I14*Assumptions!F123 -> 6.1484088e+10 | K14: =J14*Assumptions!F123 -> 6.2098929e+10
E15: =IF(Assumptions!I62>0,'Workings for PL BS 1'!E54,MIN(E53,E55)) -> 58500000000
A16: Operating Expenses | D16: =D12+D13-D14 -> 15562779375 | E16: =E12+E13-E15 -> -2.3713425e+10 | F16: =F12+F13-F14 -> 2.8882867e+10 | G16: =G12+G13-G14 -> 3.0227926e+10 | H16: =H12+H13-H14 -> 3.157308e+10 | I16: =I12+I13-I14 -> 3.2918182e+10 | J16: =J12+J13-J14 -> 3.4263233e+10 | K16: =K12+K13-K14 -> 3.5608232e+10
A17: Gross profit | D17: =D19+D18 -> 11971368750 | E17: =E19+E18 -> 1.5139822e+10 | F17: =F19+F18 -> 1.5867313e+10 | G17: =G19+G18 -> 1.6594726e+10 | H17: =H19+H18 -> 17322220630 | I17: =I19+I18 -> 1.804972e+10 | J17: =J19+J18 -> 1.8777223e+10 | K17: =K19+K18 -> 1.9504731e+10
A18: Administrative and Selling Expenses | D18: =D47 -> 606650000 | E18: =E47 -> 591572000 | F18: =F47 -> 591650600 | G18: =G47 -> 591650600 | H18: =H47 -> 591733130 | I18: =I47 -> 5.9181979e+08 | J18: =J47 -> 5.9191078e+08 | K18: =K47 -> 5.9200631e+08
A19: EBDIT | D19: ='WorKings for PL BS 2'!B31 -> 11364718750 | E19: ='WorKings for PL BS 2'!C31 -> 1.454825e+10 | F19: ='WorKings for PL BS 2'!D31 -> 1.5275662e+10 | G19: ='WorKings for PL BS 2'!E31 -> 1.6003075e+10 | H19: ='WorKings for PL BS 2'!F31 -> 1.6730487e+10 | I19: ='WorKings for PL BS 2'!G31 -> 1.74579e+10 | J19: ='WorKings for PL BS 2'!H31 -> 18185312500 | K19: ='WorKings for PL BS 2'!I31 -> 18912725000
A20: Less : Depreciation | D20: ='Dep IT act'!M17*100000 -> 9.1666667e+08 | E20: ='Dep IT act'!M24*100000 -> 9.6458333e+08 | F20: ='Dep IT act'!M31*100000 -> 822187500 | G20: ='Dep IT act'!M38*100000 -> 700921875 | H20: ='Dep IT act'!M45*100000 -> 5.9763984e+08 | I20: ='Dep IT act'!M52*100000 -> 5.0966449e+08 | J20: ='Dep IT act'!M59*100000 -> 4.3471838e+08 | K20: ='Dep IT act'!M66*100000 -> 3.7086383e+08
A21: EBIT | D21: =D19-D20 -> 1.0448052e+10 | E21: =E19-E20 -> 1.3583667e+10 | F21: =F19-F20 -> 1.4453475e+10 | G21: =G19-G20 -> 1.5302153e+10 | H21: =H19-H20 -> 1.6132848e+10 | I21: =I19-I20 -> 1.6948236e+10 | J21: =J19-J20 -> 1.7750594e+10 | K21: =K19-K20 -> 1.8541861e+10 | AE21: =RATIO!C11 -> 1.7500002 | AF21: =RATIO!D11 | AG21: =RATIO!E11 -> 2.143313 | AH21: =RATIO!F11 -> 2.2837842 | AI21: =RATIO!G11 -> 2.6972292 | AJ21: =RATIO!H11 -> 3.169084 | AK21: =RATIO!I11 -> 3.2847088
A22: Less: Interest | D22: =D51 -> 5094125000 | E22: =E51 -> 5.874125e+09 | F22: =F51 -> 5.727125e+09 | G22: =G51 -> 5.60726e+09 | H22: =H51 -> 5.5028432e+09 | I22: =I51 -> 5.5088127e+09 | J22: =J51 -> 5.5363568e+09 | K22: =K51 -> 5.5640386e+09
A24: EBT | D24: =D21-D22 -> 5.3539271e+09 | E24: =E21-E22 -> 7.7095417e+09 | F24: =F21-F22 -> 8.72635e+09 | G24: =G21-G22 -> 9.6948931e+09 | H24: =H21-H22 -> 1.0630004e+10 | I24: =I21-I22 -> 1.1439423e+10 | J24: =J21-J22 -> 1.2214237e+10 | K24: =K21-K22 -> 1.2977823e+10
A26: Net Capital | D26: =D31-SUM(D27:D30) -> -1.4411215e+09 | E26: =E31-SUM(E27:E30) -> 1.1506128e+10 | F26: =F31-SUM(F27:F30) -> 3.4293305e+10 | G26: =G31-SUM(G27:G30) -> 4.0199483e+10 | H26: =H31-SUM(H27:H30) -> 4.6546552e+10 | I26: =I31-SUM(I27:I30) -> #VALUE! | J26: =J31-SUM(J27:J30) -> #VALUE! | K26: =K31-SUM(K27:K30) -> 6.5576573e+10
A27: Term Loan | D27: ='WorKings for PL BS 2'!B14 -> 4.7833333e+09 | E27: ='WorKings for PL BS 2'!C14 -> 3.3833333e+09 | F27: ='WorKings for PL BS 2'!D14 -> 1.9833333e+09 | G27: ='WorKings for PL BS 2'!E14 -> 1.2833333e+09 | H27: ='WorKings for PL BS 2'!F14 -> 5.8333333e+08 | I27: ='WorKings for PL BS 2'!G14 -> #VALUE! | J27: ='WorKings for PL BS 2'!H14 -> #VALUE! | K27: ='WorKings for PL BS 2'!I14 -> 0
A28: ='project cost'!A31 -> Working capital Loan | D28: =Assumptions!I51*100000 -> 45000000000 | E28: =Assumptions!I51*100000 -> 45000000000 | F28: =E28 -> 45000000000 | G28: =F28 -> 45000000000 | H28: =G28 -> 45000000000 | I28: =H28 -> 45000000000 | J28: =I28 -> 45000000000 | K28: =J28 -> 45000000000
A29: Short Term Loan | D29: ='WorKings for PL BS 2'!B13 -> 1400000000 | E29: ='WorKings for PL BS 2'!C13 -> 1400000000 | F29: ='WorKings for PL BS 2'!D13 -> 1400000000 | G29: ='WorKings for PL BS 2'!E13 -> 700000000 | H29: ='WorKings for PL BS 2'!F13 -> 0 | I29: ='WorKings for PL BS 2'!G13 -> 0 | J29: ='WorKings for PL BS 2'!H13 -> 0 | K29: ='WorKings for PL BS 2'!I13 -> 0
A31: Total Liabilities | D31: =D38 -> 4.9742212e+10 | E31: =E38 -> 6.1289461e+10 | F31: =F38 -> 82676638220 | G31: =G38 -> 8.7182816e+10 | H31: =H38 -> 9.2129885e+10 | I31: =I38 -> 9.8012161e+10 | J31: =J38 -> 1.0434845e+11 | K31: =K38 -> 1.1057657e+11
A33: Fixed Assets | D33: ='Dep IT act'!M18*100000 -> 6.5833333e+09 | E33: ='Dep IT act'!M25*100000 -> 5618750000 | F33: ='Dep IT act'!M32*100000 -> 4796562500 | G33: ='Dep IT act'!M39*100000 -> 4095640625 | H33: ='Dep IT act'!M46*100000 -> 3.4980008e+09 | I33: ='Dep IT act'!M53*100000 -> 2.9883363e+09 | J33: ='Dep IT act'!M60*100000 -> 2.5536179e+09 | K33: ='Dep IT act'!M67*100000 -> 2.1827541e+09
A34: Non Current Assets | D34: =Assumptions!I39 -> 0 | E34: =D34 -> 0 | F34: =E34 -> 0 | G34: =F34 -> 0 | H34: =G34 -> 0 | I34: =H34 -> 0 | J34: =I34 -> 0 | K34: =J34 -> 0
A35: =A14 -> Closing stock | D35: =D59 -> 36000000000 | E35: ='Final workings'!C9 -> 58500000000 | F35: ='Final workings'!D9 -> 59085000000 | G35: ='Final workings'!E9 -> 59675850000 | H35: ='Final workings'!F9 -> 60272610000 | I35: ='Final workings'!G9 -> 60875330000 | J35: ='Final workings'!H9 -> 61484090000 | K35: ='Final workings'!I9 -> 62098930000
A36: Recievables | D36: =D8*Assumptions!F91 -> 2.4780733e+09 | E36: =E8*Assumptions!F92 -> -8.5736031e+08 | F36: =F8*Assumptions!F93 -> 4.9225198e+09 | G36: =G8*Assumptions!F94 -> 5.6187182e+09 | H36: =H8*Assumptions!F95 -> 6.3563891e+09 | I36: =I8*Assumptions!F96 -> 7.1355063e+09 | J36: =J8*Assumptions!F97 -> 7.9560684e+09 | K36: =K8*Assumptions!F98 -> 8.8180741e+09
A37: Cash and Cash Equivalents | D37: =D8*Assumptions!F100 -> 4.6808052e+09 | E37: =E8*Assumptions!F101 -> -1.9719287e+09 | F37: =F8*Assumptions!F102 -> 1.3872556e+10 | G37: =G8*Assumptions!F103 -> 1.7792608e+10 | H37: =H8*Assumptions!F104 -> 2.2002885e+10 | I37: =I8*Assumptions!F105 -> 2.7012988e+10 | J37: =J8*Assumptions!F106 -> 3.2354678e+10 | K37: =K8*Assumptions!F107 -> 3.7476815e+10
A38: Total Assets | D38: =SUM(D33:D37) -> 4.9742212e+10 | E38: =SUM(E33:E37) -> 6.1289461e+10 | F38: =SUM(F33:F37) -> 82676638220 | G38: =SUM(G33:G37) -> 8.7182816e+10 | H38: =SUM(H33:H37) -> 9.2129885e+10 | I38: =SUM(I33:I37) -> 9.8012161e+10 | J38: =SUM(J33:J37) -> 1.0434845e+11 | K38: =SUM(K33:K37) -> 1.1057657e+11
A40: Processing fees | D40: =Assumptions!I54*Assumptions!I53*100000 -> 605340000 | E40: =Assumptions!I40*100000*Assumptions!I53 -> 590000000 | F40: =E40 -> 590000000 | G40: =F40 -> 590000000 | H40: =G40 -> 590000000 | I40: =H40 -> 590000000 | J40: =I40 -> 590000000 | K40: =J40 -> 590000000
A41: =Assumptions!C65 -> Employee Related Expenses | D41: =Assumptions!I65*Assumptions!I62 -> 1310000 | E41: =Assumptions!I65*Assumptions!I63 -> 1572000 | F41: =Assumptions!I65*Assumptions!F130*Assumptions!I71 -> 1650600 | G41: =Assumptions!I65*Assumptions!F130*Assumptions!I71 -> 1650600 | H41: =G41*Assumptions!I71 -> 1733130 | I41: =H41*Assumptions!I71 -> 1819786.5 | J41: =I41*Assumptions!I71 -> 1910775.8 | K41: =J41*Assumptions!I71 -> 2006314.6
A42: =Assumptions!C66 -> Administrative & Office Expenses | D42: =Assumptions!I66*Assumptions!I62 -> 0 | E42: =Assumptions!I66*Assumptions!I63 -> 0 | F42: =Assumptions!I66*Assumptions!F130*Assumptions!I72 -> 0 | G42: =Assumptions!I66*Assumptions!F130*Assumptions!I72 -> 0 | H42: =G42*Assumptions!I72 -> 0 | I42: =H42*Assumptions!I72 -> 0 | J42: =I42*Assumptions!I72 -> 0 | K42: =J42*Assumptions!I72 -> 0
A43: =Assumptions!C67 -> Selling and Distribution Expenses | D43: =Assumptions!I67*Assumptions!I62 -> 0 | E43: =Assumptions!I67*Assumptions!I63 -> 0 | F43: =Assumptions!I67*Assumptions!F130*Assumptions!I73 -> 0 | G43: =F43*Assumptions!I73 -> 0 | H43: =G43*Assumptions!I73 -> 0 | I43: =H43*Assumptions!I73 -> 0 | J43: =I43*Assumptions!I73 -> 0 | K43: =J43*Assumptions!I73 -> 0
A44: =Assumptions!C68 -> General Overheads | D44: =Assumptions!I68*Assumptions!I62 -> 0 | E44: =Assumptions!I68*Assumptions!I63 -> 0 | F44: =Assumptions!I68*Assumptions!F130*Assumptions!I74 -> 0 | G44: =Assumptions!I68*Assumptions!F130*Assumptions!I74 -> 0 | H44: =G44*Assumptions!I74 -> 0 | I44: =H44*Assumptions!I74 -> 0 | J44: =I44*Assumptions!I74 -> 0 | K44: =J44*Assumptions!I74 -> 0
A45: =Assumptions!C69 -> Miscellaneous Expenses | D45: =Assumptions!I69*Assumptions!I62 -> 0 | E45: =Assumptions!I69*Assumptions!I63 -> 0 | F45: =Assumptions!I69*Assumptions!F130 -> 0 | G45: =Assumptions!I69*Assumptions!F130*Assumptions!I75 -> 0 | H45: =G45*Assumptions!I75 -> 0 | I45: =H45*Assumptions!I75 -> 0 | J45: =I45*Assumptions!I75 -> 0 | K45: =J45*Assumptions!I75 -> 0
A47: Total Selling & Adminstrative expenses | D47: =SUM(D40:D46) -> 606650000 | E47: =SUM(E40:E46) -> 591572000 | F47: =SUM(F40:F46) -> 591650600 | G47: =SUM(G40:G46) -> 591650600 | H47: =SUM(H40:H46) -> 591733130 | I47: =SUM(I40:I46) -> 5.9181979e+08 | J47: =SUM(J40:J46) -> 5.9191078e+08 | K47: =SUM(K40:K46) -> 5.9200631e+08
A49: Interest on Term Loan | D49: =SUM('Loan sch'!E24:E35) -> 5.94125e+08 | E49: =SUM('Loan sch'!E36:E47) -> 4.47125e+08 | F49: =SUM('Loan sch'!E48:E59) -> 3.00125e+08 | G49: =SUM('Loan sch'!E60:E71) -> 1.53125e+08 | H49: =SUM('Loan sch'!E72:E83) -> 21437500 | I49: =SUM('Loan sch'!E84:E95) -> 0 | J49: =SUM('Loan sch'!E96:E107) -> 0 | K49: =SUM('Loan sch'!E108:E119) -> 0
A50: Interest on CC Loan | D50: =D28*Assumptions!I52*Assumptions!I62/Assumptions!F130 -> 4500000000 | E50: =E28*Assumptions!I52*Assumptions!I63/Assumptions!F130*Assumptions!F120 -> 5.427e+09 | F50: =IF(E50=0,Assumptions!I51*100000*Assumptions!I52,Assumptions!I51*100000*Assumptions!I52*Assumptions!F127) -> 5.427e+09 | G50: =F50*Assumptions!F127 -> 5.454135e+09 | H50: =G50*Assumptions!F127 -> 5.4814057e+09 | I50: =H50*Assumptions!F127 -> 5.5088127e+09 | J50: =I50*Assumptions!F127 -> 5.5363568e+09 | K50: =J50*Assumptions!F127 -> 5.5640386e+09
D51: =SUM(D49:D50) -> 5094125000 | E51: =SUM(E49:E50) -> 5.874125e+09 | F51: =SUM(F49:F50) -> 5.727125e+09 | G51: =SUM(G49:G50) -> 5.60726e+09 | H51: =SUM(H49:H50) -> 5.5028432e+09 | I51: =SUM(I49:I50) -> 5.5088127e+09 | J51: =SUM(J49:J50) -> 5.5363568e+09 | K51: =SUM(K49:K50) -> 5.5640386e+09
D53: =D13*30% -> 6.6697626e+09 | E53: =E13*30% -> 8.4350437e+09
A54: Closing stock (130%) | D54: =Assumptions!I51*Assumptions!F122*100000 -> 58500000000 | E54: =D54 -> 58500000000
A55: Closing stock(65%) | D55: =Assumptions!I51*Assumptions!F121*100000 -> 36000000000 | E55: =D55 -> 36000000000
A57: 2 nd year closing stock | E57: =MIN(E53,E55) -> 8.4350437e+09
A59: Final Closing stock value | D59: =IF(Assumptions!I62<9,D13*30%,D55) -> 36000000000 | E59: =IF(Assumptions!J63<9,E13*30%,E55) -> 8.4350437e+09
A62: Closing stock | D62: ='Final workings'!B9 -> 6669760000 | E62: ='Final workings'!C9 -> 58500000000
A63: Debtors / Recievables | D63: ='Final workings'!B19 -> 2478070000 | E63: ='Final workings'!C19 -> -857360000
A65: Closing stock | B65: 0.75 | D65: =D62*B65 -> 5002320000 | E65: =B65*E62 -> 43875000000
A66: Debtors / Recievables | B66: 0.5 | D66: =B66*D63 -> 1239035000 | E66: =B66*E63 -> -428680000
A67: WC Eligibility arrived | D67: =D65+D66 -> 6241355000 | E67: =E65+E66 -> 43446320000
A68: Rounded off to 0000 | D68: =ROUND(D67,-4) -> 6241360000 | E68: =ROUND(E67,-4) -> 43446320000
A70: Working capital Req | D70: ='Workings for PL BS 1'!D28 -> 45000000000 | E70: ='Workings for PL BS 1'!E28 -> 45000000000
A72: Max permissable WC | D72: =IF(D68<D70,D68,D70) -> 6241360000 | E72: =IF(E68<E70,E68,E70) -> 43446320000
A74: Closing stock + Debtors | D74: =ROUND(D62,-4) -> 6669760000 | E74: =ROUND(E62,-4) -> 58500000000
A75: (Rounded off to 0000)
A77: Purchases | D77: =IF(AND(Assumptions!I62=0,Assumptions!I63=0),F17*65/30, IF(AND(Assumptions!I62=0,Assumptions!I63>0,Assumptions!I63<6),F17*65/29, IF(AND(Assumptions!I62=0,Assumptions!I63>=6),F17*65/31, IF(Assumptions!I62=0,F17*65/32,F17*65/35)))) -> 2.9467867e+10 | E77: =G17*65/32 -> 3.3708036e+10

Sheet WorKings for PL BS 2
A2: Back ground calculation (Not to be visible to customer)
A3: STEP 2: Calculation of Interest,Repayment Schedule,Loan Outstanding , Depreciation Schedule
A4: Particulars | B4: =Assumptions!I78 -> 2024-25 | C4: =Assumptions!I79 -> 2025-26 | D4: =Assumptions!I80 -> 2026-27 | E4: =Assumptions!I81 -> 2027-28 | F4: =Assumptions!I82 -> 2028-29 | G4: =Assumptions!I83 -> 2029-30 | H4: =Assumptions!I84 -> 2030-31 | I4: =Assumptions!I85 -> 2031-32
A5: Interest on Term Loan | B5: ='Workings for PL BS 1'!D49 -> 5.94125e+08 | C5: ='Workings for PL BS 1'!E49 -> 4.47125e+08 | D5: ='Workings for PL BS 1'!F49 -> 3.00125e+08 | E5: ='Workings for PL BS 1'!G49 -> 1.53125e+08 | F5: ='Workings for PL BS 1'!H49 -> 21437500 | G5: ='Workings for PL BS 1'!I49 -> 0 | H5: ='Workings for PL BS 1'!J49 -> 0 | I5: ='Workings for PL BS 1'!K49 -> 0
A6: Interest on CC Loan | B6: ='Workings for PL BS 1'!D50 -> 4500000000 | C6: ='Workings for PL BS 1'!E50 -> 5.427e+09 | D6: ='Workings for PL BS 1'!F50 -> 5.427e+09 | E6: ='Workings for PL BS 1'!G50 -> 5.454135e+09 | F6: ='Workings for PL BS 1'!H50 -> 5.4814057e+09 | G6: ='Workings for PL BS 1'!I50 -> 5.5088127e+09 | H6: ='Workings for PL BS 1'!J50 -> 5.5363568e+09 | I6: ='Workings for PL BS 1'!K50 -> 5.5640386e+09
A7: Total Interest | B7: =SUM(B5:B6) -> 5094125000 | C7: =SUM(C5:C6) -> 5.874125e+09 | D7: =SUM(D5:D6) -> 5.727125e+09 | E7: =SUM(E5:E6) -> 5.60726e+09 | F7: =SUM(F5:F6) -> 5.5028432e+09 | G7: =SUM(G5:G6) -> 5.5088127e+09 | H7: =SUM(H5:H6) -> 5.5363568e+09 | I7: =SUM(I5:I6) -> 5.5640386e+09
A9: Please refer "Repayment Sheet"
A10: Total Principal amount Repayment | B10: =Repayment!B21 -> 1400000000 | C10: =Repayment!C21 -> 1400000000 | D10: =Repayment!D21 -> 1400000000 | E10: =Repayment!E21 -> 1400000000 | F10: =Repayment!F21 -> 700000000 | G10: =Repayment!G21 -> 0 | H10: =Repayment!H21 -> 0 | I10: =Repayment!I21 -> 0
A12: Term Loan Outstanding (Including Short term loan) | B12: ='Loan sch'!G24 -> 6.1833333e+09 | C12: ='Loan sch'!G36 -> 4.7833333e+09 | D12: ='Loan sch'!G48 -> 3.3833333e+09 | E12: ='Loan sch'!G60 -> 1.9833333e+09 | F12: ='Loan sch'!G72 -> 5.8333333e+08 | G12: ='Loan sch'!G84 | H12: ='Loan sch'!G96 | I12: ='Loan sch'!G108 -> 0
A13: Short Term Loan Oustanding | B13: =Repayment!B22 -> 1400000000 | C13: =Repayment!C22 -> 1400000000 | D13: =Repayment!D22 -> 1400000000 | E13: =Repayment!E22 -> 700000000 | F13: =Repayment!F22 -> 0 | G13: =Repayment!G22 -> 0 | H13: =Repayment!H22 -> 0 | I13: =Repayment!I22 -> 0
A14: Term Loan (Only Long Term) Outstanding | B14: =B12-B13 -> 4.7833333e+09 | C14: =C12-C13 -> 3.3833333e+09 | D14: =D12-D13 -> 1.9833333e+09 | E14: =E12-E13 -> 1.2833333e+09 | F14: =F12-F13 -> 5.8333333e+08 | G14: =G12-G13 -> #VALUE! | H14: =H12-H13 -> #VALUE! | I14: =I12-I13 -> 0
A15: CC Loan Outstanding as on | B15: =IF('PL BS'!D14>0,Assumptions!I51*100000,0) -> 45000000000 | C15: =IF('PL BS'!E14>0,Assumptions!I51*100000,0) -> 0 | D15: =IF('PL BS'!F14>0,Assumptions!I51*100000,0) -> 45000000000 | E15: =IF('PL BS'!G14>0,Assumptions!I51*100000) -> 45000000000 | F15: =IF('PL BS'!H14>0,Assumptions!I51*100000,0) -> 45000000000 | G15: =IF('PL BS'!I14>0,Assumptions!I51*100000,0) -> 45000000000 | H15: =IF('PL BS'!J14>0,Assumptions!I51*100000,0) -> 45000000000 | I15: =IF('PL BS'!K14>0,Assumptions!I51*100000,0) -> 45000000000
A18: Please refer "Dep IT Act" Sheet
A19: Total Fixed Asset Value arrived
A20: Gross Fixed Assets | B20: ='Dep IT act'!M16*100000 -> 7500000000 | C20: ='Dep IT act'!M23*100000 -> 6.5833333e+09 | D20: ='Dep IT act'!M30*100000 -> 5618750000 | E20: ='Dep IT act'!M37*100000 -> 4796562500 | F20: ='Dep IT act'!M44*100000 -> 4095640625 | G20: ='Dep IT act'!M51*100000 -> 3.4980008e+09 | H20: ='Dep IT act'!M58*100000 -> 2.9883363e+09 | I20: ='Dep IT act'!M65*100000 -> 2.5536179e+09
A21: Total Depreciation | B21: ='Dep IT act'!M17*100000 -> 9.1666667e+08 | C21: ='Dep IT act'!M24*100000 -> 9.6458333e+08 | D21: ='Dep IT act'!M31*100000 -> 822187500 | E21: ='Dep IT act'!M38*100000 -> 700921875 | F21: ='Dep IT act'!M45*100000 -> 5.9763984e+08 | G21: ='Dep IT act'!M52*100000 -> 5.0966449e+08 | H21: ='Dep IT act'!M59*100000 -> 4.3471838e+08 | I21: ='Dep IT act'!M66*100000 -> 3.7086383e+08
A22: Net Fixed Assets | B22: =B20-B21 -> 6.5833333e+09 | C22: =C20-C21 -> 5618750000 | D22: =D20-D21 -> 4796562500 | E22: =E20-E21 -> 4095640625 | F22: =F20-F21 -> 3.4980008e+09 | G22: =G20-G21 -> 2.9883363e+09 | H22: =H20-H21 -> 2.5536179e+09 | I22: =I20-I21 -> 2.1827541e+09
A25: =A10 -> Total Principal amount Repayment | B25: =B10 -> 1400000000 | C25: =C10 -> 1400000000 | D25: =D10 -> 1400000000 | E25: =E10 -> 1400000000 | F25: =F10 -> 700000000 | G25: =G10 -> 0 | H25: =H10 -> 0 | I25: =I10 -> 0
A26: =A7 -> Total Interest | B26: =B7 -> 5094125000 | C26: =C7 -> 5.874125e+09 | D26: =D7 -> 5.727125e+09 | E26: =E7 -> 5.60726e+09 | F26: =F7 -> 5.5028432e+09 | G26: =G7 -> 5.5088127e+09 | H26: =H7 -> 5.5363568e+09 | I26: =I7 -> 5.5640386e+09
A27: Total (Principal + Interest) | B27: =B26+B25 -> 6494125000 | C27: =C26+C25 -> 7.274125e+09 | D27: =D26+D25 -> 7.127125e+09 | E27: =E26+E25 -> 7.00726e+09 | F27: =F26+F25 -> 6.2028432e+09 | G27: =G26+G25 -> 5.5088127e+09 | H27: =H26+H25 -> 5.5363568e+09 | I27: =I26+I25 -> 5.5640386e+09
A28: Base value for Calculating EBDIT | B28: =B27 -> 6494125000 | C28: =C27 -> 7.274125e+09 | D28: =MAX(C27:I27) -> 7.274125e+09
A31: (Finvois Value - EBDIT ) | B31: ='Final workings'!B6*'WorKings for PL BS 2'!B28 -> 11364718750 | C31: ='Final workings'!C6*C28 -> 1.454825e+10 | D31: ='Final workings'!D6*'WorKings for PL BS 2'!D28 -> 1.5275662e+10 | E31: ='Final workings'!E6*'WorKings for PL BS 2'!D28 -> 1.6003075e+10 | F31: ='Final workings'!F6*'WorKings for PL BS 2'!D28 -> 1.6730487e+10 | G31: ='Final workings'!G6*'WorKings for PL BS 2'!D28 -> 1.74579e+10 | H31: ='Final workings'!H6*'WorKings for PL BS 2'!D28 -> 18185312500 | I31: ='Final workings'!I6*'WorKings for PL BS 2'!D28 -> 18912725000

Sheet Final workings
A3: FINANCIALS AND RATIOS AT A GLANCE
A4: ='WorKings for PL BS 2'!A4 -> Particulars | B4: =Assumptions!I78 -> 2024-25 | C4: =Assumptions!I79 -> 2025-26 | D4: =Assumptions!I80 -> 2026-27 | E4: =Assumptions!I81 -> 2027-28 | F4: =Assumptions!I82 -> 2028-29 | G4: =Assumptions!I83 -> 2029-30 | H4: =Assumptions!I84 -> 2030-31 | I4: =Assumptions!I85 -> 2031-32
A5: PROFIT AND LOSS ACCOUNT Items at a Glance:
A6: Finvois Factor (Predefined and Editable) | B6: =IF(Assumptions!I62=0,0,Assumptions!F88) -> 1.75 | C6: =IF(Assumptions!I63=0,0,Assumptions!F89) -> 2 | D6: =IF(C6=0,Assumptions!F89,C6+0.1) -> 2.1 | E6: =D6+0.1 -> 2.2 | F6: =E6+0.1 -> 2.3 | G6: =F6+0.1 -> 2.4 | H6: =G6+0.1 -> 2.5 | I6: =H6+0.1 -> 2.6
A7: Turnover (Editable) | B7: =ROUND(IF(Assumptions!I62=0,0,'Workings for PL BS 1'!D8),-4) -> 27534150000 | C7: =ROUND(IF(Assumptions!I63=0,0,'Workings for PL BS 1'!E8),-4) -> -8573600000 | D7: =ROUND('Workings for PL BS 1'!F8,-4) -> 44750180000 | E7: =ROUND('Workings for PL BS 1'!G8,-4) -> 46822650000 | F7: =ROUND('Workings for PL BS 1'!H8,-4) -> 48895300000 | G7: =ROUND('Workings for PL BS 1'!I8,-4) -> 50967900000 | H7: =ROUND('Workings for PL BS 1'!J8,-4) -> 53040460000 | I7: =ROUND('Workings for PL BS 1'!K8,-4) -> 55112960000
A8: Direct Material / Expenses (Editable) | B8: =ROUND(IF(Assumptions!I62=0,0,'Workings for PL BS 1'!D13),-4) -> 22232540000 | C8: =ROUND('Workings for PL BS 1'!E13,-4) -> 28116810000 | D8: =ROUND('Workings for PL BS 1'!D77,-4) -> 29467870000 | E8: =ROUND(IF(C8=0,'Workings for PL BS 1'!E77,'Workings for PL BS 1'!G13),-4) -> 30818780000 | F8: =ROUND('Workings for PL BS 1'!H13,-4) -> 32169840000 | G8: =ROUND('Workings for PL BS 1'!I13,-4) -> 33520910000 | H8: =ROUND('Workings for PL BS 1'!J13,-4) -> 34871990000 | I8: =ROUND('Workings for PL BS 1'!K13,-4) -> 36223070000
A9: Closing stock / Closing WIP (Editable) | B9: =ROUND(IF(Assumptions!I62=0,0,'Workings for PL BS 1'!D14),-4) -> 6669760000 | C9: =ROUND(IF(C7=0,0,'Workings for PL BS 1'!E15),-4) -> 58500000000 | D9: =ROUND(IF(C9=0,'Workings for PL BS 1'!E55,'Workings for PL BS 1'!F14),-4) -> 59085000000 | E9: =ROUND('Workings for PL BS 1'!G14,-4) -> 59675850000 | F9: =ROUND('Workings for PL BS 1'!H14,-4) -> 60272610000 | G9: =ROUND('Workings for PL BS 1'!I14,-4) -> 60875330000 | H9: =ROUND('Workings for PL BS 1'!J14,-4) -> 61484090000 | I9: =ROUND('Workings for PL BS 1'!K14,-4) -> 62098930000
A10: Employee Related Expenses (Editable) | B10: =ROUND('Workings for PL BS 1'!D41,-4) -> 1310000 | C10: =ROUND('Workings for PL BS 1'!E41,-4) -> 1570000 | D10: =ROUND('Workings for PL BS 1'!F41,-4) -> 1650000 | E10: =ROUND('Workings for PL BS 1'!G41,-4) -> 1650000 | F10: =ROUND('Workings for PL BS 1'!H41,-4) -> 1730000 | G10: =ROUND('Workings for PL BS 1'!I41,-4) -> 1820000 | H10: =ROUND('Workings for PL BS 1'!J41,-4) -> 1910000 | I10: =ROUND('Workings for PL BS 1'!K41,-4) -> 2010000
A11: Administrative & Office Expenses (Editable) | B11: =ROUND('Workings for PL BS 1'!D42,-3) -> 0 | C11: =ROUND('Workings for PL BS 1'!E42,-3) -> 0 | D11: =ROUND('Workings for PL BS 1'!F42,-3) -> 0 | E11: =ROUND('Workings for PL BS 1'!G42,-3) -> 0 | F11: =ROUND('Workings for PL BS 1'!H42,-3) -> 0 | G11: =ROUND('Workings for PL BS 1'!I42,-3) -> 0 | H11: =ROUND('Workings for PL BS 1'!J42,-3) -> 0 | I11: =ROUND('Workings for PL BS 1'!K42,-3) -> 0
A12: Selling and Distribution Expenses (Editable) | B12: =ROUND('Workings for PL BS 1'!D43,-3) -> 0 | C12: =ROUND('Workings for PL BS 1'!E43,-3) -> 0 | D12: =ROUND('Workings for PL BS 1'!F43,-3) -> 0 | E12: =ROUND('Workings for PL BS 1'!G43,-3) -> 0 | F12: =ROUND('Workings for PL BS 1'!H43,-3) -> 0 | G12: =ROUND('Workings for PL BS 1'!I43,-3) -> 0 | H12: =ROUND('Workings for PL BS 1'!J43,-3) -> 0 | I12: =ROUND('Workings for PL BS 1'!K43,-3) -> 0
A13: General Overheads (Editable) | B13: =ROUND('Workings for PL BS 1'!D44,-3) -> 0 | C13: =ROUND('Workings for PL BS 1'!E44,-3) -> 0 | D13: =ROUND('Workings for PL BS 1'!F44,-3) -> 0 | E13: =ROUND('Workings for PL BS 1'!G44,-3) -> 0 | F13: =ROUND('Workings for PL BS 1'!H44,-3) -> 0 | G13: =ROUND('Workings for PL BS 1'!I44,-3) -> 0 | H13: =ROUND('Workings for PL BS 1'!J44,-3) -> 0 | I13: =ROUND('Workings for PL BS 1'!K44,-3) -> 0
A14: Miscellaneous Expenses | B14: =ROUND('Workings for PL BS 1'!D45,-3) -> 0 | C14: =ROUND('Workings for PL BS 1'!E45,-3) -> 0 | D14: =ROUND('Workings for PL BS 1'!F45,-3) -> 0 | E14: =ROUND('Workings for PL BS 1'!G45,-3) -> 0 | F14: =ROUND('Workings for PL BS 1'!H45,-3) -> 0 | G14: =ROUND('Workings for PL BS 1'!I45,-3) -> 0 | H14: =ROUND('Workings for PL BS 1'!J45,-3) -> 0 | I14: =ROUND('Workings for PL BS 1'!K45,-3) -> 0
A15: Earnings before Tax (Not Editable since Autogenerated & Visible to customer) | B15: ='PL BS'!D41 -> 5.3539283e+09 | C15: ='PL BS'!E41 -> 7.7095517e+09 | D15: ='PL BS'!F41 -> 8726347500 | E15: ='PL BS'!G41 -> 9.6948881e+09 | F15: ='PL BS'!H41 -> 1.0630007e+10 | G15: ='PL BS'!I41 -> 1.1439413e+10 | H15: ='PL BS'!J41 -> 1.2214245e+10 | I15: ='PL BS'!K41 -> 1.2977818e+10
A16: BALANCE SHEET Items at a Glance:
A17: Net Capital Inluding Net Reserves and Surplus (Opening capital + Net Profit - Drawings) (Autogenerated , Not Editable) | B17: ='PL BS'!D54 -> 7987280000 | C17: ='PL BS'!E54 -> 1.3059807e+10 | D17: ='PL BS'!F54 -> 3.4293309e+10 | E17: ='PL BS'!G54 -> 4.0199487e+10 | F17: ='PL BS'!H54 -> 4.6546557e+10 | G17: ='PL BS'!I54 -> #VALUE! | H17: ='PL BS'!J54 -> #VALUE! | I17: ='PL BS'!K54 -> 6.5576564e+10
A18: Closing Cash and Cash Equivalents (Editable) | B18: =ROUND(IF(Assumptions!I62=0,0,'Workings for PL BS 1'!D37),-4) -> 4680810000 | C18: =ROUND(IF(Assumptions!I63=0,0,'Workings for PL BS 1'!E37),-4) -> -1971930000 | D18: =ROUND('Workings for PL BS 1'!F37,-4) -> 13872560000 | E18: =ROUND('Workings for PL BS 1'!G37,-4) -> 17792610000 | F18: =ROUND('Workings for PL BS 1'!H37,-4) -> 22002890000 | G18: =ROUND('Workings for PL BS 1'!I37,-4) -> 27012990000 | H18: =ROUND('Workings for PL BS 1'!J37,-4) -> 32354680000 | I18: =ROUND('Workings for PL BS 1'!K37,-4) -> 37476810000
A19: Recievables / Debtors (Editable) | B19: =ROUND(IF(Assumptions!I62=0,0,'Workings for PL BS 1'!D36),-4) -> 2478070000 | C19: =ROUND(IF(Assumptions!I63=0,0,'Workings for PL BS 1'!E36),-4) -> -857360000 | D19: =ROUND('Workings for PL BS 1'!F36,-4) -> 4922520000 | E19: =ROUND('Workings for PL BS 1'!G36,-4) -> 5618720000 | F19: =ROUND('Workings for PL BS 1'!H36,-4) -> 6356390000 | G19: =ROUND('Workings for PL BS 1'!I36,-4) -> 7135510000 | H19: =ROUND('Workings for PL BS 1'!J36,-4) -> 7956070000 | I19: =ROUND('Workings for PL BS 1'!K36,-4) -> 8818070000
A20: Non Current Assets (Editable) | B20: =ROUND('Workings for PL BS 1'!D34,-4) -> 0 | C20: =ROUND('Workings for PL BS 1'!E34,-4) -> 0 | D20: =ROUND('Workings for PL BS 1'!F34,-4) -> 0 | E20: =ROUND('Workings for PL BS 1'!G34,-4) -> 0 | F20: =ROUND('Workings for PL BS 1'!H34,-4) -> 0 | G20: =ROUND('Workings for PL BS 1'!I34,-4) -> 0 | H20: =ROUND('Workings for PL BS 1'!J34,-4) -> 0 | I20: =ROUND('Workings for PL BS 1'!K34,-4) -> 0
A21: CASH FLOW (Surplus / Deficiet) at a Glance:
A22: Net Surplus during the year (Not Editable but Displayed) | B22: =CFs!B45 -> 4680810000 | C22: =CFs!C45 -> -6652740000 | D22: =CFs!D45 -> 15844490000 | E22: =CFs!E45 -> 3.92005e+09 | F22: =CFs!F45 -> 4210280000 | G22: =CFs!G45 -> 5010100000 | H22: =CFs!H45 -> 5.34169e+09 | I22: =CFs!I45 -> 5.12213e+09
A24: MAXIMUM PERMISSABLE BANK FINANCE LIMIT:
A25: Method 1 - Working capital Method | B25: ='MPBF '!B28 -> 6241360000 | C25: ='MPBF '!C28 -> 40703032500 | D25: ='MPBF '!D28 -> 45000000000 | E25: ='MPBF '!E28 -> 45000000000 | F25: ='MPBF '!F28 -> 45000000000 | G25: ='MPBF '!G28 -> 45000000000 | H25: ='MPBF '!H28 -> 45000000000 | I25: ='MPBF '!I28 -> 45000000000
A26: Method 2 - Total Current Assets <ethod | B26: ='MPBF '!B53 -> 6241360000 | C26: ='MPBF '!C53 -> 4.0353033e+10 | D26: ='MPBF '!D53 -> 45000000000 | E26: ='MPBF '!E53 -> 45000000000 | F26: ='MPBF '!F53 -> 45000000000 | G26: ='MPBF '!G53 -> 45000000000 | H26: ='MPBF '!H53 -> 45000000000 | I26: ='MPBF '!I53 -> 45000000000
A27: Method 3 - Nayak Committee recommandaions | B27: =Nayak!B23 -> 5506830000 | C27: =Nayak!C23 -> -1714720000 | D27: =Nayak!D23 -> 8950036000 | E27: =Nayak!E23 -> 9364530000 | F27: =Nayak!F23 -> 9779060000 | G27: =Nayak!G23 -> 10193580000 | H27: =Nayak!H23 -> 10608092000 | I27: =Nayak!I23 -> 11022592000
A28: RATIO ANALYSIS at a Glance: (Auto generated and Not Editable but displayed to customer)
A29: Arrived DSCR | B29: =IF(B7=0,0,RATIO!C11) -> 1.7500002 | C29: =IF(C7=0,0,RATIO!D11) | D29: =RATIO!E11 -> 2.143313 | E29: =RATIO!F11 -> 2.2837842 | F29: =RATIO!G11 -> 2.6972292 | G29: =RATIO!H11 -> 3.169084 | H29: =RATIO!I11 -> 3.2847088 | I29: =RATIO!J11 -> 3.3990994
A30: Required DSCR Ratio | B30: =Assumptions!I76 -> 2.5
A31: Total Outside Liabilities to Total Networth | B31: =RATIO!C77 -> 1.55556 | C31: =RATIO!D77 -> 3.6929837 | D31: =RATIO!E77 -> 1.410868 | E31: =RATIO!F77 -> 1.1687545 | F31: =RATIO!G77 -> 0.97930622 | G31: =RATIO!H77 -> #VALUE! | H31: =RATIO!I77 -> #VALUE! | I31: =RATIO!J77 -> 0.68622077
A32: Gross Profit Ratio | B32: =IF(B7=0,0,RATIO!C46) -> 43.478262 | C32: =IF(C7=0,0,RATIO!D46) -> -176.58661 | D32: =RATIO!E46 -> 35.457533 | E32: =RATIO!F46 -> 35.441651 | F32: =RATIO!G46 -> 35.427168 | G32: =RATIO!H46 -> 35.413878 | H32: =RATIO!I46 -> 35.40171 | I32: =RATIO!J46 -> 35.39046
A33: Net profit ratio | B33: =IF(B7=0,0,RATIO!C54) -> 19.444684 | C33: =IF(C7=0,0,RATIO!D54) -> -89.921989 | D33: =RATIO!E54 -> 19.500139 | E33: =RATIO!F54 -> 20.705552 | F33: =RATIO!G54 -> 21.740345 | G33: =RATIO!H54 -> 22.444348 | H33: =RATIO!I54 -> 23.028165 | I33: =RATIO!J54 -> 23.547669
A34: Current Ratio | B34: =RATIO!C34 -> 1.8097093 | C34: =RATIO!D34 -> 1.2413663 | D34: =RATIO!E34 -> 1.67845 | E34: =RATIO!F34 -> 1.8181002 | F34: =RATIO!G34 -> 1.9695976 | G34: =RATIO!H34 -> 2.1116407 | H34: =RATIO!I34 -> 2.2621076 | I34: =RATIO!J34 -> 2.4087513
A35: Debtors / Recievables Turnover Ratio (Days) | B35: =IF(B7=0,0,RATIO!C68) -> 32.849954 | C35: =IF(C7=0,0,RATIO!D68) -> 36.5 | D35: =RATIO!E68 -> 40.150002 | E35: =RATIO!F68 -> 43.800016 | F35: =RATIO!G68 -> 47.450007 | G35: =RATIO!H68 -> 51.100029 | H35: =RATIO!I68 -> 54.750007 | I35: =RATIO!J68 -> 58.399976

Sheet Cover page
D6: DETAILED PROJECT REPORT
D8: OF
D10: =Assumptions!I17 -> Doe Textiles
D12: =Assumptions!I8 -> John Doe
D15: Line of Activity : | G15: =Assumptions!I15 -> Textile Manufacturing
D20: UNIT ADDRESS :
D21: =Assumptions!I16 -> 123 Industrial Area, City
D25: REQUIREMENT:
D27: Equity Capital (Margin) | H27: =Assumptions!I55 -> 62000 | I27: Lacs
D28: Term Loan | H28: =Assumptions!I43 -> 63000 | I28: Lacs
D29: Working Capital Loan | H29: =Assumptions!I51 -> 450000 | I29: =I28 -> Lacs
D30: Total Project cost | H30: =Assumptions!I56 -> 575000 | I30: Lacs
D33: PREPARED BY
D35: FINVOIS OPEN BUSINESS SOLUTIONS LLP
D36: MSME & DPR Consultants
D37: Contact No : 9618221011

Sheet Index
C5: INDEX
D7: 1 | E7: PROJECT PROFILE OVERVIEW
D9: 2 | E9: FIRM CONSTITUTION , PROPRIETOR PROFILE & BACKGROUND
D11: 3 | E11: INTRODUCTION AND FEATURES OF RAW MATERIAL AND FINISHED PRODUCT, DEMAND SUPPLY AND ITS MARKETABILITY, SWOT ANALYSIS,STATUTORY GOVERNMENT APPROVALS,POWER REQUIREMENTS.
D15: 3 | E15: PROJECT COST AND MEANS OF FINANCE
D17: 4 | E17: PROJECTED PROFIT AND LOSS ACCOUNT & BALANCE SHEET
D19: 5 | E19: RATIO ANALYSIS
D21: 6 | E21: DEPRECIATION SCHEDULE
D23: 7 | E23: TERM LOAN SCHEDULE
D25: 8 | E25: CALCULATION OF MAXIMUM PERMISSABLE BANK FINANCE LIMIT
F26: a) Method 1 - Working Capital Method
F27: b) Method 2 - Total Current Assets Method
F28: c) Method 3 - Nayak Committee Recommandation Method
D30: 9 | E30: PRINCIPAL REPAYMENT SCHEDULE
D32: 10 | E32: CASH FLOW STATEMENT
D34: 11 | E34: FUNDS FLOW STATEMENT
D36: 12 | E36: INTERNAL RATE OF RETURN (IRR)
D38: 13 | E38: MODIFIED INTERNAL RATE OF RETURN (MIRR)
D40: 14 | E40: WEIGHTED AVERAGE COST OF CAPITAL (WACC)
D42: 14 | E42: PROFITABILITY INDEX (PI)
D44: 15 | E44: NET PRESENT VALUE (NPV)
D46: 16 | E46: INVESTMENT PAYBACK PERIOD - SIMPLE METHOD & DISCOUNTED CASHFLOW METHOD
D48: 17 | E48: SENSITIVITY ANALYSIS
D50: 18 | E50: BREAK EVEN POINT (BEP) & MARGIN OF SAFETY (MOS)
D52: 19 | E52: ALTMAN Z SCORE

Sheet profile
A2: =Assumptions!I17 -> Doe Textiles
A3: =Assumptions!I8 -> John Doe
A4: =Assumptions!I16 -> 123 Industrial Area, City
A6: PROJECT PROFILE AT A GLANCE
A7: =[1]Coverpage!C9 -> Firm Name : | C7: =A2 -> Doe Textiles
A9: Name of the proprietor | B9: : | C9: =A3 -> John Doe
A11: Address Unit | B11: : | C11: =A4 -> 123 Industrial Area, City
A13: Location of Unit | C13: =Assumptions!I22 -> Urban
A15: Manufacturing / Service / Trading Concern | B15: : | C15: =Assumptions!I14 -> Manufacturing sector
A17: =[1]Coverpage!C18 -> Line of Activity : | B17: : | C17: =Assumptions!I15 -> Textile Manufacturing
A19: Constitution | B19: : | C19: =Assumptions!I7 -> Sole Proprietorship
A21: Average DSCR | B21: : | C21: =Assumptions!I76 -> 2.5
A23: =Assumptions!B24 -> Expected Employment Generation :
A24: =Assumptions!C24 -> Skilled employees | B24: : | C24: =Assumptions!I24 -> 5
A25: =Assumptions!C25 -> Semi Skilled Employees | B25: : | C25: =Assumptions!I25 -> 3
A26: =Assumptions!C26 -> Unskiled Employees | B26: : | C26: =Assumptions!I26 -> 2
A28: Gender | B28: : | C28: =Assumptions!I13 -> Male
A30: Age of Proprietor | B30: : | C30: =Assumptions!I12 -> 35
A32: Caste | B32: : | C32: =Assumptions!I21 -> OC
A34: Pan No | B34: : | C34: =Assumptions!I11 -> ABCDE1234F
A36: Adhar No | B36: : | C36: =Assumptions!I10 -> 123456789012
A38: Mobile No | B38: : | C38: =Assumptions!I9 -> 9876543210
A40: REQUIREMENT:
A42: Term Loan | B42: : | C42: =Assumptions!I43 -> 63000 | D42: ='[2]cover page'!H30 -> Lacs
A44: =[1]Coverpage!C31 -> Capital | B44: : | C44: =Assumptions!I55 -> 62000 | D44: ='[2]cover page'!H32 -> Lacs
A46: =[1]Coverpage!C32 -> Total Project cost | B46: : | C46: =Assumptions!I41 -> 575000 | D46: ='[2]cover page'!H33 -> Lacs
A50: DISCLAIMER :
A52: The views expressed in this Project Report are advisory in nature. We assume no
A53: financial liability to anyone using the content for any purpose. All the materials
A54: and content contained in Project report is for educational purpose and reflect the
A55: views of the industry which are drawn from various research material sources from
A56: internet, experts, suppliers and various other sources. The actual cost of the
A57: project or industry will have to be taken on case to case basis considering
A58: specific requirement of the project, capacity and type of plant and other specific
A59: factors/cost directly related to the implementation of project. It is intended for
A60: general guidance only and must not be considered a substitute for a competent
A61: legal advice provided by a licensed industry professional. We hereby disclaims
A62: any and all liability to any party for any direct, indirect, implied, punitive, special,
... A64: use of the Project Report Content, which is provided as is, and without warranties.

Sheet Descriptive
B2: From the above project data/profile available ,Please prepare the following
B4: √ | C4: The Constitution of the firm | F4: Must read from "profile" sheet
B5: √ | C5: Proprietors/Partners background and experience | F5: Manually enter the description | G5: (Ex:Residential address details , Previous work experience,personal Networth, etc)
B6: √ | C6: Education back ground of each partner
C8: DETAILS OF PRODUCT MANUFACTURED / FINISHED PRODUCT:
B9: √ | C9: Introduction of product being manufactured / Service | F9: Manually enter the description | G9: (Main component of Product Manufactured / Service provided) Ex:Manufacturing of food Products
F10: Manually enter the description | G10: (Sub Component) Ex: Manufacturing of Chilly powder
B11: √ | C11: Key charecteristics of product manufactured / Service
B12: √ | C12: Manufacturing capacity of the product | F12: Manually enter the description | G12: (Ex : 80 tonnes per hour/day/month)
B13: √ | C13: Flowchart of product manufactured
B14: √ | C14: SWOT Analysis of product/Service
B15: √ | C15: Competitors data
B16: √ | C16: Market trend for this product/Service
B17: √ | C17: Statutory government approvals
B18: √ | C18: Marketing Techniques applied
D19: √ | E19: Have previous experience in the same line of business
F20: Manual Enter the description | G20: Share past experience details if any (Ex: Company name ,designation,experience in years), previous successful projects done etc
D21: √ | E21: Have Purchase orders
F22: Manual Enter the description | G22: Share PO details (Ex: Purchaser details,Monthly Quantity etc)
D23: √ | E23: Will market the products through Marketing team
D24: √ | E24: Other Marketing technique
F25: Manual Enter the description | G25: (Ex: Will Market product through Marketing team or Retail stores or Wholesalers etc)
B26: √ | C26: Targeted Customers/Audience
D27: Manual Enter the description | F27: (Ex: food processing units , farmers etc)
C31: RAW MATERIALS DETAILS:( Applicable to only manufacturing units)
B32: √ | C32: Following Raw Materials required | G32: Manually enter the description | I32: (Ex:Fruits , Vegetables , wood etc)
B33: √ | C33: Quanity required | G33: Manually enter the description | I33: (Ex : 100 tonnes per day/month)
B34: √ | C34: Description regarding the Raw Materials , Demand , supply , availability nearer to your unit.
B35: √ | C35: Raw Material suppliers details | G35: Manually enter the description | I35: (Share details like Name of supplier,place of purchase etc)
B38: √ | C38: PRODUCTION CAPACITY
C39: S.No | E39: Product Name | F39: Production capacity per Annum (Specify the capacity along with units of measurement)
C40: 1 | E40: Ex:U Bolts - 20MM to 300MM | F40: (Ex:10-15Tonnes per year)
C41: 2 | E41: Ex:U Clamps - 20MM to 300MM | F41: (Ex:5-7 Tonnes per year)
C42: 3 | E42: Ex:Anchor Fastners - 8MM to 20MM
B44: √ | C44: INVENTORY / STOCK DETAILS
C45: S.No | E45: Type of Material | F45: Quanitity to be manufactured per month | G45: Quanitity to be Stored per month | H45: No of Days of Stock | I45: Justification,if any
C46: 1 | E46: Raw material | F46: (Ex:10-15Tonnes per year)
C47: 2 | E47: Finished product | F47: (Ex:5-7 Tonnes per year)
C48: 3 | E48: Ex:Anchor Fastners - 8MM to 20MM
B51: √ | C51: MANPOWER:
E53: Sl.No | F53: Employment | G53: Category of Employment | H53: No.of Employees | I53: Salary per month per employee | J53: Total Salary per Month
E54: 1 | F54: Skilled | G54: a.(Ex:Managerial Staff)
G55: b.(Ex:Engineering Staff)
G56: c.(Ex:Technical Staff)
G57: d.(Ex:Administrative Staff)
G58: e.
G59: Total
E60: 2 | F60: Semi Skilled | G60: a.
G61: b.
G62: c.
G63: d.
G64: Total
E65: 3 | F65: Unskilled | G65: a.
G66: b.
G67: c.
G68: d.
G69: Total
E71: Sl.No | F71: Employment | G71: No.of Employees
E72: 1 | F72: Direct | G72: =H69+H64+H59 -> 0
E73: 2 | F73: Indirect
F74: Total | G74: =SUM(G72:G73) -> 0
C77: Most of which are from rural area. Thus, it fulfills the Government motto and interest in rural employment generation.
C78: There are skilled and semiskilled workers available in the surrounding area, so there is no problem in getting the manpower for the unit.
C79: The promoters have already gathered required number of skilled workers who are experienced in the same line of activity.
B82: √ | C82: IMPLEMENTATION TIMELINE OF THE PROJECT
E83: Sl.no | F83: Description | G83: Time Line
G84: Start Date | H84: End Date
E85: 1 | F85: Construction
E86: 2 | F86: Machinery/Equipment Erection
E87: 3 | F87: Machinery/Equipment Trail Run
E88: 4 | F88: Commercial Run start date
B90: √ | C90: LAND REQUIREMENT DETAILS FOR THE PROJECT:
D91: √ | E91: Land required for Plant and factory building | H91: Sq meters/Sq Feet/Sq Yards
D92: √ | E92: Land required for Administrative building | H92: Sq meters/Sq Feet/Sq Yards
D93: √ | E93: Land required for storage and warehousing | H93: Sq meters/Sq Feet/Sq Yards
D94: √ | E94: Land required for Internal roads,water storage,sub station etc. | H94: Sq meters/Sq Feet/Sq Yards
D95: √ | E95: Land required for Open areas and greenery | H95: Sq meters/Sq Feet/Sq Yards
B99: √ | C99: PLANT AND MACHINERY / EQUIPMENT DETAILS:
D100: √ | E100: Supplier Quotations taken ?
F101: Manual Enter the description | G101: (Enter Supplier complete details)
D103: √ | E103: Indegeneous Machinery
D104: √ | E104: Imported Machinery
B107: √ | C107: Due Diligence Verification Report of Applicants Residential and Office Address
E109: Browse Residential address pics of Applicant
E110: Browse Office/Factory/Unit address pics of Applicant
B113: √ | C113: DO YOU WISH TO MAKE ANY ATTACHMENTS TO YOUR PROJECT REPORT
D114: √ | E114: KYC details of proprietor/partners
D115: √ | E115: KYC of Company (GST RC,other licences,Certificate of incorporation/AOA/MOA etc)
D116: √ | E116: Machinery Quotations , if any | H116: Here for making attachments Browse option to be provided
D117: √ | E117: Other attachments if any (Plan copy,Pollution certificate etc)

Sheet project cost
A1: =Assumptions!I17 -> Doe Textiles
A2: =Assumptions!I8 -> John Doe
A3: =Assumptions!I16 -> 123 Industrial Area, City
A6: PROJECT COST AND MEANS OF FINANCE
A8: Nature of Business : | B8: =Assumptions!I15 -> Textile Manufacturing
A11: A. COST OF THE PROJECT
C12: Rs in Lakhs
A13: Particulars | C13: Amount
A15: =Assumptions!C29 -> Service Equipment | C15: =Assumptions!I28 -> 70000
A17: =Assumptions!C40 -> Working capital Requirement | C17: =Assumptions!I40 -> 500000
A20: Total | C20: =SUM(C15:C19) -> 570000
A23: B. MEANS OF FINANCE
C24: =C12 -> Rs in Lakhs
A25: Particulars | C25: Amount
A27: Equity Capital (Margin) | C27: =C34-C31-C29 -> 57000
A29: Term Loan | C29: =Assumptions!I43 -> 63000
A31: Working capital Loan | C31: =Assumptions!I51 -> 450000
A34: Total | C34: =C20 -> 570000

Sheet PL BS
A1: =Assumptions!I17 -> Doe Textiles
A2: =Assumptions!I8 -> John Doe
A3: =Assumptions!I16 -> 123 Industrial Area, City
A5: PROFIT & LOSS ACCOUNT FOR YEAR ENDED
A6: PARTICULARS | B6: Sch | D6: =Assumptions!J78 -> Estimated | E6: =Assumptions!J79 -> Projected | F6: =Assumptions!J80 -> Projected | G6: =Assumptions!J81 -> Projected | H6: =Assumptions!J82 -> Projected | I6: =Assumptions!J83 -> Projected | J6: =Assumptions!J84 -> Projected | K6: =Assumptions!J85 -> Projected
D7: =Assumptions!I78 -> 2024-25 | E7: =Assumptions!I79 -> 2025-26 | F7: =Assumptions!I80 -> 2026-27 | G7: =Assumptions!I81 -> 2027-28 | H7: =Assumptions!I82 -> 2028-29 | I7: =Assumptions!I83 -> 2029-30 | J7: =Assumptions!I84 -> 2030-31 | K7: =Assumptions!I85 -> 2031-32
A9: Gross reciepts
A14: Gross Revenue | D14: ='Final workings'!B7 -> 27534150000 | E14: ='Final workings'!C7 -> -8573600000 | F14: ='Final workings'!D7 -> 44750180000 | G14: ='Final workings'!E7 -> 46822650000 | H14: ='Final workings'!F7 -> 48895300000 | I14: ='Final workings'!G7 -> 50967900000 | J14: ='Final workings'!H7 -> 53040460000 | K14: ='Final workings'!I7 -> 55112960000
A16: Opening Stock | D16: 0 | E16: =D18 -> #REF! | F16: =E18 -> #REF! | G16: =F18 -> #REF! | H16: =G18 -> #REF! | I16: =H18 -> #REF! | J16: =I18 -> #REF! | K16: =J18 -> #REF!
A17: Direct expenses | D17: =D11*Assumptions!#REF! -> #REF! | E17: =E11*Assumptions!#REF! -> #REF! | F17: =F11*Assumptions!#REF! -> #REF! | G17: =G11*Assumptions!#REF! -> #REF! | H17: =H11*Assumptions!#REF! -> #REF! | I17: =I11*Assumptions!#REF! -> #REF! | J17: =J11*Assumptions!#REF! -> #REF! | K17: =J17*Assumptions!#REF! -> #REF!
A18: Closing Stock | D18: =Assumptions!#REF!*D11 -> #REF! | E18: =Assumptions!#REF!*E11 -> #REF! | F18: =Assumptions!#REF!*F11 -> #REF! | G18: =Assumptions!#REF!*G11 -> #REF! | H18: =Assumptions!#REF!*H11 -> #REF! | I18: =Assumptions!#REF!*I11 -> #REF! | J18: =Assumptions!#REF!*J11 -> #REF! | K18: =Assumptions!#REF!*K11 -> #REF!
A19: Less : Cost of Goods Sold / Direct Costs
A21: Opening Stock | D21: =Assumptions!F124 -> 0 | E21: =D25 -> 6669760000 | F21: =E25 -> 58500000000 | G21: =F25 -> 59085000000 | H21: =G25 -> 59675850000 | I21: =H25 -> 60272610000 | J21: =I25 -> 60875330000 | K21: =J25 -> 61484090000
A23: Direct Material/Expenses | D23: ='Final workings'!B8 -> 22232540000 | E23: ='Final workings'!C8 -> 28116810000 | F23: ='Final workings'!D8 -> 29467870000 | G23: ='Final workings'!E8 -> 30818780000 | H23: ='Final workings'!F8 -> 32169840000 | I23: ='Final workings'!G8 -> 33520910000 | J23: ='Final workings'!H8 -> 34871990000 | K23: ='Final workings'!I8 -> 36223070000
A25: Closing stock / WIP | D25: ='Final workings'!B9 -> 6669760000 | E25: ='Final workings'!C9 -> 58500000000 | F25: ='Final workings'!D9 -> 59085000000 | G25: ='Final workings'!E9 -> 59675850000 | H25: ='Final workings'!F9 -> 60272610000 | I25: ='Final workings'!G9 -> 60875330000 | J25: ='Final workings'!H9 -> 61484090000 | K25: ='Final workings'!I9 -> 62098930000
A27: Cost of Goods Sold / Direct Costs | D27: =D21+D23-D25 -> 15562780000 | E27: =E21+E23-E25 -> -23713430000 | F27: =F21+F23-F25 -> 28882870000 | G27: =G21+G23-G25 -> 30227930000 | H27: =H21+H23-H25 -> 31573080000 | I27: =I21+I23-I25 -> 32918190000 | J27: =J21+J23-J25 -> 34263230000 | K27: =K21+K23-K25 -> 35608230000
A29: Gross profit | D29: =D14-D27 -> 11971370000 | E29: =E14-E27 -> 15139830000 | F29: =F14-F27 -> 15867310000 | G29: =G14-G27 -> 16594720000 | H29: =H14-H27 -> 17322220000 | I29: =I14-I27 -> 18049710000 | J29: =J14-J27 -> 18777230000 | K29: =K14-K27 -> 19504730000
A31: Less: Indirect Expenses | B31: Sch 1 | D31: =D106 -> 606650000 | E31: =E106 -> 591570000 | F31: =F106 -> 591650000 | G31: =G106 -> 591650000 | H31: =H106 -> 591730000 | I31: =I106 -> 591820000 | J31: =J106 -> 591910000 | K31: =K106 -> 592010000
A33: EBDIT | D33: =D29-D31 -> 11364720000 | E33: =E29-E31 -> 14548260000 | F33: =F29-F31 -> 15275660000 | G33: =G29-G31 -> 16003070000 | H33: =H29-H31 -> 16730490000 | I33: =I29-I31 -> 17457890000 | J33: =J29-J31 -> 18185320000 | K33: =K29-K31 -> 18912720000
A35: Less : Depreciation | D35: ='Dep IT act'!M17*100000 -> 9.1666667e+08 | E35: ='Dep IT act'!M24*100000 -> 9.6458333e+08 | F35: ='Dep IT act'!M31*100000 -> 822187500 | G35: ='Dep IT act'!M38*100000 -> 700921875 | H35: ='Dep IT act'!M45*100000 -> 5.9763984e+08 | I35: ='Dep IT act'!M52*100000 -> 5.0966449e+08 | J35: ='Dep IT act'!M59*100000 -> 4.3471838e+08 | K35: ='Dep IT act'!M66*100000 -> 3.7086383e+08
A37: EBIT | D37: =D33-D35 -> 1.0448053e+10 | E37: =E33-E35 -> 1.3583677e+10 | F37: =F33-F35 -> 14453472500 | G37: =G33-G35 -> 15302148125 | H37: =H33-H35 -> 1.613285e+10 | I37: =I33-I35 -> 1.6948226e+10 | J37: =J33-J35 -> 1.7750602e+10 | K37: =K33-K35 -> 1.8541856e+10
A39: Less: Interest | B39: Sch 2 | D39: =D119 -> 5094125000 | E39: =E119 -> 5.874125e+09 | F39: =F119 -> 5.727125e+09 | G39: =G119 -> 5.60726e+09 | H39: =H119 -> 5.5028432e+09 | I39: =I119 -> 5.5088127e+09 | J39: =J119 -> 5.5363568e+09 | K39: =K119 -> 5.5640386e+09
A41: Earnings before Tax (EBT) | D41: =D37-D39 -> 5.3539283e+09 | E41: =E37-E39 -> 7.7095517e+09 | F41: =F37-F39 -> 8726347500 | G41: =G37-G39 -> 9.6948881e+09 | H41: =H37-H39 -> 1.0630007e+10 | I41: =I37-I39 -> 1.1439413e+10 | J41: =J37-J39 -> 1.2214245e+10 | K41: =K37-K39 -> 1.2977818e+10
A45: =Assumptions!I17 -> Doe Textiles
A46: =Assumptions!I8 -> John Doe
A47: =Assumptions!I16 -> 123 Industrial Area, City
A49: BALANCE SHEET AS ON
A50: Particulars | B50: =B6 -> Sch | D50: =Assumptions!J78 -> Estimated | E50: =Assumptions!J79 -> Projected | F50: =Assumptions!J80 -> Projected | G50: =Assumptions!J81 -> Projected | H50: =Assumptions!J82 -> Projected | I50: =Assumptions!J83 -> Projected | J50: =Assumptions!J84 -> Projected | K50: =Assumptions!J85 -> Projected
D51: =Assumptions!I78 -> 2024-25 | E51: =Assumptions!I79 -> 2025-26 | F51: =Assumptions!I80 -> 2026-27 | G51: =Assumptions!I81 -> 2027-28 | H51: =Assumptions!I82 -> 2028-29 | I51: =Assumptions!I83 -> 2029-30 | J51: =Assumptions!I84 -> 2030-31 | K51: =Assumptions!I85 -> 2031-32
A52: SOURCES OF FUNDS:
A54: Net Capital Including Net Reserves and Surplus | D54: =D66-SUM(D57:D65) -> 7987280000 | E54: =E66-SUM(E57:E65) -> 1.3059807e+10 | F54: =F66-SUM(F57:F65) -> 3.4293309e+10 | G54: =G66-SUM(G57:G65) -> 4.0199487e+10 | H54: =H66-SUM(H57:H65) -> 4.6546557e+10 | I54: =I66-SUM(I57:I65) -> #VALUE! | J54: =J66-SUM(J57:J65) -> #VALUE! | K54: =K66-SUM(K57:K65) -> 6.5576564e+10
A56: (Opening capital + Net profit - Drawings)
A58: TERM LOANS : | D58: ='WorKings for PL BS 2'!B14 -> 4.7833333e+09 | E58: ='WorKings for PL BS 2'!C14 -> 3.3833333e+09 | F58: ='WorKings for PL BS 2'!D14 -> 1.9833333e+09 | G58: ='WorKings for PL BS 2'!E14 -> 1.2833333e+09 | H58: ='WorKings for PL BS 2'!F14 -> 5.8333333e+08 | I58: ='WorKings for PL BS 2'!G14 -> #VALUE! | J58: ='WorKings for PL BS 2'!H14 -> #VALUE! | K58: ='WorKings for PL BS 2'!I14 -> 0
A60: CURRENT LIABILITIES :
A62: ='project cost'!A31 -> Working capital Loan | D62: ='Workings for PL BS 1'!D72 -> 6241360000 | E62: ='Workings for PL BS 1'!E72 -> 43446320000 | F62: ='WorKings for PL BS 2'!D15 -> 45000000000 | G62: ='WorKings for PL BS 2'!E15 -> 45000000000 | H62: ='WorKings for PL BS 2'!F15 -> 45000000000 | I62: ='WorKings for PL BS 2'!G15 -> 45000000000 | J62: ='WorKings for PL BS 2'!H15 -> 45000000000 | K62: ='WorKings for PL BS 2'!I15 -> 45000000000
A64: Short Term Loan | D64: ='WorKings for PL BS 2'!B13 -> 1400000000 | E64: ='WorKings for PL BS 2'!C13 -> 1400000000 | F64: ='WorKings for PL BS 2'!D13 -> 1400000000 | G64: ='WorKings for PL BS 2'!E13 -> 700000000 | H64: ='WorKings for PL BS 2'!F13 -> 0 | I64: ='WorKings for PL BS 2'!G13 -> 0 | J64: ='WorKings for PL BS 2'!H13 -> 0 | K64: ='WorKings for PL BS 2'!I13 -> 0
D66: =D82 -> 2.0411973e+10 | E66: =E82 -> 61289460000 | F66: =F82 -> 82676642500 | G66: =G82 -> 87182820625 | H66: =H82 -> 9.2129891e+10 | I66: =I82 -> 9.8012166e+10 | J66: =J82 -> 1.0434846e+11 | K66: =K82 -> 1.1057656e+11
A68: APPLICATION OF FUNDS:
A70: FIXED ASSETS: | D70: ='WorKings for PL BS 2'!B22 -> 6.5833333e+09 | E70: ='WorKings for PL BS 2'!C22 -> 5618750000 | F70: ='WorKings for PL BS 2'!D22 -> 4796562500 | G70: ='WorKings for PL BS 2'!E22 -> 4095640625 | H70: ='WorKings for PL BS 2'!F22 -> 3.4980008e+09 | I70: ='WorKings for PL BS 2'!G22 -> 2.9883363e+09 | J70: ='WorKings for PL BS 2'!H22 -> 2.5536179e+09 | K70: ='WorKings for PL BS 2'!I22 -> 2.1827541e+09
A72: =IF('Final workings'!B20=0,"",NON CURRENT ASSETS) | D72: =IF('Final workings'!B20=0,"",'Final workings'!B20) | E72: =IF('Final workings'!C20=0,"",'Final workings'!C20) | F72: =IF('Final workings'!D20=0,"",'Final workings'!D20) | G72: =IF('Final workings'!E20=0,"",'Final workings'!E20) | H72: =IF('Final workings'!F20=0,"",'Final workings'!F20) | I72: =IF('Final workings'!G20=0,"",'Final workings'!G20) | J72: =IF('Final workings'!H20=0,"",'Final workings'!H20) | K72: =IF('Final workings'!I20=0,"",'Final workings'!I20)
A74: CURRENT ASSETS :
A76: =A25 -> Closing stock / WIP | D76: ='Final workings'!B9 -> 6669760000 | E76: ='Final workings'!C9 -> 58500000000 | F76: ='Final workings'!D9 -> 59085000000 | G76: ='Final workings'!E9 -> 59675850000 | H76: ='Final workings'!F9 -> 60272610000 | I76: ='Final workings'!G9 -> 60875330000 | J76: ='Final workings'!H9 -> 61484090000 | K76: ='Final workings'!I9 -> 62098930000
A78: Recievables / Debtors | D78: ='Final workings'!B19 -> 2478070000 | E78: ='Final workings'!C19 -> -857360000 | F78: ='Final workings'!D19 -> 4922520000 | G78: ='Final workings'!E19 -> 5618720000 | H78: ='Final workings'!F19 -> 6356390000 | I78: ='Final workings'!G19 -> 7135510000 | J78: ='Final workings'!H19 -> 7956070000 | K78: ='Final workings'!I19 -> 8818070000
A80: Cash and Cash Equivalents | D80: ='Final workings'!B18 -> 4680810000 | E80: ='Final workings'!C18 -> -1971930000 | F80: ='Final workings'!D18 -> 13872560000 | G80: ='Final workings'!E18 -> 17792610000 | H80: ='Final workings'!F18 -> 22002890000 | I80: ='Final workings'!G18 -> 27012990000 | J80: ='Final workings'!H18 -> 32354680000 | K80: ='Final workings'!I18 -> 37476810000
D82: =SUM(D70:D81) -> 2.0411973e+10 | E82: =SUM(E70:E81) -> 61289460000 | F82: =SUM(F70:F81) -> 82676642500 | G82: =SUM(G70:G81) -> 87182820625 | H82: =SUM(H70:H81) -> 9.2129891e+10 | I82: =SUM(I70:I81) -> 9.8012166e+10 | J82: =SUM(J70:J81) -> 1.0434846e+11 | K82: =SUM(K70:K81) -> 1.1057656e+11
A89: Schedule 1 - Indirect Expenses
A90: Particulars | D90: =Assumptions!I78 -> 2024-25 | E90: =Assumptions!I79 -> 2025-26 | F90: =Assumptions!I80 -> 2026-27 | G90: =Assumptions!I81 -> 2027-28 | H90: =Assumptions!I82 -> 2028-29 | I90: =Assumptions!I83 -> 2029-30 | J90: =Assumptions!I84 -> 2030-31 | K90: =Assumptions!I85 -> 2031-32
A92: Processing fees | D92: ='Workings for PL BS 1'!D40 -> 605340000 | E92: ='Workings for PL BS 1'!E40 -> 590000000 | F92: ='Workings for PL BS 1'!F40 -> 590000000 | G92: ='Workings for PL BS 1'!G40 -> 590000000 | H92: ='Workings for PL BS 1'!H40 -> 590000000 | I92: ='Workings for PL BS 1'!I40 -> 590000000 | J92: ='Workings for PL BS 1'!J40 -> 590000000 | K92: ='Workings for PL BS 1'!K40 -> 590000000
A94: =IF('Final workings'!B10=0,"",'Workings for PL BS 1'!A41) -> Employee Related Expenses | D94: =IF('Final workings'!B10=0,"",'Final workings'!B10) -> 1310000 | E94: =IF('Final workings'!B10=0,"",'Final workings'!C10) -> 1570000 | F94: =IF('Final workings'!B10=0,"",'Final workings'!D10) -> 1650000 | G94: =IF('Final workings'!B10=0,"",'Final workings'!E10) -> 1650000 | H94: =IF('Final workings'!B10=0,"",'Final workings'!F10) -> 1730000 | I94: =IF('Final workings'!B10=0,"",'Final workings'!G10) -> 1820000 | J94: =IF('Final workings'!B10=0,"",'Final workings'!H10) -> 1910000 | K94: =IF('Final workings'!B10=0,"",'Final workings'!I10) -> 2010000
A96: =IF('Final workings'!B11=0,"",'Workings for PL BS 1'!A42) | D96: =IF('Final workings'!B11=0,"",'Final workings'!B11) | E96: =IF('Final workings'!B11=0,"",'Final workings'!C11) | F96: =IF('Final workings'!B11=0,"",'Final workings'!D11) | G96: =IF('Final workings'!B11=0,"",'Final workings'!E11) | H96: =IF('Final workings'!B11=0,"",'Final workings'!F11) | I96: =IF('Final workings'!B11=0,"",'Final workings'!G11) | J96: =IF('Final workings'!B11=0,"",'Final workings'!H11) | K96: =IF('Final workings'!B11=0,"",'Final workings'!I11)
A98: =IF('Final workings'!B12=0,"",'Workings for PL BS 1'!A43) | D98: =IF('Final workings'!B12=0,"",'Final workings'!B12) | E98: =IF('Final workings'!B12=0,"",'Final workings'!C12) | F98: =IF('Final workings'!B12=0,"",'Final workings'!D12) | G98: =IF('Final workings'!B12=0,"",'Final workings'!E12) | H98: =IF('Final workings'!B12=0,"",'Final workings'!F12) | I98: =IF('Final workings'!B12=0,"",'Final workings'!G12) | J98: =IF('Final workings'!B12=0,"",'Final workings'!H12) | K98: =IF('Final workings'!B12=0,"",'Final workings'!I12)
A100: =IF('Final workings'!B13=0,"",'Workings for PL BS 1'!A44) | D100: =IF('Final workings'!B13=0,"",'Final workings'!B13) | E100: =IF('Final workings'!B13=0,"",'Final workings'!C13) | F100: =IF('Final workings'!B13=0,"",'Final workings'!D13) | G100: =IF('Final workings'!B13=0,"",'Final workings'!E13) | H100: =IF('Final workings'!B13=0,"",'Final workings'!F13) | I100: =IF('Final workings'!B13=0,"",'Final workings'!G13) | J100: =IF('Final workings'!B13=0,"",'Final workings'!H13) | K100: =IF('Final workings'!B13=0,"",'Final workings'!I13)
A102: =IF('Final workings'!B14=0,"",'Workings for PL BS 1'!A45) | D102: =IF('Final workings'!B14=0,"",'Final workings'!B14) | E102: =IF('Final workings'!B14=0,"",'Final workings'!C14) | F102: =IF('Final workings'!B14=0,"",'Final workings'!D14) | G102: =IF('Final workings'!B14=0,"",'Final workings'!E14) | H102: =IF('Final workings'!B14=0,"",'Final workings'!F14) | I102: =IF('Final workings'!B14=0,"",'Final workings'!G14) | J102: =IF('Final workings'!B14=0,"",'Final workings'!H14) | K102: =IF('Final workings'!B14=0,"",'Final workings'!I14)
D106: =SUM(D91:D105) -> 606650000 | E106: =SUM(E91:E105) -> 591570000 | F106: =SUM(F91:F105) -> 591650000 | G106: =SUM(G91:G105) -> 591650000 | H106: =SUM(H91:H105) -> 591730000 | I106: =SUM(I91:I105) -> 591820000 | J106: =SUM(J91:J105) -> 591910000 | K106: =SUM(K91:K105) -> 592010000
A109: Schedule 2 - Interest Statement
A110: Particulars | D110: =Assumptions!I78 -> 2024-25 | E110: =Assumptions!I79 -> 2025-26 | F110: =Assumptions!I80 -> 2026-27 | G110: =Assumptions!I81 -> 2027-28 | H110: =Assumptions!I82 -> 2028-29 | I110: =Assumptions!I83 -> 2029-30 | J110: =Assumptions!I84 -> 2030-31 | K110: =Assumptions!I85 -> 2031-32
A113: Interest on Term Loan | D113: ='WorKings for PL BS 2'!B5 -> 5.94125e+08 | E113: ='WorKings for PL BS 2'!C5 -> 4.47125e+08 | F113: ='WorKings for PL BS 2'!D5 -> 3.00125e+08 | G113: ='WorKings for PL BS 2'!E5 -> 1.53125e+08 | H113: ='WorKings for PL BS 2'!F5 -> 21437500 | I113: ='WorKings for PL BS 2'!G5 -> 0 | J113: ='WorKings for PL BS 2'!H5 -> 0 | K113: ='WorKings for PL BS 2'!I5 -> 0
A115: Interest on CC Loan | D115: ='WorKings for PL BS 2'!B6 -> 4500000000 | E115: ='WorKings for PL BS 2'!C6 -> 5.427e+09 | F115: ='WorKings for PL BS 2'!D6 -> 5.427e+09 | G115: ='WorKings for PL BS 2'!E6 -> 5.454135e+09 | H115: ='WorKings for PL BS 2'!F6 -> 5.4814057e+09 | I115: ='WorKings for PL BS 2'!G6 -> 5.5088127e+09 | J115: ='WorKings for PL BS 2'!H6 -> 5.5363568e+09 | K115: ='WorKings for PL BS 2'!I6 -> 5.5640386e+09
D119: =SUM(D112:D117) -> 5094125000 | E119: =SUM(E112:E117) -> 5.874125e+09 | F119: =SUM(F112:F117) -> 5.727125e+09 | G119: =SUM(G112:G117) -> 5.60726e+09 | H119: =SUM(H112:H117) -> 5.5028432e+09 | I119: =SUM(I112:I117) -> 5.5088127e+09 | J119: =SUM(J112:J117) -> 5.5363568e+09 | K119: =SUM(K112:K117) -> 5.5640386e+09

Sheet RATIO
A1: =Assumptions!I17 -> Doe Textiles
A2: =Assumptions!I8 -> John Doe
A3: =Assumptions!I16 -> 123 Industrial Area, City
A5: RATIO ANALYSIS
A7: A . DEBT SERVICE COVERAGE RATIO
B8: IDEAL RATIO - 1.75 TO 3 Times
A9: Partiiculars | C9: =IF(Assumptions!I62=0,"",'Workings for PL BS 1'!D4) -> 2024-25 | D9: =IF(Assumptions!I63=0,"",Assumptions!I79) -> 2025-26 | E9: ='Workings for PL BS 1'!F4 -> 2026-27 | F9: ='Workings for PL BS 1'!G4 -> 2027-28 | G9: ='Workings for PL BS 1'!H4 -> 2028-29 | H9: ='Workings for PL BS 1'!I4 -> 2029-30 | I9: ='Workings for PL BS 1'!J4 -> 2030-31 | J9: ='Workings for PL BS 1'!K4 -> 2031-32
A11: DSCR ( A / B ) | C11: =IF('Final workings'!B7<=0,"",RATIO!C16/RATIO!C23) -> 1.7500002 | D11: =IF('Final workings'!C7<=0,"",D16/D23) | E11: =E16/E23 -> 2.143313 | F11: =F16/F23 -> 2.2837842 | G11: =G16/G23 -> 2.6972292 | H11: =H16/H23 -> 3.169084 | I11: =I16/I23 -> 3.2847088 | J11: =J16/J23 -> 3.3990994
A13: Earnings before Interest,Depreciation
A14: Interest and Installment
A16: A .Earnings Before Interest ,Depreciation | C16: ='PL BS'!D33 -> 11364720000 | D16: ='PL BS'!E33 -> 14548260000 | E16: ='PL BS'!F33 -> 15275660000 | F16: ='PL BS'!G33 -> 16003070000 | G16: ='PL BS'!H33 -> 16730490000 | H16: ='PL BS'!I33 -> 17457890000 | I16: ='PL BS'!J33 -> 18185320000 | J16: ='PL BS'!K33 -> 18912720000
A18: B .Interest and Installment
A20: Total Interest (CC & TL) | C20: ='WorKings for PL BS 2'!B7 -> 5094125000 | D20: ='WorKings for PL BS 2'!C7 -> 5.874125e+09 | E20: ='WorKings for PL BS 2'!D7 -> 5.727125e+09 | F20: ='WorKings for PL BS 2'!E7 -> 5.60726e+09 | G20: ='WorKings for PL BS 2'!F7 -> 5.5028432e+09 | H20: ='WorKings for PL BS 2'!G7 -> 5.5088127e+09 | I20: ='WorKings for PL BS 2'!H7 -> 5.5363568e+09 | J20: ='WorKings for PL BS 2'!I7 -> 5.5640386e+09
A21: Installment | C21: ='WorKings for PL BS 2'!B10 -> 1400000000 | D21: ='WorKings for PL BS 2'!C10 -> 1400000000 | E21: ='WorKings for PL BS 2'!D10 -> 1400000000 | F21: ='WorKings for PL BS 2'!E10 -> 1400000000 | G21: ='WorKings for PL BS 2'!F10 -> 700000000 | H21: ='WorKings for PL BS 2'!G10 -> 0 | I21: ='WorKings for PL BS 2'!H10 -> 0 | J21: ='WorKings for PL BS 2'!I10 -> 0
C23: =C20+C21 -> 6494125000 | D23: =D20+D21 -> 7.274125e+09 | E23: =E20+E21 -> 7.127125e+09 | F23: =F20+F21 -> 7.00726e+09 | G23: =G20+G21 -> 6.2028432e+09 | H23: =H20+H21 -> 5.5088127e+09 | I23: =I20+I21 -> 5.5363568e+09 | J23: =J20+J21 -> 5.5640386e+09
A27: NOTE : Indicates extent of current Earnings Available for meeting commitments towards interest and Instalment .
A30: B .CURRENT ASSETS RATIO
A32: Particulars | C32: =IF(Assumptions!I62=0,"",Assumptions!I78) -> 2024-25 | D32: =IF(Assumptions!I63=0,"",Assumptions!I79) -> 2025-26 | E32: =E107 -> 2026-27 | F32: =F107 -> 2027-28 | G32: =G107 -> 2028-29 | H32: =H107 -> 2029-30 | I32: =I107 -> 2030-31 | J32: =J107 -> 2031-32
A34: Current Ratio | C34: =IF(C38<=0,"",C36/C37) -> 1.8097093 | D34: =IF(D38<=0,"",D36/D37) -> 1.2413663 | E34: =E36/E37 -> 1.67845 | F34: =F36/F37 -> 1.8181002 | G34: =G36/G37 -> 1.9695976 | H34: =H36/H37 -> 2.1116407 | I34: =I36/I37 -> 2.2621076 | J34: =J36/J37 -> 2.4087513
A36: Current Assets | C36: =SUM('PL BS'!D76:D80) -> 13828640000 | D36: =SUM('PL BS'!E76:E80) -> 55670710000 | E36: =SUM('PL BS'!F76:F80) -> 77880080000 | F36: =SUM('PL BS'!G76:G80) -> 83087180000 | G36: =SUM('PL BS'!H76:H80) -> 88631890000 | H36: =SUM('PL BS'!I76:I80) -> 95023830000 | I36: =SUM('PL BS'!J76:J80) -> 101794840000 | J36: =SUM('PL BS'!K76:K80) -> 108393810000
A37: Current Liabilities | C37: =SUM('PL BS'!D62:D65) -> 7641360000 | D37: =SUM('PL BS'!E62:E65) -> 44846320000 | E37: =SUM('PL BS'!F62:F65) -> 46400000000 | F37: =SUM('PL BS'!G62:G65) -> 45700000000 | G37: =SUM('PL BS'!H62:H65) -> 45000000000 | H37: =SUM('PL BS'!I62:I65) -> 45000000000 | I37: =SUM('PL BS'!J62:J65) -> 45000000000 | J37: =SUM('PL BS'!K62:K65) -> 45000000000
A38: Net Current Assets | C38: =C36-C37 -> 6187280000 | D38: =D36-D37 -> 10824390000 | E38: =E36-E37 -> 31480080000 | F38: =F36-F37 -> 37387180000 | G38: =G36-G37 -> 43631890000 | H38: =H36-H37 -> 50023830000 | I38: =I36-I37 -> 56794840000 | J38: =J36-J37 -> 63393810000
A40: NOTE : Indicates Net Income on Average Assets .
A42: C . GROSS PROFIT RATIO
A44: Particulars | C44: =IF(Assumptions!I62=0,"",Assumptions!I78) -> 2024-25 | D44: =IF(Assumptions!I63=0,"",Assumptions!I79) -> 2025-26 | E44: =E115 -> 2026-27 | F44: =F115 -> 2027-28 | G44: =G115 -> 2028-29 | H44: =H115 -> 2029-30 | I44: =I115 -> 2030-31 | J44: =J115 -> 2031-32
A46: Gross Profit / Sales * 100 | C46: =IF('Final workings'!B7=0,"",'PL BS'!D29/'PL BS'!D14*100) -> 43.478262 | D46: =IF('Final workings'!C7=0,"",'PL BS'!E29/'PL BS'!E14*100) -> -176.58661 | E46: ='PL BS'!F29/'PL BS'!F14*100 -> 35.457533 | F46: ='PL BS'!G29/'PL BS'!G14*100 -> 35.441651 | G46: ='PL BS'!H29/'PL BS'!H14*100 -> 35.427168 | H46: ='PL BS'!I29/'PL BS'!I14*100 -> 35.413878 | I46: ='PL BS'!J29/'PL BS'!J14*100 -> 35.40171 | J46: ='PL BS'!K29/'PL BS'!K14*100 -> 35.39046
A48: NOTES : Indicates overall Profitability of the Business.
A50: D . NETPROFIT RATIO
A52: Particulars | C52: =IF(Assumptions!I62=0,"",Assumptions!I78) -> 2024-25 | D52: =IF(Assumptions!I63=0,"",Assumptions!I79) -> 2025-26 | E52: ='Workings for PL BS 1'!F4 -> 2026-27 | F52: ='Workings for PL BS 1'!G4 -> 2027-28 | G52: ='Workings for PL BS 1'!H4 -> 2028-29 | H52: ='Workings for PL BS 1'!I4 -> 2029-30 | I52: ='Workings for PL BS 1'!J4 -> 2030-31 | J52: ='Workings for PL BS 1'!K4 -> 2031-32
A54: Netprofit / Sales * 100 | C54: =IF('Final workings'!B7=0,"",'PL BS'!D41/'PL BS'!D14*100) -> 19.444684 | D54: =IF('Final workings'!C7=0,"",'PL BS'!E41/'PL BS'!E14*100) -> -89.921989 | E54: ='PL BS'!F41/'PL BS'!F14*100 -> 19.500139 | F54: ='PL BS'!G41/'PL BS'!G14*100 -> 20.705552 | G54: ='PL BS'!H41/'PL BS'!H14*100 -> 21.740345 | H54: ='PL BS'!I41/'PL BS'!I14*100 -> 22.444348 | I54: ='PL BS'!J41/'PL BS'!J14*100 -> 23.028165 | J54: ='PL BS'!K41/'PL BS'!K14*100 -> 23.547669
A56: NOTES : Indicates overall Profitability of the Business.
A59: E . DEBTORS / RECIEVABLES TURNOVER RATIO
A60: Particulars | C60: =IF(Assumptions!I62=0,"",Assumptions!I78) -> 2024-25 | D60: =IF(Assumptions!I63=0,"",Assumptions!I79) -> 2025-26 | E60: ='Workings for PL BS 1'!F4 -> 2026-27 | F60: ='Workings for PL BS 1'!G4 -> 2027-28 | G60: ='Workings for PL BS 1'!H4 -> 2028-29 | H60: ='Workings for PL BS 1'!I4 -> 2029-30 | I60: ='Workings for PL BS 1'!J4 -> 2030-31 | J60: ='Workings for PL BS 1'!K4 -> 2031-32
A62: Credit sales / Average debtors | C62: =IF('Final workings'!B7=0,0,'PL BS'!D14/'PL BS'!D78) -> 11.111127 | D62: =IF('Final workings'!C7=0,0,'PL BS'!E14/'PL BS'!E78) -> 10 | E62: ='PL BS'!F14/'PL BS'!F78 -> 9.0909087 | F62: ='PL BS'!G14/'PL BS'!G78 -> 8.3333304 | G62: ='PL BS'!H14/'PL BS'!H78 -> 7.6923065 | H62: ='PL BS'!I14/'PL BS'!I78 -> 7.1428531 | I62: ='PL BS'!J14/'PL BS'!J78 -> 6.6666658 | J62: ='PL BS'!K14/'PL BS'!K78 -> 6.2500026
A63: *Sales assumed as credit sales
A65: NOTES : It indicates velocity of debt collection. Higer the DTR indicates good vellocity of debt
A66: collection.
A68: DEBTORS COLLECTION PERIOD : | C68: =IF(C62=0,"",B71/C62) -> 32.849954 | D68: =IF(D62=0,"",B71/D62) -> 36.5 | E68: =B71/E62 -> 40.150002 | F68: =B71/F62 -> 43.800016 | G68: =B71/G62 -> 47.450007 | H68: =B71/H62 -> 51.100029 | I68: =B71/I62 -> 54.750007 | J68: =B71/J62 -> 58.399976
A69: (No of days/debtor turnover ratio)
A71: * No. of Days Assumed as | B71: 365
A73: F . TOTAL OUTSIDE LIABILITIES TO TOTAL NETWORTH
A75: Particulars | C75: ='Workings for PL BS 1'!D4 -> 2024-25 | D75: =Assumptions!I79 -> 2025-26 | E75: ='Workings for PL BS 1'!F4 -> 2026-27 | F75: ='Workings for PL BS 1'!G4 -> 2027-28 | G75: ='Workings for PL BS 1'!H4 -> 2028-29 | H75: ='Workings for PL BS 1'!I4 -> 2029-30 | I75: ='Workings for PL BS 1'!J4 -> 2030-31 | J75: ='Workings for PL BS 1'!K4 -> 2031-32
A77: TOL / TW | C77: =SUM('PL BS'!D57:D65)/'PL BS'!D54 -> 1.55556 | D77: =SUM('PL BS'!E57:E65)/'PL BS'!E54 -> 3.6929837 | E77: =SUM('PL BS'!F57:F65)/'PL BS'!F54 -> 1.410868 | F77: =SUM('PL BS'!G57:G65)/'PL BS'!G54 -> 1.1687545 | G77: =SUM('PL BS'!H57:H65)/'PL BS'!H54 -> 0.97930622 | H77: =SUM('PL BS'!I57:I65)/'PL BS'!I54 -> #VALUE! | I77: =SUM('PL BS'!J57:J65)/'PL BS'!J54 -> #VALUE! | J77: =SUM('PL BS'!K57:K65)/'PL BS'!K54 -> 0.68622077
A79: NOTES : Indicates Extent of own funds used in business.
A81: G. RETURN ON CAPITAL EMPLOYED
A83: Particulars | C83: =IF(Assumptions!I62=0,"",Assumptions!I78) -> 2024-25 | D83: =IF(Assumptions!I63=0,"",Assumptions!I79) -> 2025-26 | E83: ='Workings for PL BS 1'!F4 -> 2026-27 | F83: ='Workings for PL BS 1'!G4 -> 2027-28 | G83: ='Workings for PL BS 1'!H4 -> 2028-29 | H83: ='Workings for PL BS 1'!I4 -> 2029-30 | I83: ='Workings for PL BS 1'!J4 -> 2030-31 | J83: ='Workings for PL BS 1'!K4 -> 2031-32
A85: PAT / (Capital+Long Term loan) | C85: =IF(Assumptions!I62=0,"",'PL BS'!D41/SUM('PL BS'!D53:D58)) -> 0.41923815 | D85: =IF(Assumptions!I63=0,"",'PL BS'!E41/SUM('PL BS'!E53:E58)) -> 0.46886128 | E85: ='PL BS'!F41/SUM('PL BS'!F53:F58) -> 0.24055003 | F85: ='PL BS'!G41/SUM('PL BS'!G53:G58) -> 0.23370851 | G85: ='PL BS'!H41/SUM('PL BS'!H53:H58) -> 0.22554703 | H85: ='PL BS'!I41/SUM('PL BS'!I53:I58) -> #VALUE! | I85: ='PL BS'!J41/SUM('PL BS'!J53:J58) -> #VALUE! | J85: ='PL BS'!K41/SUM('PL BS'!K53:K58) -> 0.19790329
A87: NOTE : Indicates overall profitability of Business for capital employed .
A89: H. FIXED ASSETS TO LONGTERM FUND RATIO
A91: Particulars | C91: ='Workings for PL BS 1'!D4 -> 2024-25 | D91: =Assumptions!I79 -> 2025-26 | E91: ='Workings for PL BS 1'!F4 -> 2026-27 | F91: ='Workings for PL BS 1'!G4 -> 2027-28 | G91: ='Workings for PL BS 1'!H4 -> 2028-29 | H91: ='Workings for PL BS 1'!I4 -> 2029-30 | I91: ='Workings for PL BS 1'!J4 -> 2030-31 | J91: ='Workings for PL BS 1'!K4 -> 2031-32
A93: Fixed Assets / Long Term Funds | C93: ='PL BS'!D70/'PL BS'!D58 -> 1.3763066 | D93: ='PL BS'!E70/'PL BS'!E58 -> 1.6607143 | E93: ='PL BS'!F70/'PL BS'!F58 -> 2.4184349 | F93: ='PL BS'!G70/'PL BS'!G58 -> 3.1914083 | G93: =IF('PL BS'!H58=0,0,'PL BS'!H70/'PL BS'!H58) -> 5.9965728 | H93: =IF('PL BS'!I58=0,0,'PL BS'!I70/'PL BS'!I58) -> #VALUE! | I93: =IF('PL BS'!J58=0,0,'PL BS'!J70/'PL BS'!J58) -> #VALUE! | J93: =IF('PL BS'!K58=0,0,'PL BS'!K70/'PL BS'!K58) -> 0
A95: NOTES : Shows proportion of Fixed Assets Financed by Long Term funds .
A97: I . PROPRIETORY RATIO
A99: Particulars | C99: ='Workings for PL BS 1'!D4 -> 2024-25 | D99: =Assumptions!I79 -> 2025-26 | E99: ='Workings for PL BS 1'!F4 -> 2026-27 | F99: ='Workings for PL BS 1'!G4 -> 2027-28 | G99: ='Workings for PL BS 1'!H4 -> 2028-29 | H99: ='Workings for PL BS 1'!I4 -> 2029-30 | I99: ='Workings for PL BS 1'!J4 -> 2030-31 | J99: ='Workings for PL BS 1'!K4 -> 2031-32
A101: Capital / Total Assets | C101: ='PL BS'!D54/'PL BS'!D70 -> 1.2132577 | D101: ='PL BS'!E54/'PL BS'!E70 -> 2.324326 | E101: ='PL BS'!F54/'PL BS'!F70 -> 7.1495595 | F101: ='PL BS'!G54/'PL BS'!G70 -> 9.8151891 | G101: ='PL BS'!H54/'PL BS'!H70 -> 13.306617 | H101: ='PL BS'!I54/'PL BS'!I70 -> #VALUE! | I101: ='PL BS'!J54/'PL BS'!J70 -> #VALUE! | J101: ='PL BS'!K54/'PL BS'!K70 -> 30.043038
A103: NOTES : Shows extent of Owners funds utilised in financing assets .
A105: J . RETURN ON ASSETS
A107: Particulars | C107: =IF(Assumptions!I62=0,"",Assumptions!I78) -> 2024-25 | D107: =IF(Assumptions!I63=0,"",Assumptions!I79) -> 2025-26 | E107: ='Workings for PL BS 1'!F4 -> 2026-27 | F107: ='Workings for PL BS 1'!G4 -> 2027-28 | G107: ='Workings for PL BS 1'!H4 -> 2028-29 | H107: ='Workings for PL BS 1'!I4 -> 2029-30 | I107: ='Workings for PL BS 1'!J4 -> 2030-31 | J107: ='Workings for PL BS 1'!K4 -> 2031-32
A109: PAT / Average total assets | C109: =IF(Assumptions!I62=0,"",'PL BS'!D41/'PL BS'!D82) -> 0.26229352 | D109: =IF(Assumptions!I63=0,"",'PL BS'!E41/'PL BS'!E82) -> 0.12578919 | E109: ='PL BS'!F41/'PL BS'!F82 -> 0.10554792 | F109: ='PL BS'!G41/'PL BS'!G82 -> 0.11120182 | G109: ='PL BS'!H41/'PL BS'!H82 -> 0.11538065 | H109: ='PL BS'!I41/'PL BS'!I82 -> 0.11671421 | I109: ='PL BS'!J41/'PL BS'!J82 -> 0.11705247 | J109: ='PL BS'!K41/'PL BS'!K82 -> 0.11736499
A111: NOTE : Indicates Net Income on Average Assets .
A113: K . INTEREST COVERAGE RATIO
A115: Partiiculars | C115: =IF(Assumptions!I62=0,"",Assumptions!I78) -> 2024-25 | D115: =IF(Assumptions!I63=0,"",Assumptions!I79) -> 2025-26 | E115: ='Workings for PL BS 1'!F4 -> 2026-27 | F115: ='Workings for PL BS 1'!G4 -> 2027-28 | G115: ='Workings for PL BS 1'!H4 -> 2028-29 | H115: ='Workings for PL BS 1'!I4 -> 2029-30 | I115: ='Workings for PL BS 1'!J4 -> 2030-31 | J115: ='Workings for PL BS 1'!K4 -> 2031-32
A117: E B I / Interest | C117: =IF(Assumptions!I62=0,"",C119/C120) -> 2.0510006 | D117: =IF(Assumptions!I63=0,"",D119/D120) -> 2.3124596 | E117: =E119/E120 -> 2.5236873 | F117: =F119/F120 -> 2.7289885 | G117: =G119/G120 -> 2.93173 | H117: =H119/H120 -> 3.0765659 | I117: =I119/I120 -> 3.2061882 | J117: =J119/J120 -> 3.3324457
A119: EBI | C119: ='PL BS'!D37 -> 1.0448053e+10 | D119: ='PL BS'!E37 -> 1.3583677e+10 | E119: ='PL BS'!F37 -> 14453472500 | F119: ='PL BS'!G37 -> 15302148125 | G119: ='PL BS'!H37 -> 1.613285e+10 | H119: ='PL BS'!I37 -> 1.6948226e+10 | I119: ='PL BS'!J37 -> 1.7750602e+10 | J119: ='PL BS'!K37 -> 1.8541856e+10
A120: Interest | C120: ='WorKings for PL BS 2'!B7 -> 5094125000 | D120: ='WorKings for PL BS 2'!C7 -> 5.874125e+09 | E120: ='WorKings for PL BS 2'!D7 -> 5.727125e+09 | F120: ='WorKings for PL BS 2'!E7 -> 5.60726e+09 | G120: ='WorKings for PL BS 2'!F7 -> 5.5028432e+09 | H120: ='WorKings for PL BS 2'!G7 -> 5.5088127e+09 | I120: ='WorKings for PL BS 2'!H7 -> 5.5363568e+09 | J120: ='WorKings for PL BS 2'!I7 -> 5.5640386e+09
A122: NOTE : Indicates ability to meet Interest Obligation of the current year .

Sheet Leverage ratios
B2: =Assumptions!I17 -> Doe Textiles
B3: =Assumptions!I8 -> John Doe
B4: =Assumptions!I16 -> 123 Industrial Area, City
B7: LEVERAGE RATIO ANALYSIS
B10: CALCULATION OF OPERATING LEVERAGE
B12: Particulars | C12: =IF(Assumptions!I62=0,"",'PL BS'!D7) -> 2024-25 | D12: =IF(Assumptions!I63=0,"",'PL BS'!E7) -> 2025-26 | E12: ='PL BS'!F7 -> 2026-27 | F12: ='PL BS'!G7 -> 2027-28 | G12: ='PL BS'!H7 -> 2028-29 | H12: ='PL BS'!I7 -> 2029-30 | I12: ='PL BS'!J7 -> 2030-31 | J12: ='PL BS'!K7 -> 2031-32
B15: Operating Leverage (OL) | C15: =IF('Final workings'!B7=0,0,BEP!B14/'PL BS'!D37) -> 1.1457991 | D15: =IF('Final workings'!C7=0,0,BEP!C14/'PL BS'!E37) -> 1.1145605 | E15: =BEP!D14/'PL BS'!F37 -> 1.0978199 | F15: =BEP!E14/'PL BS'!G37 -> 1.08447 | G15: =BEP!F14/'PL BS'!H37 -> 1.0737235 | H15: =BEP!G14/'PL BS'!I37 -> 1.0649911 | I15: =BEP!H14/'PL BS'!J37 -> 1.0578363 | J15: =BEP!I14/'PL BS'!K37 -> 1.0519297
B16: (Contribution / EBIT)
B19: The operating Leverage of 1.2 means that 1% increase in sales would result into 1.2% increase in operating profit
B21: If operating leverage is high, it means that break even point will be reached at a higher level of sales and the margin of safety is low.
B23: NOTE : Indicates Firms ability to use fixed operating costs to magnify effects of changes in sales on its earnings before increase and taxes
B26: CALCULATION OF FINANCIAL LEVERAGE
B28: Particulars | C28: =C12 -> 2024-25 | D28: =D12 -> 2025-26 | E28: =E12 -> 2026-27 | F28: =F12 -> 2027-28 | G28: =G12 -> 2028-29 | H28: =H12 -> 2029-30 | I28: =I12 -> 2030-31 | J28: =J12 -> 2031-32
B30: Financial Leverage (FL) | C30: =IF('Final workings'!B7=0,0,'PL BS'!D37/'PL BS'!D41) -> 1.9514743 | D30: =IF('Final workings'!C7=0,0,'PL BS'!E37/'PL BS'!E41) -> 1.7619282 | E30: ='PL BS'!F37/'PL BS'!F41 -> 1.6563027 | F30: ='PL BS'!G37/'PL BS'!G41 -> 1.5783728 | G30: ='PL BS'!H37/'PL BS'!H41 -> 1.5176707 | H30: ='PL BS'!I37/'PL BS'!I41 -> 1.4815643 | I30: ='PL BS'!J37/'PL BS'!J41 -> 1.4532705 | J30: ='PL BS'!K37/'PL BS'!K41 -> 1.4287345
B31: (EBIT / EBT)
B33: The FL is favourable when the firms earns more on the investment/assets financed by the sources having fixed charges.
B34: Shareholders gain in a situation where the company earns a high rate of return and pays a lower rate
B35: of return to the supplier of long-term funds. FL is such easer is also called “Trading on Equity”.
B39: CALCULATION OF COMBINED LEVERAGE
B41: Particulars | C41: =C28 -> 2024-25 | D41: =D28 -> 2025-26 | E41: =E28 -> 2026-27 | F41: =F28 -> 2027-28 | G41: =G28 -> 2028-29 | H41: =H28 -> 2029-30 | I41: =I28 -> 2030-31 | J41: =J28 -> 2031-32
B43: Operating Leverage * Financial Leverage | C43: =C15*C30 -> 2.2359974 | D43: =D15*D30 -> 1.9637757 | E43: =E15*E30 -> 1.818322 | F43: =F15*F30 -> 1.7116979 | G43: =G15*G30 -> 1.6295587 | H43: =H15*H30 -> 1.5778528 | I43: =I15*I30 -> 1.5373222 | J43: =J15*J30 -> 1.5029283
B45: A high Operating and Financial Leverage Combination is very risky. If the company is producing and selling at a high level , it will
B46: make extremely high profit for it and shareholders . But even a small fall in the level of operation would result in tremendous fall in
B47: Earnings. Proper Balance should be maintained.
B50: A high OL and low FL indicate that management is careful since the higher amount of risk involved in high OL has been sought to be
B51: balanced by low FL. Preferable situation will be low OL and high FL. Low FL results in equivalent Break even sales.

Sheet Dep IT act
A1: =Assumptions!I17 -> Doe Textiles
A2: =Assumptions!I8 -> John Doe
A3: =Assumptions!I16 -> 123 Industrial Area, City
A6: CALCULATION OF DEPRECIATION AS PER INCOME TAX ACT
M7: Rs in lacs
B8: =Assumptions!C28 -> Plant and Machinery | D8: =Assumptions!C30 -> Shed Construction and Civil works | I8: =Assumptions!C35 -> Vehicles | K8: =Assumptions!C37 -> Other Assets | L8: =Assumptions!B226 -> Other Assets (Nil depreciation)
C9: =Assumptions!C29 -> Service Equipment | E9: =Assumptions!C31 -> Land | F9: =Assumptions!C32 -> Electrical Items & fittings | G9: =Assumptions!C33 -> Electronic Items | H9: =Assumptions!C34 -> Furniture and Fittings | J9: =Assumptions!C36 -> Live stock | M9: Total
B10: =Assumptions!F109 -> 0.15 | C10: =Assumptions!F110 -> 0.15 | D10: =Assumptions!F111 -> 0.1 | E10: =Assumptions!F112 -> 0 | F10: =Assumptions!F113 -> 0.15 | G10: =Assumptions!F114 -> 0.15 | H10: =Assumptions!F115 -> 0.1 | I10: =Assumptions!F116 -> 0.15 | J10: =Assumptions!F117 -> 0 | K10: =Assumptions!F118 -> 0.1 | L10: 0
A13: =Assumptions!I78 -> 2024-25
A14: WDV in the beginning of year 1 | B14: 0 | C14: 0 | D14: 0 | E14: 0 | F14: 0 | G14: 0 | H14: 0 | I14: 0 | J14: 0 | K14: 0 | L14: 0 | M14: =SUM(B14:L14) -> 0
A15: Add : Additions during year | B15: ='project cost'!C15 -> 70000 | C15: =Assumptions!I29 -> 0 | D15: =Assumptions!I30 -> 0 | E15: =Assumptions!I31 -> 0 | F15: =Assumptions!I32 -> 0 | G15: =Assumptions!I33 -> 0 | H15: =Assumptions!I34 -> 5000 | I15: =Assumptions!I35 -> 0 | J15: =Assumptions!I36 -> 0 | K15: =Assumptions!I37 -> 0 | L15: =Assumptions!I38 -> 0 | M15: =SUM(B15:L15) -> 75000
A16: Total | B16: =B14+B15 -> 70000 | C16: =C14+C15 -> 0 | D16: =D14+D15 -> 0 | E16: =E14+E15 -> 0 | F16: =F14+F15 -> 0 | G16: =G14+G15 -> 0 | H16: =H14+H15 -> 5000 | I16: =I14+I15 -> 0 | ... L16: =L14+L15 -> 0 | M16: =SUM(B16:L16) -> 75000
A17: Less: Depreciation | B17: =B10*B16*Assumptions!I62/Assumptions!F130 -> 8750 | C17: =C10*C16*Assumptions!I62/Assumptions!F130 -> 0 | D17: =D10*D16*Assumptions!I62/Assumptions!F130 -> 0 | E17: =E10*E16*Assumptions!I62/Assumptions!F130 -> 0 | F17: =F10*F16*Assumptions!I62/Assumptions!F130 -> 0 | G17: =G10*G16*Assumptions!I62/Assumptions!F130 -> 0 | H17: =H10*H16*Assumptions!I62/Assumptions!F130 -> 416.66667 | I17: =I10*I16*Assumptions!I62/Assumptions!F130 -> 0 | J17: =J10*J16*Assumptions!I62/Assumptions!F130 -> 0 | K17: =K10*K16*Assumptions!I62/Assumptions!F130 -> 0 | L17: =L10 -> 0 | M17: =SUM(B17:L17) -> 9166.6667
A18: WDV at the end of 1st Year | B18: =B16-B17 -> 61250 | C18: =C16-C17 -> 0 | D18: =D16-D17 -> 0 | E18: =E16-E17 -> 0 | F18: =F16-F17 -> 0 | G18: =G16-G17 -> 0 | H18: =H16-H17 -> 4583.3333 | I18: =I16-I17 -> 0 | ... L18: =L16-L17 -> 0 | M18: =SUM(B18:L18) -> 65833.333
A20: =Assumptions!I79 -> 2025-26
A21: WDV in the beginning of year 2 | B21: =B18 -> 61250 | C21: =C18 -> 0 | D21: =D18 -> 0 | E21: =E18 -> 0 | F21: =F18 -> 0 | G21: =G18 -> 0 | H21: =H18 -> 4583.3333 | I21: =I18 -> 0 | ... L21: =L18 -> 0 | M21: =SUM(B21:L21) -> 65833.333
A22: Add : Additions during year | B22: 0 | C22: 0 | D22: 0 | E22: 0 | F22: 0 | G22: 0 | H22: 0 | I22: 0 | J22: 0 | K22: 0 | L22: 0 | M22: =SUM(B22:L22) -> 0
A23: Total | B23: =B21+B22 -> 61250 | C23: =C21+C22 -> 0 | D23: =D21+D22 -> 0 | E23: =E21+E22 -> 0 | F23: =F21+F22 -> 0 | G23: =G21+G22 -> 0 | H23: =H21+H22 -> 4583.3333 | I23: =I21+I22 -> 0 | ... L23: =L21+L22 -> 0 | M23: =SUM(B23:L23) -> 65833.333
A24: Less: Depreciation | B24: =B23*B10*Assumptions!I63/Assumptions!F130 -> 9187.5 | C24: =C23*C10*Assumptions!I63/Assumptions!F130 -> 0 | D24: =D23*D10*Assumptions!I63/Assumptions!F130 -> 0 | E24: =E23*E10*Assumptions!I63/Assumptions!F130 -> 0 | F24: =F23*F10*Assumptions!I63/Assumptions!F130 -> 0 | G24: =G23*G10*Assumptions!I63/Assumptions!F130 -> 0 | H24: =H23*H10*Assumptions!I63/Assumptions!F130 -> 458.33333 | I24: =I23*I10*Assumptions!I63/Assumptions!F130 -> 0 | J24: =J23*J10*Assumptions!I63/Assumptions!F130 -> 0 | K24: =K23*K10*Assumptions!I63/Assumptions!F130 -> 0 | L24: =L23*L10 -> 0 | M24: =SUM(B24:L24) -> 9645.8333
A25: WDV at the end of 2nd Year | B25: =B23-B24 -> 52062.5 | C25: =C23-C24 -> 0 | D25: =D23-D24 -> 0 | E25: =E23-E24 -> 0 | F25: =F23-F24 -> 0 | G25: =G23-G24 -> 0 | H25: =H23-H24 -> 4125 | I25: =I23-I24 -> 0 | ... L25: =L23-L24 -> 0 | M25: =SUM(B25:L25) -> 56187.5
A27: =Assumptions!I80 -> 2026-27
A28: WDV in the beginning of year 3 | B28: =B25 -> 52062.5 | C28: =C25 -> 0 | D28: =D25 -> 0 | E28: =E25 -> 0 | F28: =F25 -> 0 | G28: =G25 -> 0 | H28: =H25 -> 4125 | I28: =I25 -> 0 | ... L28: =L25 -> 0 | M28: =SUM(B28:L28) -> 56187.5
A29: Add : Additions during year | B29: 0 | C29: 0 | D29: 0 | E29: 0 | F29: 0 | G29: 0 | H29: 0 | I29: 0 | J29: 0 | K29: 0 | L29: 0 | M29: =SUM(B29:L29) -> 0
A30: Total | B30: =B28+B29 -> 52062.5 | C30: =C28+C29 -> 0 | D30: =D28+D29 -> 0 | E30: =E28+E29 -> 0 | F30: =F28+F29 -> 0 | G30: =G28+G29 -> 0 | H30: =H28+H29 -> 4125 | I30: =I28+I29 -> 0 | ... L30: =L28+L29 -> 0 | M30: =SUM(B30:L30) -> 56187.5
A31: Less: Depreciation | B31: =B30*B10 -> 7809.375 | C31: =C30*C10 -> 0 | D31: =D30*D10 -> 0 | E31: =E30*E10 -> 0 | F31: =F30*F10 -> 0 | G31: =G30*G10 -> 0 | H31: =H30*H10 -> 412.5 | I31: =I30*I10 -> 0 | ... L31: =L30*L10 -> 0 | M31: =SUM(B31:L31) -> 8221.875
A32: WDV at the end of 3rd Year | B32: =B30-B31 -> 44253.125 | C32: =C30-C31 -> 0 | D32: =D30-D31 -> 0 | E32: =E30-E31 -> 0 | F32: =F30-F31 -> 0 | G32: =G30-G31 -> 0 | H32: =H30-H31 -> 3712.5 | I32: =I30-I31 -> 0 | ... L32: =L30-L31 -> 0 | M32: =SUM(B32:L32) -> 47965.625
A34: =Assumptions!I81 -> 2027-28
A35: WDV in the beginning of year 4 | B35: =B32 -> 44253.125 | C35: =C32 -> 0 | D35: =D32 -> 0 | E35: =E32 -> 0 | F35: =F32 -> 0 | G35: =G32 -> 0 | H35: =H32 -> 3712.5 | I35: =I32 -> 0 | ... L35: =L32 -> 0 | M35: =SUM(B35:L35) -> 47965.625
A36: Add : Additions during year | B36: 0 | C36: 0 | D36: 0 | E36: 0 | F36: 0 | G36: 0 | H36: 0 | I36: 0 | J36: 0 | K36: 0 | L36: 0 | M36: =SUM(B36:L36) -> 0
A37: Total | B37: =B35+B36 -> 44253.125 | C37: =C35+C36 -> 0 | D37: =D35+D36 -> 0 | E37: =E35+E36 -> 0 | F37: =F35+F36 -> 0 | G37: =G35+G36 -> 0 | H37: =H35+H36 -> 3712.5 | I37: =I35+I36 -> 0 | ... L37: =L35+L36 -> 0 | M37: =SUM(B37:L37) -> 47965.625
A38: Less: Depreciation | B38: =B37*B10 -> 6637.9688 | C38: =C37*C10 -> 0 | D38: =D37*D10 -> 0 | E38: =E37*E10 -> 0 | F38: =F37*F10 -> 0 | G38: =G37*G10 -> 0 | H38: =H37*H10 -> 371.25 | I38: =I37*I10 -> 0 | ... L38: =L37*L10 -> 0 | M38: =SUM(B38:L38) -> 7009.2188
A39: WDVat the end of 4th Year | B39: =B37-B38 -> 37615.156 | C39: =C37-C38 -> 0 | D39: =D37-D38 -> 0 | E39: =E37-E38 -> 0 | F39: =F37-F38 -> 0 | G39: =G37-G38 -> 0 | H39: =H37-H38 -> 3341.25 | I39: =I37-I38 -> 0 | ... L39: =L37-L38 -> 0 | M39: =SUM(B39:L39) -> 40956.406
A41: =Assumptions!I82 -> 2028-29
A42: WDV in the beginning of year 5 | B42: =B39 -> 37615.156 | C42: =C39 -> 0 | D42: =D39 -> 0 | E42: =E39 -> 0 | F42: =F39 -> 0 | G42: =G39 -> 0 | H42: =H39 -> 3341.25 | I42: =I39 -> 0 | ... L42: =L39 -> 0 | M42: =SUM(B42:L42) -> 40956.406
A43: Add : Additions during year | B43: 0 | C43: 0 | D43: 0 | E43: 0 | F43: 0 | G43: 0 | H43: 0 | I43: 0 | J43: 0 | K43: 0 | L43: 0 | M43: =SUM(B43:L43) -> 0
A44: Total | B44: =B42+B43 -> 37615.156 | C44: =C42+C43 -> 0 | D44: =D42+D43 -> 0 | E44: =E42+E43 -> 0 | F44: =F42+F43 -> 0 | G44: =G42+G43 -> 0 | H44: =H42+H43 -> 3341.25 | I44: =I42+I43 -> 0 | ... L44: =L42+L43 -> 0 | M44: =SUM(B44:L44) -> 40956.406
A45: Less: Depreciation | B45: =B44*B10 -> 5642.2734 | C45: =C44*C10 -> 0 | D45: =D44*D10 -> 0 | E45: =E44*E10 -> 0 | F45: =F44*F10 -> 0 | G45: =G44*G10 -> 0 | H45: =H44*H10 -> 334.125 | I45: =I44*I10 -> 0 | ... L45: =L44*L10 -> 0 | M45: =SUM(B45:L45) -> 5976.3984
A46: WDV at the end of 5th Year | B46: =B44-B45 -> 31972.883 | C46: =C44-C45 -> 0 | D46: =D44-D45 -> 0 | E46: =E44-E45 -> 0 | F46: =F44-F45 -> 0 | G46: =G44-G45 -> 0 | H46: =H44-H45 -> 3007.125 | I46: =I44-I45 -> 0 | ... L46: =L44-L45 -> 0 | M46: =SUM(B46:L46) -> 34980.008
A48: =Assumptions!I83 -> 2029-30
A49: WDV in the beginning of year 6 | B49: =B46 -> 31972.883 | C49: =C46 -> 0 | D49: =D46 -> 0 | E49: =E46 -> 0 | F49: =F46 -> 0 | G49: =G46 -> 0 | H49: =H46 -> 3007.125 | I49: =I46 -> 0 | ... L49: =L46 -> 0 | M49: =SUM(B49:L49) -> 34980.008
A50: Add : Additions during year | B50: 0 | C50: 0 | D50: 0 | E50: 0 | F50: 0 | G50: 0 | H50: 0 | I50: 0 | J50: 0 | K50: 0 | L50: 0 | M50: =SUM(B50:L50) -> 0
A51: Total | B51: =B49+B50 -> 31972.883 | C51: =C49+C50 -> 0 | D51: =D49+D50 -> 0 | E51: =E49+E50 -> 0 | F51: =F49+F50 -> 0 | G51: =G49+G50 -> 0 | H51: =H49+H50 -> 3007.125 | I51: =I49+I50 -> 0 | ... L51: =L49+L50 -> 0 | M51: =SUM(B51:L51) -> 34980.008
A52: Less: Depreciation | B52: =B51*B10 -> 4795.9324 | C52: =C51*C10 -> 0 | D52: =D51*D10 -> 0 | E52: =E51*E10 -> 0 | F52: =F51*F10 -> 0 | G52: =G51*G10 -> 0 | H52: =H51*H10 -> 300.7125 | I52: =I51*I10 -> 0 | ... L52: =L51*L10 -> 0 | M52: =SUM(B52:L52) -> 5096.6449
A53: WDV at the end of 6th Year | B53: =B51-B52 -> 27176.95 | C53: =C51-C52 -> 0 | D53: =D51-D52 -> 0 | E53: =E51-E52 -> 0 | F53: =F51-F52 -> 0 | G53: =G51-G52 -> 0 | H53: =H51-H52 -> 2706.4125 | I53: =I51-I52 -> 0 | ... L53: =L51-L52 -> 0 | M53: =SUM(B53:L53) -> 29883.363
A55: =Assumptions!I84 -> 2030-31
A56: WDV in the beginning of year 7 | B56: =B53 -> 27176.95 | C56: =C53 -> 0 | D56: =D53 -> 0 | E56: =E53 -> 0 | F56: =F53 -> 0 | G56: =G53 -> 0 | H56: =H53 -> 2706.4125 | I56: =I53 -> 0 | ... L56: =L53 -> 0 | M56: =SUM(B56:L56) -> 29883.363
A57: Add : Additions during year | B57: 0 | C57: 0 | D57: 0 | E57: 0 | F57: 0 | G57: 0 | H57: 0 | I57: 0 | J57: 0 | K57: 0 | L57: 0 | M57: =SUM(B57:L57) -> 0
A58: Total | B58: =B56+B57 -> 27176.95 | C58: =C56+C57 -> 0 | D58: =D56+D57 -> 0 | E58: =E56+E57 -> 0 | F58: =F56+F57 -> 0 | G58: =G56+G57 -> 0 | H58: =H56+H57 -> 2706.4125 | I58: =I56+I57 -> 0 | ... L58: =L56+L57 -> 0 | M58: =SUM(B58:L58) -> 29883.363
A59: Less: Depreciation | B59: =B58*B10 -> 4076.5426 | C59: =C58*C10 -> 0 | D59: =D58*D10 -> 0 | E59: =E58*E10 -> 0 | F59: =F58*F10 -> 0 | G59: =G58*G10 -> 0 | H59: =H58*H10 -> 270.64125 | I59: =I58*I10 -> 0 | ... L59: =L58*L10 -> 0 | M59: =SUM(B59:L59) -> 4347.1838
A60: WDV at the end of 7th Year | B60: =B58-B59 -> 23100.408 | C60: =C58-C59 -> 0 | D60: =D58-D59 -> 0 | E60: =E58-E59 -> 0 | F60: =F58-F59 -> 0 | G60: =G58-G59 -> 0 | H60: =H58-H59 -> 2435.7712 | I60: =I58-I59 -> 0 | ... L60: =L58-L59 -> 0 | M60: =SUM(B60:L60) -> 25536.179
A62: =Assumptions!I85 -> 2031-32
A63: WDV in the beginning of year 8 | B63: =B60 -> 23100.408 | C63: =C60 -> 0 | D63: =D60 -> 0 | E63: =E60 -> 0 | F63: =F60 -> 0 | G63: =G60 -> 0 | H63: =H60 -> 2435.7712 | I63: =I60 -> 0 | ... L63: =L60 -> 0 | M63: =SUM(B63:L63) -> 25536.179
A64: Add : Additions during year | B64: 0 | C64: 0 | D64: 0 | E64: 0 | F64: 0 | G64: 0 | H64: 0 | I64: 0 | J64: 0 | K64: 0 | L64: 0 | M64: =SUM(B64:L64) -> 0
A65: Total | B65: =B63+B64 -> 23100.408 | C65: =C63+C64 -> 0 | D65: =D63+D64 -> 0 | E65: =E63+E64 -> 0 | F65: =F63+F64 -> 0 | G65: =G63+G64 -> 0 | H65: =H63+H64 -> 2435.7712 | I65: =I63+I64 -> 0 | ... L65: =L63+L64 -> 0 | M65: =SUM(B65:L65) -> 25536.179
A66: Less: Depreciation | B66: =B65*B10 -> 3465.0612 | C66: =C65*C10 -> 0 | D66: =D65*D10 -> 0 | E66: =E65*E10 -> 0 | F66: =F65*F10 -> 0 | G66: =G65*G10 -> 0 | H66: =H65*H10 -> 243.57712 | I66: =I65*I10 -> 0 | ... L66: =L65*L10 -> 0 | M66: =SUM(B66:L66) -> 3708.6383
A67: WDV at the end of 8th Year | B67: =B65-B66 -> 19635.347 | C67: =C65-C66 -> 0 | D67: =D65-D66 -> 0 | E67: =E65-E66 -> 0 | F67: =F65-F66 -> 0 | G67: =G65-G66 -> 0 | H67: =H65-H66 -> 2192.1941 | I67: =I65-I66 -> 0 | ... L67: =L65-L66 -> 0 | M67: =SUM(B67:L67) -> 21827.541

Sheet Loan sch
A1: =Assumptions!I17 -> Doe Textiles
A2: =Assumptions!I8 -> John Doe
A3: =Assumptions!I16 -> 123 Industrial Area, City
B5: EMI STATEMENT
B8: LOAN AMOUNT | E8: =Assumptions!I43*100000 -> 6300000000 | J8: When EMI is shared equally over loan term period formulae is =-PMT(E12,E14,E8)
B10: RATE OF INTEREST PER ANNUM | E10: =Assumptions!I45 -> 0.105
B12: RATE OF INTEREST PER MONTH | E12: =E10/12 -> 0.00875 | I12: EMI | J12: =-PMT(E12,E14,E8) -> 1.4689202e+08
B14: NO OF INSTALLMENT (Excluding Moratorium period) | E14: =Assumptions!I47-Assumptions!I49 -> 54
E15: 62
B18: =Assumptions!I48 -> 1. EMI shared equally over loan Term period
B20: CALCULATION OF DETAILS OF EMI
B22: MONTHS | C22: MONTH | D22: EMI | E22: INTEREST | F22: PRINCIPAL REPAYMENT | G22: OUTSTANDING PRINCIPAL
B23: =Assumptions!I49 -> 6 | G23: =E8 -> 6300000000
B24: =IF(ROW()-ROW($B$24)+1 <= $E$14, ROW()-ROW($B$24)+1, "") -> 1 | C24: =Assumptions!I58 -> 45383 | D24: =IF($B24<>"", E24+F24, "") -> 1.7179167e+08 | E24: =IF($B24<>"", G23*$E$12, "") -> 55125000 | F24: =IF($B24<>"", $E$8/$E$14, "") -> 1.1666667e+08 | G24: =IF($B24<>"", G23-F24, "") -> 6.1833333e+09
B25: =IF(ROW()-ROW($B$24)+1 <= $E$14, ROW()-ROW($B$24)+1, "") -> 2 | C25: =IF($B25<>"", EDATE(C24,1), "") -> 45413 | D25: =IF($B25<>"", E25+F25, "") -> 1.7077083e+08 | E25: =IF($B25<>"", G24*$E$12, "") -> 54104167 | F25: =IF($B25<>"", $E$8/$E$14, "") -> 1.1666667e+08 | G25: =IF($B25<>"", G24-F25, "") -> 6.0666667e+09
B26: =IF(ROW()-ROW($B$24)+1 <= $E$14, ROW()-ROW($B$24)+1, "") -> 3 | C26: =IF($B26<>"", EDATE(C25,1), "") -> 45444 | D26: =IF($B26<>"", E26+F26, "") -> 169750000 | E26: =IF($B26<>"", G25*$E$12, "") -> 53083333 | F26: =IF($B26<>"", $E$8/$E$14, "") -> 1.1666667e+08 | G26: =IF($B26<>"", G25-F26, "") -> 5.95e+09
B27: =IF(ROW()-ROW($B$24)+1 <= $E$14, ROW()-ROW($B$24)+1, "") -> 4 | C27: =IF($B27<>"", EDATE(C26,1), "") -> 45474 | D27: =IF($B27<>"", E27+F27, "") -> 1.6872917e+08 | E27: =IF($B27<>"", G26*$E$12, "") -> 52062500 | F27: =IF($B27<>"", $E$8/$E$14, "") -> 1.1666667e+08 | G27: =IF($B27<>"", G26-F27, "") -> 5.8333333e+09
B28: =IF(ROW()-ROW($B$24)+1 <= $E$14, ROW()-ROW($B$24)+1, "") -> 5 | C28: =IF($B28<>"", EDATE(C27,1), "") -> 45505 | D28: =IF($B28<>"", E28+F28, "") -> 1.6770833e+08 | E28: =IF($B28<>"", G27*$E$12, "") -> 51041667 | F28: =IF($B28<>"", $E$8/$E$14, "") -> 1.1666667e+08 | G28: =IF($B28<>"", G27-F28, "") -> 5.7166667e+09
B29: =IF(ROW()-ROW($B$24)+1 <= $E$14, ROW()-ROW($B$24)+1, "") -> 6 | C29: =IF($B29<>"", EDATE(C28,1), "") -> 45536 | D29: =IF($B29<>"", E29+F29, "") -> 166687500 | E29: =IF($B29<>"", G28*$E$12, "") -> 50020833 | F29: =IF($B29<>"", $E$8/$E$14, "") -> 1.1666667e+08 | G29: =IF($B29<>"", G28-F29, "") -> 5.6e+09
B30: =IF(ROW()-ROW($B$24)+1 <= $E$14, ROW()-ROW($B$24)+1, "") -> 7 | C30: =IF($B30<>"", EDATE(C29,1), "") -> 45566 | D30: =IF($B30<>"", E30+F30, "") -> 1.6566667e+08 | E30: =IF($B30<>"", G29*$E$12, "") -> 49000000 | F30: =IF($B30<>"", $E$8/$E$14, "") -> 1.1666667e+08 | G30: =IF($B30<>"", G29-F30, "") -> 5.4833333e+09
B31: =IF(ROW()-ROW($B$24)+1 <= $E$14, ROW()-ROW($B$24)+1, "") -> 8 | C31: =IF($B31<>"", EDATE(C30,1), "") -> 45597 | D31: =IF($B31<>"", E31+F31, "") -> 1.6464583e+08 | E31: =IF($B31<>"", G30*$E$12, "") -> 47979167 | F31: =IF($B31<>"", $E$8/$E$14, "") -> 1.1666667e+08 | G31: =IF($B31<>"", G30-F31, "") -> 5.3666667e+09
B32: =IF(ROW()-ROW($B$24)+1 <= $E$14, ROW()-ROW($B$24)+1, "") -> 9 | C32: =IF($B32<>"", EDATE(C31,1), "") -> 45627 | D32: =IF($B32<>"", E32+F32, "") -> 1.63625e+08 | E32: =IF($B32<>"", G31*$E$12, "") -> 46958333 | F32: =IF($B32<>"", $E$8/$E$14, "") -> 1.1666667e+08 | G32: =IF($B32<>"", G31-F32, "") -> 5.25e+09
B33: =IF(ROW()-ROW($B$24)+1 <= $E$14, ROW()-ROW($B$24)+1, "") -> 10 | C33: =IF($B33<>"", EDATE(C32,1), "") -> 45658 | D33: =IF($B33<>"", E33+F33, "") -> 1.6260417e+08 | E33: =IF($B33<>"", G32*$E$12, "") -> 45937500 | F33: =IF($B33<>"", $E$8/$E$14, "") -> 1.1666667e+08 | G33: =IF($B33<>"", G32-F33, "") -> 5.1333333e+09
B34: =IF(ROW()-ROW($B$24)+1 <= $E$14, ROW()-ROW($B$24)+1, "") -> 11 | C34: =IF($B34<>"", EDATE(C33,1), "") -> 45689 | D34: =IF($B34<>"", E34+F34, "") -> 1.6158333e+08 | E34: =IF($B34<>"", G33*$E$12, "") -> 44916667 | F34: =IF($B34<>"", $E$8/$E$14, "") -> 1.1666667e+08 | G34: =IF($B34<>"", G33-F34, "") -> 5.0166667e+09
B35: =IF(ROW()-ROW($B$24)+1 <= $E$14, ROW()-ROW($B$24)+1, "") -> 12 | C35: =IF($B35<>"", EDATE(C34,1), "") -> 45717 | D35: =IF($B35<>"", E35+F35, "") -> 1.605625e+08 | E35: =IF($B35<>"", G34*$E$12, "") -> 43895833 | F35: =IF($B35<>"", $E$8/$E$14, "") -> 1.1666667e+08 | G35: =IF($B35<>"", G34-F35, "") -> 4.9e+09
B36: =IF(ROW()-ROW($B$24)+1 <= $E$14, ROW()-ROW($B$24)+1, "") -> 13 | C36: =IF($B36<>"", EDATE(C35,1), "") -> 45748 | D36: =IF($B36<>"", E36+F36, "") -> 1.5954167e+08 | E36: =IF($B36<>"", G35*$E$12, "") -> 42875000 | F36: =IF($B36<>"", $E$8/$E$14, "") -> 1.1666667e+08 | G36: =IF($B36<>"", G35-F36, "") -> 4.7833333e+09
... B107: =IF(ROW()-ROW($B$24)+1 <= $E$14, ROW()-ROW($B$24)+1, "") | C107: =IF($B107<>"", EDATE(C106,1), "") | D107: =IF($B107<>"", E107+F107, "") | E107: =IF($B107<>"", G106*$E$12, "") | F107: =IF($B107<>"", $E$8/$E$14, "") | G107: =IF($B107<>"", G106-F107, "")
B155: Present Value Annuity Factor Table
B157: 100 | D157: =100+100*E12 -> 100.875 | E157: =B157/D157 -> 0.9913259
B158: 100 | D158: =D157+D157*E12 -> 101.75766 | E158: =B158/D158 -> 0.98272704
B159: 100 | D159: =D158+D158*E12 -> 102.64804 | E159: =B159/D159 -> 0.97420276
B160: 100 | D160: =D159+D159*E12 -> 103.54621 | E160: =B160/D160 -> 0.96575243
B161: 100 | D161: =D160+D160*E12 -> 104.45224 | E161: =B161/D161 -> 0.95737539
B162: 100 | D162: =D161+D161*E12 -> 105.36619 | E162: =B162/D162 -> 0.94907102
B163: 100 | D163: =D162+D162*E12 -> 106.28815 | E163: =B163/D163 -> 0.94083868
B164: 100 | D164: =D163+D163*E12 -> 107.21817 | E164: =B164/D164 -> 0.93267775
B165: 100 | D165: =D164+D164*E12 -> 108.15633 | E165: =B165/D165 -> 0.92458761
B166: 100 | D166: =D165+D165*E12 -> 109.10269 | E166: =B166/D166 -> 0.91656765
B167: 100 | D167: =D166+D166*E12 -> 110.05734 | E167: =B167/D167 -> 0.90861724
B168: 100 | D168: =D167+D167*E12 -> 111.02035 | E168: =B168/D168 -> 0.90073581
B169: 100 | D169: =D168+D168*E12 -> 111.99177 | E169: =B169/D169 -> 0.89292273
B170: 100 | D170: =D169+D169*E12 -> 112.9717 | E170: =B170/D170 -> 0.88517743
B171: 100 | D171: =D170+D170*E12 -> 113.9602 | E171: =B171/D171 -> 0.87749931
B172: 100 | D172: =D171+D171*E12 -> 114.95736 | E172: =B172/D172 -> 0.86988779
B173: 100 | D173: =D172+D172*E12 -> 115.96323 | E173: =B173/D173 -> 0.8623423
B174: 100 | D174: =D173+D173*E12 -> 116.97791 | E174: =B174/D174 -> 0.85486225
B175: 100 | D175: =D174+D174*E12 -> 118.00147 | E175: =B175/D175 -> 0.84744709
B176: 100 | D176: =D175+D175*E12 -> 119.03398 | E176: =B176/D176 -> 0.84009625
B177: 100 | D177: =D176+D176*E12 -> 120.07553 | E177: =B177/D177 -> 0.83280917
B178: 100 | D178: =D177+D177*E12 -> 121.12619 | E178: =B178/D178 -> 0.8255853
B179: 100 | D179: =D178+D178*E12 -> 122.18604 | E179: =B179/D179 -> 0.81842409
B180: 100 | D180: =D179+D179*E12 -> 123.25517 | E180: =B180/D180 -> 0.81132499
B181: 100 | D181: =D180+D180*E12 -> 124.33365 | E181: =B181/D181 -> 0.80428748
B182: 100 | D182: =D181+D181*E12 -> 125.42157 | E182: =B182/D182 -> 0.79731101
B183: 100 | D183: =D182+D182*E12 -> 126.51901 | E183: =B183/D183 -> 0.79039505
B184: 100 | D184: =D183+D183*E12 -> 127.62605 | E184: =B184/D184 -> 0.78353908
B185: 100 | D185: =D184+D184*E12 -> 128.74278 | E185: =B185/D185 -> 0.77674258
B186: 100 | D186: =D185+D185*E12 -> 129.86928 | E186: =B186/D186 -> 0.77000504
B187: 100 | D187: =D186+D186*E12 -> 131.00564 | E187: =B187/D187 -> 0.76332594
B188: 100 | D188: =D187+D187*E12 -> 132.15194 | E188: =B188/D188 -> 0.75670477
B189: 100 | D189: =D188+D188*E12 -> 133.30826 | E189: =B189/D189 -> 0.75014104
B190: 100 | D190: =D189+D189*E12 -> 134.47471 | E190: =B190/D190 -> 0.74363424
B191: 100 | D191: =D190+D190*E12 -> 135.65137 | E191: =B191/D191 -> 0.73718388
B192: 100 | D192: =D191+D191*E12 -> 136.83832 | E192: =B192/D192 -> 0.73078947
B193: ANNUITY | E193: =SUM(E157:E192) -> 30.766918

Sheet Repayment
A1: =Assumptions!I17 -> Doe Textiles
A2: =Assumptions!I8 -> John Doe
A3: =Assumptions!I16 -> 123 Industrial Area, City
A6: Repayment Schedule - Term Loan
A8: Particulars | B8: =Assumptions!I78 -> 2024-25 | C8: =Assumptions!I79 -> 2025-26 | D8: =Assumptions!I80 -> 2026-27 | E8: =Assumptions!I81 -> 2027-28 | F8: =Assumptions!I82 -> 2028-29 | G8: =Assumptions!I83 -> 2029-30 | H8: =Assumptions!I84 -> 2030-31 | I8: =Assumptions!I85 -> 2031-32
A9: April | B9: ='Loan sch'!F24 -> 1.1666667e+08 | C9: ='Loan sch'!F36 -> 1.1666667e+08 | D9: ='Loan sch'!F48 -> 1.1666667e+08 | E9: ='Loan sch'!F60 -> 1.1666667e+08 | F9: ='Loan sch'!F72 -> 1.1666667e+08 | G9: ='Loan sch'!F84 | H9: ='Loan sch'!F96 | I9: ='Loan sch'!F108 -> 0
A10: May | B10: ='Loan sch'!F25 -> 1.1666667e+08 | C10: ='Loan sch'!F37 -> 1.1666667e+08 | D10: ='Loan sch'!F49 -> 1.1666667e+08 | E10: ='Loan sch'!F61 -> 1.1666667e+08 | F10: ='Loan sch'!F73 -> 1.1666667e+08 | G10: ='Loan sch'!F85 | H10: ='Loan sch'!F97 | I10: ='Loan sch'!F109 -> 0
A11: June | B11: ='Loan sch'!F26 -> 1.1666667e+08 | C11: ='Loan sch'!F38 -> 1.1666667e+08 | D11: ='Loan sch'!F50 -> 1.1666667e+08 | E11: ='Loan sch'!F62 -> 1.1666667e+08 | F11: ='Loan sch'!F74 -> 1.1666667e+08 | G11: ='Loan sch'!F86 | H11: ='Loan sch'!F98 | I11: ='Loan sch'!F110 -> 0
A12: July | B12: ='Loan sch'!F27 -> 1.1666667e+08 | C12: ='Loan sch'!F39 -> 1.1666667e+08 | D12: ='Loan sch'!F51 -> 1.1666667e+08 | E12: ='Loan sch'!F63 -> 1.1666667e+08 | F12: ='Loan sch'!F75 -> 1.1666667e+08 | G12: ='Loan sch'!F87 | H12: ='Loan sch'!F99 | I12: ='Loan sch'!F111 -> 0
A13: August | B13: ='Loan sch'!F28 -> 1.1666667e+08 | C13: ='Loan sch'!F40 -> 1.1666667e+08 | D13: ='Loan sch'!F52 -> 1.1666667e+08 | E13: ='Loan sch'!F64 -> 1.1666667e+08 | F13: ='Loan sch'!F76 -> 1.1666667e+08 | G13: ='Loan sch'!F88 | H13: ='Loan sch'!F100 | I13: ='Loan sch'!F112 -> 0
A14: September | B14: ='Loan sch'!F29 -> 1.1666667e+08 | C14: ='Loan sch'!F41 -> 1.1666667e+08 | D14: ='Loan sch'!F53 -> 1.1666667e+08 | E14: ='Loan sch'!F65 -> 1.1666667e+08 | F14: ='Loan sch'!F77 -> 1.1666667e+08 | G14: ='Loan sch'!F89 | H14: ='Loan sch'!F101 | I14: ='Loan sch'!F113 -> 0
A15: October | B15: ='Loan sch'!F30 -> 1.1666667e+08 | C15: ='Loan sch'!F42 -> 1.1666667e+08 | D15: ='Loan sch'!F54 -> 1.1666667e+08 | E15: ='Loan sch'!F66 -> 1.1666667e+08 | F15: ='Loan sch'!F78 | G15: ='Loan sch'!F90 | H15: ='Loan sch'!F102 | I15: ='Loan sch'!F114 -> 0
A16: November | B16: ='Loan sch'!F31 -> 1.1666667e+08 | C16: ='Loan sch'!F43 -> 1.1666667e+08 | D16: ='Loan sch'!F55 -> 1.1666667e+08 | E16: ='Loan sch'!F67 -> 1.1666667e+08 | F16: ='Loan sch'!F79 | G16: ='Loan sch'!F91 | H16: ='Loan sch'!F103 | I16: ='Loan sch'!F115 -> 0
A17: December | B17: ='Loan sch'!F32 -> 1.1666667e+08 | C17: ='Loan sch'!F44 -> 1.1666667e+08 | D17: ='Loan sch'!F56 -> 1.1666667e+08 | E17: ='Loan sch'!F68 -> 1.1666667e+08 | F17: ='Loan sch'!F80 | G17: ='Loan sch'!F92 | H17: ='Loan sch'!F104 | I17: ='Loan sch'!F116 -> 0
A18: January | B18: ='Loan sch'!F33 -> 1.1666667e+08 | C18: ='Loan sch'!F45 -> 1.1666667e+08 | D18: ='Loan sch'!F57 -> 1.1666667e+08 | E18: ='Loan sch'!F69 -> 1.1666667e+08 | F18: ='Loan sch'!F81 | G18: ='Loan sch'!F93 | H18: ='Loan sch'!F105 | I18: ='Loan sch'!F117 -> 0
A19: February | B19: ='Loan sch'!F34 -> 1.1666667e+08 | C19: ='Loan sch'!F46 -> 1.1666667e+08 | D19: ='Loan sch'!F58 -> 1.1666667e+08 | E19: ='Loan sch'!F70 -> 1.1666667e+08 | F19: ='Loan sch'!F82 | G19: ='Loan sch'!F94 | H19: ='Loan sch'!F106 | I19: ='Loan sch'!F118 -> 0
A20: March | B20: ='Loan sch'!F35 -> 1.1666667e+08 | C20: ='Loan sch'!F47 -> 1.1666667e+08 | D20: ='Loan sch'!F59 -> 1.1666667e+08 | E20: ='Loan sch'!F71 -> 1.1666667e+08 | F20: ='Loan sch'!F83 | G20: ='Loan sch'!F95 | H20: ='Loan sch'!F107 | I20: ='Loan sch'!F119 -> 0
A21: Total Term Loan Paid | B21: =SUM(B9:B20) -> 1400000000 | C21: =SUM(C9:C20) -> 1400000000 | D21: =SUM(D9:D20) -> 1400000000 | E21: =SUM(E9:E20) -> 1400000000 | F21: =SUM(F9:F20) -> 700000000 | G21: =SUM(G9:G20) -> 0 | H21: =SUM(H9:H20) -> 0 | I21: =SUM(I9:I20) -> 0
A22: Short Term Loan Outstanding | B22: =C21 -> 1400000000 | C22: =D21 -> 1400000000 | D22: =E21 -> 1400000000 | E22: =F21 -> 700000000 | F22: =G21 -> 0 | G22: =H21 -> 0 | H22: =I21 -> 0 | I22: 0
A27: Repayment Schedule - Proposed Term Loan
A29: Particulars | B29: ='Workings for PL BS 1'!#REF! -> #REF! | C29: ='Workings for PL BS 1'!C4 -> 0
A30: April
A31: May
A32: June
A33: July
A34: August
A35: September
A36: October
A37: November
A38: December
A39: January
A40: February
A41: March
A42: Total | B42: =SUM(B30:B41) -> 0 | C42: =SUM(C30:C41) -> 0
A46: 12 m
A47: 24 M
A48: 36 M
A49: 48 m

Sheet CFs
A3: PROJECTED CASH FLOW STATEMENTS
A5: Particulars | B5: ='Workings for PL BS 1'!D4 -> 2024-25 | C5: ='Workings for PL BS 1'!E4 -> 2025-26 | D5: ='Workings for PL BS 1'!F4 -> 2026-27 | E5: ='Workings for PL BS 1'!G4 -> 2027-28 | F5: ='Workings for PL BS 1'!H4 -> 2028-29 | G5: ='Workings for PL BS 1'!I4 -> 2029-30 | H5: ='Workings for PL BS 1'!J4 -> 2030-31 | I5: ='Workings for PL BS 1'!K4 -> 2031-32
A7: In flows:
A9: Profit before Bank Interest & Tax but after depreciation | B9: ='PL BS'!D37 -> 1.0448053e+10 | C9: ='PL BS'!E37 -> 1.3583677e+10 | D9: ='PL BS'!F37 -> 14453472500 | E9: ='PL BS'!G37 -> 15302148125 | F9: ='PL BS'!H37 -> 1.613285e+10 | G9: ='PL BS'!I37 -> 1.6948226e+10 | H9: ='PL BS'!J37 -> 1.7750602e+10 | I9: ='PL BS'!K37 -> 1.8541856e+10
A11: Increase in Depreciation | B11: ='CF workings'!B9 -> 9.1666667e+08 | C11: ='CF workings'!C9 -> 9.6458333e+08 | D11: ='CF workings'!D9 -> 822187500 | E11: ='CF workings'!E9 -> 700921875 | F11: ='CF workings'!F9 -> 5.9763984e+08 | G11: ='CF workings'!G9 -> 5.0966449e+08 | H11: ='CF workings'!H9 -> 4.3471838e+08 | I11: ='CF workings'!I9 -> 3.7086383e+08
A13: Increase in Term Loan | B13: ='CF workings'!B10 -> 6300000000 | C13: 0 | D13: 0 | E13: 0 | F13: 0 | G13: 0 | H13: 0 | I13: 0
A15: ='CF workings'!A11 -> Increase in working capital loan | B15: ='CF workings'!B11 -> 6241360000 | C15: ='CF workings'!C11 -> 37204960000 | D15: ='CF workings'!D11 -> 1553680000 | E15: ='CF workings'!E11 -> 0 | F15: ='CF workings'!F11 -> 0 | G15: ='CF workings'!G11 -> 0 | H15: ='CF workings'!H11 -> 0 | I15: ='CF workings'!I11 -> 0
A17: Increase In Capital | B17: ='CF workings'!B12 -> 6200000000 | C17: 0 | D17: 0 | E17: 0 | F17: 0 | G17: 0 | H17: 0 | I17: 0
A19: Increase in Capital during the year | B19: ='CF workings'!B36 -> 0 | C19: ='CF workings'!C36 -> 0 | D19: ='CF workings'!D36 -> 12507155000 | E19: ='CF workings'!E36 -> 0 | F19: ='CF workings'!F36 -> 0 | G19: ='CF workings'!G36 -> 0 | H19: ='CF workings'!H36 -> 0 | I19: ='CF workings'!I36 -> 0
B22: =SUM(B9:B21) -> 30106080000 | C22: =SUM(C9:C21) -> 51753220000 | D22: =SUM(D9:D21) -> 29336495000 | E22: =SUM(E9:E21) -> 16003070000 | F22: =SUM(F9:F21) -> 16730490000 | G22: =SUM(G9:G21) -> 17457890000 | H22: =SUM(H9:H21) -> 18185320000 | I22: =SUM(I9:I21) -> 18912720000
A24: Outflows:
A26: Increase in Capital expenditure | B26: ='CF workings'!B19 -> 7500000000 | C26: ='CF workings'!C19 -> 0 | D26: ='CF workings'!D19 -> 0 | E26: ='CF workings'!E19 -> 0 | F26: ='CF workings'!F19 -> 0 | G26: ='CF workings'!G19 -> 0 | H26: ='CF workings'!H19 -> 0 | I26: ='CF workings'!I19 -> 0
A28: Increase in Term Loan interest | B28: ='CF workings'!B20 -> 5.94125e+08 | C28: ='CF workings'!C20 -> 4.47125e+08 | D28: ='CF workings'!D20 -> 3.00125e+08 | E28: ='CF workings'!E20 -> 1.53125e+08 | F28: ='CF workings'!F20 -> 21437500 | G28: ='CF workings'!G20 -> 0 | H28: ='CF workings'!H20 -> 0 | I28: ='CF workings'!I20 -> 0
A30: ='CF workings'!A21 -> Increase in CC Loan interest | B30: ='CF workings'!B21 -> 4500000000 | C30: ='CF workings'!C21 -> 5.427e+09 | D30: ='CF workings'!D21 -> 5.427e+09 | E30: ='CF workings'!E21 -> 5.454135e+09 | F30: ='CF workings'!F21 -> 5.4814057e+09 | G30: ='CF workings'!G21 -> 5.5088127e+09 | H30: ='CF workings'!H21 -> 5.5363568e+09 | I30: ='CF workings'!I21 -> 5.5640386e+09
A32: Decrease in Term Loan | B32: ='CF workings'!B22 -> 1400000000 | C32: ='CF workings'!C22 -> 1400000000 | D32: ='CF workings'!D22 -> 1400000000 | E32: ='CF workings'!E22 -> 1400000000 | F32: ='CF workings'!F22 -> 700000000 | G32: ='CF workings'!G22 -> 0 | H32: ='CF workings'!H22 -> 0 | I32: ='CF workings'!I22 -> 0
A34: Increase in Recievables | B34: ='CF workings'!B23 -> 2478070000 | C34: ='CF workings'!C23 -> -3335430000 | D34: ='CF workings'!D23 -> 5779880000 | E34: ='CF workings'!E23 -> 696200000 | F34: ='CF workings'!F23 -> 737670000 | G34: ='CF workings'!G23 -> 779120000 | H34: ='CF workings'!H23 -> 820560000 | I34: ='CF workings'!I23 -> 862000000
A36: ='CF workings'!A24 -> Increase in Stock | B36: ='CF workings'!B24 -> 6669760000 | C36: ='CF workings'!C24 -> 51830240000 | D36: ='CF workings'!D24 -> 585000000 | E36: ='CF workings'!E24 -> 590850000 | F36: ='CF workings'!F24 -> 596760000 | G36: ='CF workings'!G24 -> 602720000 | H36: ='CF workings'!H24 -> 608760000 | I36: ='CF workings'!I24 -> 614840000
A38: Increase in Drawings | B38: ='CF workings'!B37 -> 2283315000 | C38: ='CF workings'!C37 -> 2637025000 | D38: ='CF workings'!D37 -> 0 | E38: ='CF workings'!E37 -> 3788710000 | F38: ='CF workings'!F37 -> 4.9829368e+09 | G38: ='CF workings'!G37 -> 5.5571373e+09 | H38: ='CF workings'!H37 -> 5.8779532e+09 | I38: ='CF workings'!I37 -> 6.7497114e+09
B41: =SUM(B26:B39) -> 25425270000 | C41: =SUM(C26:C39) -> 58405960000 | D41: =SUM(D26:D39) -> 13492005000 | E41: =SUM(E26:E39) -> 1.208302e+10 | F41: =SUM(F26:F39) -> 12520210000 | G41: =SUM(G26:G39) -> 12447790000 | H41: =SUM(H26:H39) -> 1.284363e+10 | I41: =SUM(I26:I39) -> 1.379059e+10
A43: Opening balance of cash | B43: =Assumptions!F124 -> 0 | C43: =+B47 -> 4680810000 | D43: =+C47 -> -1971930000 | E43: =+D47 -> 13872560000 | F43: =+E47 -> 17792610000 | G43: =+F47 -> 22002890000 | H43: =+G47 -> 27012990000 | I43: =+H47 -> 32354680000
A45: Net Surplus during the year | B45: =B22-B41 -> 4680810000 | C45: =C22-C41 -> -6652740000 | D45: =D22-D41 -> 15844490000 | E45: =E22-E41 -> 3.92005e+09 | F45: =F22-F41 -> 4210280000 | G45: =G22-G41 -> 5010100000 | H45: =H22-H41 -> 5.34169e+09 | I45: =I22-I41 -> 5.12213e+09
A47: Closing balance of cash | B47: ='Final workings'!B18 -> 4680810000 | C47: ='Final workings'!C18 -> -1971930000 | D47: ='Final workings'!D18 -> 13872560000 | E47: ='Final workings'!E18 -> 17792610000 | F47: ='Final workings'!F18 -> 22002890000 | G47: ='Final workings'!G18 -> 27012990000 | H47: ='Final workings'!H18 -> 32354680000 | I47: ='Final workings'!I18 -> 37476810000
A50: Back ground Working Notes: (Not to be visible to end user and Also not part of project report)
B51: =B43+B45 -> 4680810000 | C51: =C43+C45 -> -1971930000 | D51: =D43+D45 -> 13872560000 | E51: =E43+E45 -> 17792610000 | F51: =F43+F45 -> 22002890000 | G51: =G43+G45 -> 27012990000 | H51: =H43+H45 -> 32354680000 | I51: =I43+I45 -> 37476810000
B52: =B51-B47 -> 0 | C52: =C51-C47 -> 0 | D52: =D51-D47 -> 0 | E52: =E51-E47 -> 0 | F52: =F51-F47 -> 0 | G52: =G51-G47 -> 0 | H52: =H51-H47 -> 0 | I52: =I51-I47 -> 0

Sheet Funds Flow statement
B2: FUNDS FLOW STATEMENT
B4: Statement of Changes in Working capital
B6: PARTICULARS | C6: =Assumptions!I78 -> 2024-25 | D6: =Assumptions!I79 -> 2025-26 | E6: Changes in Working capital
B8: CURRENT ASSETS:
B10: ='PL BS'!A76 -> Closing stock / WIP | C10: ='PL BS'!D76 -> 6669760000 | D10: ='PL BS'!E76 -> 58500000000 | E10: =D10-C10 -> 51830240000
B11: ='PL BS'!A78 -> Recievables / Debtors | C11: ='PL BS'!D78 -> 2478070000 | D11: ='PL BS'!E78 -> -857360000 | E11: =D11-C11 -> -3335430000
B12: ='PL BS'!A80 -> Cash and Cash Equivalents | C12: ='PL BS'!D80 -> 4680810000 | D12: ='PL BS'!E80 -> -1971930000 | E12: =D12-C12 -> -6652740000
E13: =D13-C13 -> 0
B14: Total Current Assets (A) | C14: =SUM(C10:C13) -> 13828640000 | D14: =SUM(D10:D13) -> 55670710000 | E14: =SUM(E10:E13) -> 41842070000
B16: CURRENT LIABILITIES:
B18: ='PL BS'!A62 -> Working capital Loan | C18: ='PL BS'!D62 -> 6241360000 | D18: ='PL BS'!E62 -> 43446320000 | E18: =C19-D19 -> 0
B19: ='PL BS'!A64 -> Short Term Loan | C19: ='PL BS'!D64 -> 1400000000 | D19: ='PL BS'!E64 -> 1400000000 | E19: =C20-D20 -> 0
B21: Total Current Liabilities (B) | C21: =SUM(C17:C20) -> 7641360000 | D21: =SUM(D17:D20) -> 44846320000 | E21: =SUM(E18:E20) -> 0
B23: NET WORKING CAPITAL (A-B) | C23: =C14-C21 -> 6187280000 | D23: =D14-D21 -> 10824390000
B25: Increase in Working capital | C25: =D23-C23 -> 4637110000 | E25: =E14+E21 -> 41842070000
B28: PARTICULARS | C28: =Assumptions!I79 -> 2025-26 | D28: =Assumptions!I80 -> 2026-27 | E28: Changes in Working capital
B30: =B8 -> CURRENT ASSETS:
B32: =B10 -> Closing stock / WIP | C32: ='PL BS'!E76 -> 58500000000 | D32: ='PL BS'!F76 -> 59085000000 | E32: =D32-C32 -> 585000000
B33: =B11 -> Recievables / Debtors | C33: ='PL BS'!E78 -> -857360000 | D33: ='PL BS'!F78 -> 4922520000 | E33: =D33-C33 -> 5779880000
B34: =B12 -> Cash and Cash Equivalents | C34: ='PL BS'!E80 -> -1971930000 | D34: ='PL BS'!F80 -> 13872560000 | E34: =D34-C34 -> 15844490000
E35: =D35-C35 -> 0
B36: Total Current Assets (A) | C36: =SUM(C32:C35) -> 55670710000 | D36: =SUM(D32:D35) -> 77880080000 | E36: =SUM(E32:E35) -> 22209370000
B38: =B16 -> CURRENT LIABILITIES:
B40: ='PL BS'!A62 -> Working capital Loan | C40: ='PL BS'!E62 -> 43446320000 | D40: ='PL BS'!F62 -> 45000000000 | E40: =C40-D40 -> -1553680000
B41: ='PL BS'!A64 -> Short Term Loan | C41: ='PL BS'!E64 -> 1400000000 | D41: ='PL BS'!F64 -> 1400000000 | E41: =C41-D41 -> 0
B43: Total Current Liabilities (B) | C43: =SUM(C39:C42) -> 44846320000 | D43: =SUM(D39:D42) -> 46400000000 | E43: =SUM(E40:E42) -> -1553680000
B45: NET WORKING CAPITAL (A-B) | C45: =C36-C43 -> 10824390000 | D45: =D36-D43 -> 31480080000
B47: Increase in Working capital | C47: =D45-C45 -> 20655690000 | E47: =E36+E43 -> 20655690000
B50: PARTICULARS | C50: =Assumptions!I80 -> 2026-27 | D50: =Assumptions!I81 -> 2027-28 | E50: Changes in Working capital
B52: =B30 -> CURRENT ASSETS:
B54: =B32 -> Closing stock / WIP | C54: ='PL BS'!F76 -> 59085000000 | D54: ='PL BS'!G76 -> 59675850000 | E54: =D54-C54 -> 590850000
B55: =B33 -> Recievables / Debtors | C55: ='PL BS'!F78 -> 4922520000 | D55: ='PL BS'!G78 -> 5618720000 | E55: =D55-C55 -> 696200000
B56: =B34 -> Cash and Cash Equivalents | C56: ='PL BS'!F80 -> 13872560000 | D56: ='PL BS'!G80 -> 17792610000 | E56: =D56-C56 -> 3920050000
E57: =D57-C57 -> 0
B58: =B36 -> Total Current Assets (A) | C58: =SUM(C54:C57) -> 77880080000 | D58: =SUM(D54:D57) -> 83087180000 | E58: =SUM(E54:E57) -> 5207100000
B60: =B38 -> CURRENT LIABILITIES:
B62: ='PL BS'!A62 -> Working capital Loan | C62: ='PL BS'!F62 -> 45000000000 | D62: ='PL BS'!G62 -> 45000000000 | E62: =C62-D62 -> 0
B63: ='PL BS'!A64 -> Short Term Loan | C63: ='PL BS'!F64 -> 1400000000 | D63: ='PL BS'!G64 -> 700000000 | E63: =C63-D63 -> 700000000
B65: Total Current Liabilities (B) | C65: =SUM(C61:C64) -> 46400000000 | D65: =SUM(D61:D64) -> 45700000000 | E65: =SUM(E61:E64) -> 700000000
B67: NET WORKING CAPITAL (A-B) | C67: =C58-C65 -> 31480080000 | D67: =D58-D65 -> 37387180000
B69: Increase in Working capital | C69: =D67-C67 -> 5907100000 | E69: =E58+E65 -> 5907100000
B72: PARTICULARS | C72: =Assumptions!I81 -> 2027-28 | D72: =Assumptions!I82 -> 2028-29 | E72: Changes in Working capital
B74: =B52 -> CURRENT ASSETS:
B76: =B54 -> Closing stock / WIP | C76: ='PL BS'!G76 -> 59675850000 | D76: ='PL BS'!H76 -> 60272610000 | E76: =D76-C76 -> 596760000
B77: =B55 -> Recievables / Debtors | C77: ='PL BS'!G78 -> 5618720000 | D77: ='PL BS'!H78 -> 6356390000 | E77: =D77-C77 -> 737670000
B78: =B56 -> Cash and Cash Equivalents | C78: ='PL BS'!G80 -> 17792610000 | D78: ='PL BS'!H80 -> 22002890000 | E78: =D78-C78 -> 4210280000
B80: =B58 -> Total Current Assets (A) | C80: =SUM(C76:C79) -> 83087180000 | D80: =SUM(D76:D79) -> 88631890000 | E80: =SUM(E76:E79) -> 5544710000
B83: =B60 -> CURRENT LIABILITIES:
B85: ='PL BS'!A62 -> Working capital Loan | C85: ='PL BS'!G62 -> 45000000000 | D85: ='PL BS'!H62 -> 45000000000 | E85: =C85-D85 -> 0
B86: ='PL BS'!A64 -> Short Term Loan | C86: ='PL BS'!G64 -> 700000000 | D86: ='PL BS'!H64 -> 0 | E86: =C86-D86 -> 700000000
B88: Total Current Liabilities (B) | C88: =SUM(C84:C87) -> 45700000000 | D88: =SUM(D84:D87) -> 45000000000 | E88: =SUM(E84:E87) -> 700000000
B90: NET WORKING CAPITAL (A-B) | C90: =C80-C88 -> 37387180000 | D90: =D80-D88 -> 43631890000
B92: Increase in Working capital | C92: =D90-C90 -> 6244710000 | E92: =E80+E88 -> 6244710000
B95: PARTICULARS | C95: =Assumptions!I82 -> 2028-29 | D95: =Assumptions!I83 -> 2029-30 | E95: Changes in Working capital
B97: =B74 -> CURRENT ASSETS:
B99: =B76 -> Closing stock / WIP | C99: ='PL BS'!H76 -> 60272610000 | D99: ='PL BS'!I76 -> 60875330000 | E99: =D99-C99 -> 602720000
B100: =B77 -> Recievables / Debtors | C100: ='PL BS'!H78 -> 6356390000 | D100: ='PL BS'!I78 -> 7135510000 | E100: =D100-C100 -> 779120000
B101: =B78 -> Cash and Cash Equivalents | C101: ='PL BS'!H80 -> 22002890000 | D101: ='PL BS'!I80 -> 27012990000 | E101: =D101-C101 -> 5010100000
B103: =B80 -> Total Current Assets (A) | C103: =SUM(C99:C102) -> 88631890000 | D103: =SUM(D99:D102) -> 95023830000 | E103: =SUM(E99:E102) -> 6391940000
B106: =B83 -> CURRENT LIABILITIES:
B108: ='PL BS'!A62 -> Working capital Loan | C108: ='PL BS'!H62 -> 45000000000 | D108: ='PL BS'!I62 -> 45000000000 | E108: =C108-D108 -> 0
B109: ='PL BS'!A64 -> Short Term Loan | C109: ='PL BS'!H64 -> 0 | D109: ='PL BS'!I64 -> 0 | E109: =C109-D109 -> 0
B111: Total Current Liabilities (B) | C111: =SUM(C107:C110) -> 45000000000 | D111: =SUM(D107:D110) -> 45000000000 | E111: =SUM(E107:E110) -> 0
B113: NET WORKING CAPITAL (A-B) | C113: =C103-C111 -> 43631890000 | D113: =D103-D111 -> 50023830000
B115: Increase in Working capital | C115: =D113-C113 -> 6391940000 | E115: =E103+E111 -> 6391940000
B118: PARTICULARS | C118: =Assumptions!I83 -> 2029-30 | D118: =Assumptions!I84 -> 2030-31 | E118: Changes in Working capital
B120: =B97 -> CURRENT ASSETS:
B122: =B99 -> Closing stock / WIP | C122: ='PL BS'!I76 -> 60875330000 | D122: ='PL BS'!J76 -> 61484090000 | E122: =D122-C122 -> 608760000
B123: =B100 -> Recievables / Debtors | C123: ='PL BS'!I78 -> 7135510000 | D123: ='PL BS'!J78 -> 7956070000 | E123: =D123-C123 -> 820560000
B124: =B101 -> Cash and Cash Equivalents | C124: ='PL BS'!I80 -> 27012990000 | D124: ='PL BS'!J80 -> 32354680000 | E124: =D124-C124 -> 5341690000
B126: =B103 -> Total Current Assets (A) | C126: =SUM(C122:C125) -> 95023830000 | D126: =SUM(D122:D125) -> 101794840000 | E126: =SUM(E122:E125) -> 6771010000
B129: =B106 -> CURRENT LIABILITIES:
B131: ='PL BS'!A62 -> Working capital Loan | C131: ='PL BS'!I62 -> 45000000000 | D131: ='PL BS'!J62 -> 45000000000 | E131: =C131-D131 -> 0
B132: ='PL BS'!A64 -> Short Term Loan | C132: ='PL BS'!I64 -> 0 | D132: ='PL BS'!J64 -> 0 | E132: =C132-D132 -> 0
B134: Total Current Liabilities (B) | C134: =SUM(C130:C133) -> 45000000000 | D134: =SUM(D130:D133) -> 45000000000 | E134: =SUM(E130:E133) -> 0
B136: NET WORKING CAPITAL (A-B) | C136: =C126-C134 -> 50023830000 | D136: =D126-D134 -> 56794840000
B138: Increase in Working capital | C138: =D136-C136 -> 6771010000 | E138: =E126+E134 -> 6771010000
B144: PARTICULARS | C144: =Assumptions!I84 -> 2030-31 | D144: =Assumptions!I85 -> 2031-32 | E144: Changes in Working capital
B146: =B123 -> Recievables / Debtors
B148: ='PL BS'!A76 -> Closing stock / WIP | C148: ='PL BS'!J76 -> 61484090000 | D148: ='PL BS'!K76 -> 62098930000 | E148: =D148-C148 -> 614840000
B149: ='PL BS'!A78 -> Recievables / Debtors | C149: ='PL BS'!J78 -> 7956070000 | D149: ='PL BS'!K78 -> 8818070000 | E149: =D149-C149 -> 862000000
B150: ='PL BS'!A80 -> Cash and Cash Equivalents | C150: ='PL BS'!J80 -> 32354680000 | D150: ='PL BS'!K80 -> 37476810000 | E150: =D150-C150 -> 5122130000
B152: =B129 -> CURRENT LIABILITIES: | C152: =SUM(C148:C151) -> 101794840000 | D152: =SUM(D148:D151) -> 108393810000 | E152: =SUM(E148:E151) -> 6598970000
B155: =B132 -> Short Term Loan
B157: ='PL BS'!A62 -> Working capital Loan | C157: ='PL BS'!J62 -> 45000000000 | D157: ='PL BS'!K62 -> 45000000000 | E157: =C157-D157 -> 0
B158: ='PL BS'!A64 -> Short Term Loan | C158: ='PL BS'!J64 -> 0 | D158: ='PL BS'!K64 -> 0 | E158: =C158-D158 -> 0
B160: Total Current Liabilities (B) | C160: =SUM(C156:C159) -> 45000000000 | D160: =SUM(D156:D159) -> 45000000000 | E160: =SUM(E156:E159) -> 0
B162: NET WORKING CAPITAL (A-B) | C162: =C152-C160 -> 56794840000 | D162: =D152-D160 -> 63393810000
B164: Increase in Working capital | C164: =D162-C162 -> 6598970000 | E164: =E152+E160 -> 6598970000

Sheet MPBF 
A2: =Assumptions!I17 -> Doe Textiles
A3: =Assumptions!I8 -> John Doe
A4: =Assumptions!I16 -> 123 Industrial Area, City
A6: CALCULATION OF MAXIMUM PERMISSIBLE BANK FINANCE
A8: Method 1 : Working Capital method
A9: Particulars | B9: =IF('Final workings'!B7=0,"",Assumptions!I78) -> 2024-25 | C9: =IF(Assumptions!I63=0,"",Assumptions!I79) -> 2025-26 | D9: =Assumptions!I80 -> 2026-27 | E9: =Assumptions!I81 -> 2027-28 | F9: =Assumptions!I82 -> 2028-29 | G9: =Assumptions!I83 -> 2029-30 | H9: =Assumptions!I84 -> 2030-31 | I9: =Assumptions!I85 -> 2031-32
A11: 1. Total current assets | B11: =IF('Final workings'!B7=0,"",SUM('PL BS'!D75:D81)) -> 13828640000 | C11: =IF(Assumptions!I63=0,"",SUM('PL BS'!E75:E81)) -> 55670710000 | D11: =SUM('PL BS'!F75:F81) -> 77880080000 | E11: =SUM('PL BS'!G75:G81) -> 83087180000 | F11: =SUM('PL BS'!H75:H81) -> 88631890000 | G11: =SUM('PL BS'!I75:I81) -> 95023830000 | H11: =SUM('PL BS'!J75:J81) -> 101794840000 | I11: =SUM('PL BS'!K75:K81) -> 108393810000
A13: 2. Other current liabilities | B13: =IF('Final workings'!B7=0,"",SUM('PL BS'!D63:D65)) -> 1400000000 | C13: =IF(Assumptions!I63=0,"",SUM('PL BS'!E63:E65)) -> 1400000000 | D13: =SUM('PL BS'!F63:F65) -> 1400000000 | E13: =SUM('PL BS'!G63:G65) -> 700000000 | F13: =SUM('PL BS'!H63:H65) -> 0 | G13: =SUM('PL BS'!I63:I65) -> 0 | H13: =SUM('PL BS'!J63:J65) -> 0 | I13: =SUM('PL BS'!K63:K65) -> 0
A14: (Other than Working capital Loan )
A16: 3. Working capital gap | B16: =IF('Final workings'!B7=0,"",'MPBF '!B11-'MPBF '!B13) -> 12428640000 | C16: =IF(Assumptions!I63=0,"",+C11-C13) -> 54270710000 | D16: =+D11-D13 -> 76480080000 | E16: =+E11-E13 -> 82387180000 | F16: =+F11-F13 -> 88631890000 | G16: =+G11-G13 -> 95023830000 | H16: =+H11-H13 -> 101794840000 | I16: =+I11-I13 -> 108393810000
A18: 4. Min. stipulated Networking capital
A19: (25% of WCG excluding export | B19: =IF('Final workings'!B7=0,"",B16*0.25) -> 3107160000 | C19: =IF(Assumptions!I63=0,"",+C16*0.25) -> 13567677500 | D19: =+D16*0.25 -> 19120020000 | E19: =+E16*0.25 -> 20596795000 | F19: =+F16*0.25 -> 22157972500 | G19: =+G16*0.25 -> 23755957500 | H19: =+H16*0.25 -> 25448710000 | I19: =+I16*0.25 -> 27098452500
A20: receivables)
A22: 5. Actual/projected net working capital | B22: =IF(Assumptions!I62=0,"",SUM('PL BS'!D75:D81)-SUM('PL BS'!D61:D65)) -> 6187280000 | C22: =IF(Assumptions!I63=0,"",SUM('PL BS'!E75:E81)-SUM('PL BS'!E61:E65)) -> 10824390000 | D22: =SUM('PL BS'!F75:F81)-SUM('PL BS'!F61:F65) -> 31480080000 | E22: =SUM('PL BS'!G75:G81)-SUM('PL BS'!G61:G65) -> 37387180000 | F22: =SUM('PL BS'!H75:H81)-SUM('PL BS'!H61:H65) -> 43631890000 | G22: =SUM('PL BS'!I75:I81)-SUM('PL BS'!I61:I65) -> 50023830000 | H22: =SUM('PL BS'!J75:J81)-SUM('PL BS'!J61:J65) -> 56794840000 | I22: =SUM('PL BS'!K75:K81)-SUM('PL BS'!K61:K65) -> 63393810000
A24: 6.Item 3 minus item 4 | B24: =IF('Final workings'!B7=0,"",B16-B19) -> 9321480000 | C24: =IF(Assumptions!I63=0,"",+C16-C19) -> 40703032500 | D24: =+D16-D19 -> 57360060000 | E24: =+E16-E19 -> 61790385000 | F24: =+F16-F19 -> 66473917500 | G24: =+G16-G19 -> 71267872500 | H24: =+H16-H19 -> 76346130000 | I24: =+I16-I19 -> 81295357500
A26: 7.Item 3 minus item 5 | B26: =IF('Final workings'!B7=0,"",B16-B22) -> 6241360000 | C26: =IF(Assumptions!I63=0,"",C16-C22) -> 43446320000 | D26: =D16-D22 -> 45000000000 | E26: =E16-E22 -> 45000000000 | F26: =F16-F22 -> 45000000000 | G26: =G16-G22 -> 45000000000 | H26: =H16-H22 -> 45000000000 | I26: =I16-I22 -> 45000000000
A28: 8. Maximum permissible bank | B28: =IF(B24<B26,B24,B26) -> 6241360000 | C28: =IF(C24<C26,C24,C26) -> 40703032500 | D28: =IF(D24<D26,D24,D26) -> 45000000000 | E28: =IF(E24<E26,E24,E26) -> 45000000000 | F28: =IF(F24<F26,F24,F26) -> 45000000000 | G28: =IF(G24<G26,G24,G26) -> 45000000000 | H28: =IF(H24<H26,H24,H26) -> 45000000000 | I28: =IF(I24<I26,I24,I26) -> 45000000000
A29: finance(lower of 6 or 7 )
A33: Method 2 : Total Current Assets Method
A34: Particulars | B34: =IF(Assumptions!I62=0,"",+B9) -> 2024-25 | C34: =IF(Assumptions!I63=0,"",+C9) -> 2025-26 | D34: =+D9 -> 2026-27 | E34: =+E9 -> 2027-28 | F34: =+F9 -> 2028-29 | G34: =+G9 -> 2029-30 | H34: =+H9 -> 2030-31 | I34: =+I9 -> 2031-32
A36: 1. Total current assets | B36: =IF(Assumptions!I62=0,"",B11) -> 13828640000 | C36: =IF(Assumptions!I63=0,"",+SUM('Workings for PL BS 1'!E35:E37)) -> 5.5670711e+10 | D36: =D11 -> 77880080000 | E36: =E11 -> 83087180000 | F36: =F11 -> 88631890000 | G36: =G11 -> 95023830000 | H36: =H11 -> 101794840000 | I36: =I11 -> 108393810000
A38: 2. Other current liabilities | B38: =IF(Assumptions!I62=0,"",B13) -> 1400000000 | C38: =IF(Assumptions!I63=0,"",C13) -> 1400000000 | D38: =D13 -> 1400000000 | E38: =E13 -> 700000000 | F38: =F13 -> 0 | G38: =G13 -> 0 | H38: =H13 -> 0 | I38: =I13 -> 0
A39: (Other than Working capital Loan )
A41: 3. Working capital gap | B41: =IF(Assumptions!I62=0,"",+B36-B38) -> 12428640000 | C41: =IF(Assumptions!I63=0,"",+C36-C38) -> 5.4270711e+10 | D41: =+D36-D38 -> 76480080000 | E41: =+E36-E38 -> 82387180000 | F41: =+F36-F38 -> 88631890000 | G41: =+G36-G38 -> 95023830000 | H41: =+H36-H38 -> 101794840000 | I41: =+I36-I38 -> 108393810000
A43: 4. Min. stipulated Networking capital
A44: (25% of Current Assets) | B44: =IF(Assumptions!I62=0,"",+B36*0.25) -> 3457160000 | C44: =IF(Assumptions!I63=0,"",+C36*0.25) -> 1.3917678e+10 | D44: =+D36*0.25 -> 19470020000 | E44: =+E36*0.25 -> 20771795000 | F44: =+F36*0.25 -> 22157972500 | G44: =+G36*0.25 -> 23755957500 | H44: =+H36*0.25 -> 25448710000 | I44: =+I36*0.25 -> 27098452500
A47: 5. Actual/projected net working capital | B47: =B22 -> 6187280000 | C47: =C22 -> 10824390000 | D47: =D22 -> 31480080000 | E47: =E22 -> 37387180000 | F47: =F22 -> 43631890000 | G47: =G22 -> 50023830000 | H47: =H22 -> 56794840000 | I47: =I22 -> 63393810000
A49: 6.Item 3 minus item 4 | B49: =IF(Assumptions!I62=0,"",+B41-B44) -> 8971480000 | C49: =IF(Assumptions!I63=0,"",+C41-C44) -> 4.0353033e+10 | D49: =+D41-D44 -> 57010060000 | E49: =+E41-E44 -> 61615385000 | F49: =+F41-F44 -> 66473917500 | G49: =+G41-G44 -> 71267872500 | H49: =+H41-H44 -> 76346130000 | I49: =+I41-I44 -> 81295357500
A51: 7.Item 3 minus item 5 | B51: =IF(Assumptions!I62=0,"",B41-B47) -> 6241360000 | C51: =IF(Assumptions!I63=0,"",C41-C47) -> 4.3446321e+10 | D51: =D41-D47 -> 45000000000 | E51: =E41-E47 -> 45000000000 | F51: =F41-F47 -> 45000000000 | G51: =G41-G47 -> 45000000000 | H51: =H41-H47 -> 45000000000 | I51: =I41-I47 -> 45000000000
A53: 8. Maximum permissible bank | B53: =IF(B49<B51,B49,B51) -> 6241360000 | C53: =IF(C49<C51,C49,C51) -> 4.0353033e+10 | D53: =IF(D49<D51,D49,D51) -> 45000000000 | E53: =IF(E49<E51,E49,E51) -> 45000000000 | F53: =IF(F49<F51,F49,F51) -> 45000000000 | G53: =IF(G49<G51,G49,G51) -> 45000000000 | H53: =IF(H49<H51,H49,H51) -> 45000000000 | I53: =IF(I49<I51,I49,I51) -> 45000000000
A54: finance(lower of 6 or 7 )

Sheet Nayak
A2: =IRR!B2 -> Doe Textiles
A3: =IRR!B3 -> John Doe
A4: =IRR!B4 -> 123 Industrial Area, City
A7: WORKING CAPITAL ASSESSMENT - TURNOVER METHOD
A8: (NAYAK COMMITTEE RECOMONDATIONS)
A11: PARTICULARS | B11: =IF('Final workings'!B7=0,"",Assumptions!I78) -> 2024-25 | C11: =IF(Assumptions!I63=0,"",'MPBF '!C9) -> 2025-26 | D11: ='MPBF '!D9 -> 2026-27 | E11: ='MPBF '!E9 -> 2027-28 | F11: ='MPBF '!F9 -> 2028-29 | G11: ='MPBF '!G9 -> 2029-30 | H11: ='MPBF '!H9 -> 2030-31 | I11: ='MPBF '!I9 -> 2031-32
A13: Turnover | B13: =IF('Final workings'!B7=0,"",'PL BS'!D14) -> 27534150000 | C13: =IF(Assumptions!I63=0,"",'PL BS'!E14) -> -8573600000 | D13: ='PL BS'!F14 -> 44750180000 | E13: ='PL BS'!G14 -> 46822650000 | F13: ='PL BS'!H14 -> 48895300000 | G13: ='PL BS'!I14 -> 50967900000 | H13: ='PL BS'!J14 -> 53040460000 | I13: ='PL BS'!K14 -> 55112960000
A15: Working Capital Requirment | B15: =IF('Final workings'!B7=0,"",B13*25%) -> 6883537500 | C15: =IF(Assumptions!I63=0,"",C13*25%) -> -2143400000 | D15: =D13*25% -> 11187545000 | E15: =E13*25% -> 11705662500 | F15: =F13*25% -> 12223825000 | G15: =G13*25% -> 12741975000 | H15: =H13*25% -> 13260115000 | I15: =I13*25% -> 13778240000
A16: (25% of Turnover)
A18: Minimum WC Limit | B18: =IF('Final workings'!B7=0,"",B15*80%) -> 5506830000 | C18: =IF(Assumptions!I63=0,"",C15*80%) -> -1714720000 | D18: =D15*80% -> 8950036000 | E18: =E15*80% -> 9364530000 | F18: =F15*80% -> 9779060000 | G18: =G15*80% -> 10193580000 | H18: =H15*80% -> 10608092000 | I18: =I15*80% -> 11022592000
A19: (80%of WC Requirment)
A21: Drawing Power | B21: =IF('Final workings'!B7=0,"",'PL BS'!D62) -> 6241360000 | C21: =IF(Assumptions!I63=0,"",'PL BS'!E62) -> 43446320000 | D21: ='PL BS'!F62 -> 45000000000 | E21: ='PL BS'!G62 -> 45000000000 | F21: ='PL BS'!H62 -> 45000000000 | G21: ='PL BS'!I62 -> 45000000000 | H21: ='PL BS'!J62 -> 45000000000 | I21: ='PL BS'!K62 -> 45000000000
A23: Maximum Bank CC Loan | B23: =IF(B18<B21,B18,B21) -> 5506830000 | C23: =IF(C18<C21,C18,C21) -> -1714720000 | D23: =IF(D18<D21,D18,D21) -> 8950036000 | E23: =IF(E18<E21,E18,E21) -> 9364530000 | F23: =IF(F18<F21,F18,F21) -> 9779060000 | G23: =IF(G18<G21,G18,G21) -> 10193580000 | H23: =IF(H18<H21,H18,H21) -> 10608092000 | I23: =IF(I18<I21,I18,I21) -> 11022592000
A27: Notes :
A28: 1. Maximum Working capital Limit Must not exceed Drawing power .
A29: 2. Four Operating cycles per Annum is Assumed.

Sheet IRR
B2: =Assumptions!I17 -> Doe Textiles
B3: =Assumptions!I8 -> John Doe
B4: =Assumptions!I16 -> 123 Industrial Area, City
B6: INTERNAL RATE OF RETURN (IRR)
B8: PARTICULARS | G8: Amount (Rs)
B10: CASH OUTFLOWS | G10: =-'project cost'!C20*100000 -> -57000000000
B13: CASH INFLOWS
B15: =Assumptions!I78 -> 2024-25 | G15: =CFs!B45 -> 4680810000
B17: =Assumptions!I79 -> 2025-26 | G17: =CFs!C45 -> -6652740000
B19: =Assumptions!I80 -> 2026-27 | G19: =CFs!D45 -> 15844490000
B21: =Assumptions!I81 -> 2027-28 | G21: =CFs!E45 -> 3.92005e+09
B23: =Assumptions!I82 -> 2028-29 | G23: =CFs!F45 -> 4210280000
B25: =Assumptions!I83 -> 2029-30 | G25: =CFs!G45 -> 5010100000
B27: =Assumptions!I84 -> 2030-31 | G27: =CFs!H45 -> 5.34169e+09
B29: =Assumptions!I85 -> 2031-32 | G29: =CFs!I45 -> 5.12213e+09
B31: INTERNAL RATE OF RETURN (IRR) | G31: =+IRR((G10:G29)) -> -0.079220216

Sheet Gaurantors
A3: PARTICULARS OF GUARANTOR/S
A5: Particulars | B5: 1 | C5: 2 | D5: 3 | E5: 4 | F5: 5 | G5: 6 | H5: 7 | I5: 8
A7: Name of the Guarantor | B7: Yeddula Vijaya Bhaskar | C7: K.Sunil Kumar | D7: H Ganganna | E7: D.R.Jayasheela | F7: V.Yesodamma | G7: J.Malleswari | H7: Y.Lakshmi Kanthamma | I7: D.Ammulu
A9: Fathers/Husbands Name | B9: S/o. Y Raja reddy | C9: S/o.K.Sudheer | D9: Plot No.401, SV Pride | E9: W/O.K.Sunil Kumar | F9: W/o.Namdev | G9: 22-69/4-1 | H9: W/o.Y.Raja Reddy | I9: Flat No.301, MIGH - 5
B10: E-136, RTPP, Kalamalla colony, | C10: Plot No.72, LF Nagar | D10: Birla Compound, | E10: Flat No.72, LF Nagar | F10: # 16-5-400 | G10: Op.KVR college | H10: E-136, RTPP, Kalamalla colony, | I10: Udaynagar Colony
B11: RTPP, kalamalla, | C11: Tirupati Rural | D11: Kurnool | E11: Tirupati Rural | F11: Kasturibai Lane | G11: Nandigama | H11: RTPP, kalamalla, | I11: BK Guda
B12: Yerraguntla Mandal, | C12: Chittoor Dt - 517502 | D12: Kurnool Dt. | E12: Chittoor Dt - 517502 | F12: Tirupati - 517501 | G12: Krishna Dt. | H12: Yerraguntla Mandal, | I12: Hydarabad - 500038
B13: Kadapa Dt.(A.P.) | H13: Kadapa Dt.(A.P.)
A15: Relationship with Applicant
A17: Date of Birth | B17: 26785 | C17: 26088 | D17: 25633 | E17: 27837 | F17: 16834 | H17: 60Years | I17: 28970
A19: Gender | B19: Male | C19: Male | D19: Male | E19: Female | F19: Female | G19: Female | H19: Female | I19: Female
A21: Marital Status | B21: Married | C21: Married | D21: Married | E21: Married | F21: Married | G21: Married | H21: Married | I21: Married
A23: Educational Qualifications | B23: B.Tech | C23: Diploma | D23: B.Tech, MBA | E23: MA, B.Ed | F23: SSC | H23: ----- | I23: M.Tech, MBA
A25: Occupations | B25: Employee, RTPP, | C25: Employee | D25: Employee ADE, APTRANSCO | E25: School Asst. | F25: House Wife | G25: House Wife | H25: House Wife | I25: Employee (BSNL)
A27: PAN | B27: AAYPY9926D | C27: AKWPK4001H | D27: ABFPH8341H | E27: AJGPJ3825P | F27: ----- | G27: ARRPJ7908G | H27: ----- | I27: AGHPA6225C
A29: Pass Port No | B29: ----- | C29: J8977476 | E29: ----- | F29: ----- | H29: ----- | I29: -----
A31: Voter Card No. | B31: RGS0012344 | C31: AYM0026039 | E31: AYM0047175 | F31: ----- | H31: -----
A33: Annual Income | B33: 750000 | C33: 200000 | D33: 750000 | E33: 300000 | F33: 100000 | H33: ----- | I33: 500000
A35: Net worth (Rs.in lakhs) | B35: 30 | C35: 30.61 | D35: 25 | E35: 30.61 | F35: 45.62 | G35: 18.98 | H35: 45.1 | I35: 21.3

Sheet BEP analysis
A1: ='Workings for PL BS 1'!A1:D1 -> STEP 2 : BACK GROUND CALCULATION . NOT TO BE VISIBLE TO CUSTOMER
A2: ='Workings for PL BS 1'!#REF! -> #REF!
A3: ='Workings for PL BS 1'!#REF! -> #REF!
A5: CALCULATION OF B.E.P.
A7: Particulars | B7: ='Workings for PL BS 1'!#REF! -> #REF! | C7: ='Workings for PL BS 1'!#REF! -> #REF! | D7: ='Workings for PL BS 1'!#REF! -> #REF! | E7: ='Workings for PL BS 1'!#REF! -> #REF! | F7: ='Workings for PL BS 1'!#REF! -> #REF! | G7: ='Workings for PL BS 1'!#REF! -> #REF!
A11: Sales | B11: =#REF! -> #REF! | C11: =#REF! -> #REF! | D11: =#REF! -> #REF! | E11: =#REF! -> #REF! | F11: =#REF! -> #REF! | G11: =#REF! -> #REF!
A13: Variable Exp
A14: Materials | B14: =#REF! -> #REF! | C14: =#REF! -> #REF! | D14: =#REF! -> #REF! | E14: =#REF! -> #REF! | F14: =#REF! -> #REF! | G14: =#REF! -> #REF!
A15: Power & Fuel | B15: =#REF! -> #REF! | C15: =#REF! -> #REF! | D15: =#REF! -> #REF! | E15: =#REF! -> #REF! | F15: =#REF! -> #REF! | G15: =#REF! -> #REF!
A16: Direct Labour | B16: =#REF! -> #REF! | C16: =#REF! -> #REF! | D16: =#REF! -> #REF! | E16: =#REF! -> #REF! | F16: =#REF! -> #REF! | G16: =#REF! -> #REF!
A19: Tota Variable Exp. | B19: =SUM(B14:B18) -> #REF! | C19: =SUM(C14:C18) -> #REF! | D19: =SUM(D14:D18) -> #REF! | E19: =SUM(E14:E18) -> #REF! | F19: =SUM(F14:F18) -> #REF! | G19: =SUM(G14:G18) -> #REF!
A21: Contribution | B21: =B11-B19 -> #REF! | C21: =C11-C19 -> #REF! | D21: =D11-D19 -> #REF! | E21: =E11-E19 -> #REF! | F21: =F11-F19 -> #REF! | G21: =G11-G19 -> #REF!
A23: P/V ratio | B23: =B21/B11 -> #REF! | C23: =C21/C11 -> #REF! | D23: =D21/D11 -> #REF! | E23: =E21/E11 -> #REF! | F23: =F21/F11 -> #REF! | G23: =G21/G11 -> #REF!
A25: Fixed Expenses
A27: Interest | B27: =#REF! -> #REF! | C27: =#REF! -> #REF! | D27: =#REF! -> #REF! | E27: =#REF! -> #REF! | F27: =#REF! -> #REF! | G27: =#REF! -> #REF!
A28: Depreciation | B28: =#REF! -> #REF! | C28: =#REF! -> #REF! | D28: =#REF! -> #REF! | E28: =#REF! -> #REF! | F28: =#REF! -> #REF! | G28: =#REF! -> #REF!
A29: Administrative Exp. | B29: =#REF! -> #REF! | C29: =#REF! -> #REF! | D29: =#REF! -> #REF! | E29: =#REF! -> #REF! | F29: =#REF! -> #REF! | G29: =#REF! -> #REF!
A32: Total Fixed Exp. | B32: =SUM(B27:B31) -> #REF! | C32: =SUM(C27:C31) -> #REF! | D32: =SUM(D27:D31) -> #REF! | E32: =SUM(E27:E31) -> #REF! | F32: =SUM(F27:F31) -> #REF! | G32: =SUM(G27:G31) -> #REF!
A34: BEP Sales | B34: =B32/B23 -> #REF! | C34: =C32/C23 -> #REF! | D34: =D32/D23 -> #REF! | E34: =E32/E23 -> #REF! | F34: =F32/F23 -> #REF! | G34: =G32/G23 -> #REF!
A36: Sales at 100% Operating Level | B36: =#REF!+#REF! -> #REF! | C36: =B36 -> #REF! | D36: =C36 -> #REF! | E36: =D36 -> #REF! | F36: =E36 -> #REF! | G36: =F36 -> #REF!
A38: BEP | B38: =B34/B36 -> #REF! | C38: =C34/C36 -> #REF! | D38: =D34/D36 -> #REF! | E38: =E34/E36 -> #REF! | F38: =F34/F36 -> #REF! | G38: =G34/G36 -> #REF!

Sheet Sales
A2: STATEMENT SHOWING CALCULATION OF SALES,PRODUCTION AND CLOSING STOCK
B4: Year
B5: ='Workings for PL BS 1'!#REF! -> #REF! | C5: ='Workings for PL BS 1'!C4 -> 0 | D5: ='Workings for PL BS 1'!#REF! -> #REF! | E5: ='Workings for PL BS 1'!#REF! -> #REF! | F5: ='Workings for PL BS 1'!D4 -> 2024-25 | G5: 2019-20
A7: Utilised Capacity | B7: 0 | C7: 0.75 | D7: 0.85 | E7: 0.95 | F7: 1 | G7: 1
A9: Granuels Price | B9: 0 | C9: 55 | D9: 60 | E9: 60 | F9: 65 | G9: 65
A11: LD Covers Price | B11: 0 | C11: 70 | D11: 75 | E11: 75 | F11: 90 | G11: 90
A13: Output
A15: Granuels | B15: =F34*$B$7 -> 0 | C15: =F34*$C$7 -> 229500 | D15: =F34*$D$7 -> 260100 | E15: =F34*$E$7 -> 290700 | F15: =F34*$F$7 -> 306000 | G15: =F34*$F$7 -> 306000
A17: LD Covers | B17: =F36*$B$7 -> 0 | C17: =F36*$C$7 -> 40500 | D17: =F36*$D$7 -> 45900 | E17: =F36*$E$7 -> 51300 | F17: =F36*$F$7 -> 54000 | G17: =F36*$F$7 -> 54000
A20: Sales
A22: Granuels | B22: =B15*B9 -> 0 | C22: =C15*C9 -> 12622500 | D22: =D15*D9 -> 15606000 | E22: =E15*E9 -> 17442000 | F22: =F15*F9 -> 19890000 | G22: =G15*G9 -> 19890000
A24: LD Covers | B24: =B17*B11 -> 0 | C24: =C17*C11 -> 2835000 | D24: =D17*D11 -> 3442500 | E24: =E17*E11 -> 3847500 | F24: =F17*F11 -> 4860000 | G24: =G17*G11 -> 4860000
A26: Total | B26: =B22+B24 -> 0 | C26: =770000*12 -> 9240000 | D26: =800000*12 -> 9600000 | E26: =850000*12 -> 10200000 | F26: =E26*1.1 -> 11220000 | G26: =F26*1.2 -> 13464000
A30: Full Production in Kgs | B30: 1600 Kgs Per Day*25 days*12 Months | F30: =1200*25*12 -> 360000
A32: Out of Above
A34: Granuels 85% | F34: =F30*0.85 -> 306000
A36: LD Covers 15 % | F36: =F30-F34 -> 54000
A39: Purchases
A40: Waste Paper | B40: =(B15+B17)/0.9*110*32 -> 0 | C40: =C26*70% -> 6468000 | D40: =D26*70% -> 6720000 | E40: =E26*70% -> 7140000 | F40: =F26*70% -> 7854000 | G40: =G26*70% -> 9424800
A42: Closing Stock 10% of | B42: =B40*0.1 -> 0 | C42: =C40*0.1 -> 646800 | D42: =D40*0.1 -> 672000 | E42: =E40*0.1 -> 714000 | F42: =F40*0.1 -> 785400 | G42: =G40*0.1 -> 942480
A43: purchases
A45: Over heads | B45: =B17*2 -> 0 | C45: =C17*5 -> 202500 | D45: =D17*5 -> 229500 | E45: =E17*5 -> 256500 | F45: =F17*5 -> 270000 | G45: =G17*5 -> 270000

Sheet MIRR
B2: =Assumptions!I17 -> Doe Textiles
B3: =Assumptions!I8 -> John Doe
B4: =Assumptions!I16 -> 123 Industrial Area, City
B6: MODIFIED INTERNAL RATE OF RETURN (MIRR)
B8: PARTICULARS | G8: Amount (Rs)
B10: CASH OUTFLOWS | G10: =-'project cost'!C20*100000 -> -57000000000
B13: CASH INFLOWS
B15: =Assumptions!I78 -> 2024-25 | G15: =CFs!B45 -> 4680810000
B17: =Assumptions!I79 -> 2025-26 | G17: =CFs!C45 -> -6652740000
B19: =Assumptions!I80 -> 2026-27 | G19: =CFs!D45 -> 15844490000
B21: =Assumptions!I81 -> 2027-28 | G21: =CFs!E45 -> 3.92005e+09
B23: =Assumptions!I82 -> 2028-29 | G23: =CFs!F45 -> 4210280000
B25: =Assumptions!I83 -> 2029-30 | G25: =CFs!G45 -> 5010100000
B27: =Assumptions!I84 -> 2030-31 | G27: =CFs!H45 -> 5.34169e+09
B29: =Assumptions!I85 -> 2031-32 | G29: =CFs!I45 -> 5.12213e+09
B31: MODIFIED INTERNAL RATE OF RETURN (MIRR) | G31: =MIRR(G10:G30,Assumptions!I45,Assumptions!F129) -> 0.017067426
B35: Note:
B36: Reinvestment Rate is assumed at | E36: =Assumptions!F129 -> 0.135

Sheet WACC
B2: =Assumptions!I17 -> Doe Textiles
B3: =Assumptions!I8 -> John Doe
B4: =Assumptions!I16 -> 123 Industrial Area, City
B7: Calculation of Weighted Average Cost of Capital (WACC)
B10: Particulars | C10: Sources of Funds (Rs in Lacs) | D10: Portion % | E10: Cost | F10: WACC
B12: Equity Capital | C12: ='project cost'!C27 -> 57000 | D12: =C12/C19 -> 0.1 | E12: =Assumptions!F128 -> 0.1 | F12: =D12*E12 -> 0.01
B14: Term Loan | C14: ='project cost'!C29 -> 63000 | D14: =C14/C19 -> 0.11052632 | E14: =Assumptions!I45 -> 0.105 | F14: =D14*E14*(1-30%) -> 0.0081236842
B16: Working capital Loan | C16: ='project cost'!C31 -> 450000 | D16: =C16/C19 -> 0.78947368 | E16: =Assumptions!I52 -> 0.12 | F16: =D16*E16*(1-30%) -> 0.066315789
B19: Total | C19: =SUM(C12:C16) -> 570000 | F19: =SUM(F11:F17) -> 0.084439474
B22: WACC (Minimum Return Required or Cost of Money) is | E22: =F19 -> 0.084439474

Sheet Profitability Index
B2: =Assumptions!I17 -> Doe Textiles
B3: =Assumptions!I8 -> John Doe
B4: =Assumptions!I16 -> 123 Industrial Area, City
B6: PROFITABILITY INDEX
B8: PARTICULARS | G8: Amount (Rs)
B10: CASH OUTFLOWS | G10: =-'project cost'!C20*100000 -> -57000000000
B13: CASH INFLOWS
B15: =Assumptions!I78 -> 2024-25 | G15: =CFs!B45 -> 4680810000
B17: =Assumptions!I79 -> 2025-26 | G17: =CFs!C45 -> -6652740000
B19: =Assumptions!I80 -> 2026-27 | G19: =CFs!D45 -> 15844490000
B21: =Assumptions!I81 -> 2027-28 | G21: =CFs!E45 -> 3.92005e+09
B23: =Assumptions!I82 -> 2028-29 | G23: =CFs!F45 -> 4210280000
B25: =Assumptions!I83 -> 2029-30 | G25: =CFs!G45 -> 5010100000
B27: =Assumptions!I84 -> 2030-31 | G27: =CFs!H45 -> 5.34169e+09
B29: =Assumptions!I85 -> 2031-32 | G29: =CFs!I45 -> 5.12213e+09
B31: PROFITABILITY INDEX | G31: =NPV(Assumptions!I45,'Profitability Index'!G15:G30)/ABS('Profitability Index'!G10) -> 0.41101457
B34: From the above PI arived , Every 1 Rs invested in this project creates | F34: =G31-1 -> -0.58898543 | G34: Additional Value

Sheet NPV
B2: =Assumptions!I17 -> Doe Textiles
B3: =Assumptions!I8 -> John Doe
B4: =Assumptions!I16 -> 123 Industrial Area, City
B7: PRESENT VALUE OF FUTURE CASH FLOWS AND NET PRESENT VALUE
B9: PARTICULARS | G9: Amount (Rs)
B11: CASH INFLOWS
B13: =Assumptions!I78 -> 2024-25 | G13: =CFs!B45 -> 4680810000
B15: =Assumptions!I79 -> 2025-26 | G15: =CFs!C45 -> -6652740000
B17: =Assumptions!I80 -> 2026-27 | G17: =CFs!D45 -> 15844490000
B19: =Assumptions!I81 -> 2027-28 | G19: =CFs!E45 -> 3.92005e+09
B21: =Assumptions!I82 -> 2028-29 | G21: =CFs!F45 -> 4210280000
B23: =Assumptions!I83 -> 2029-30 | G23: =CFs!G45 -> 5010100000
B25: =Assumptions!I84 -> 2030-31 | G25: =CFs!H45 -> 5.34169e+09
B27: =Assumptions!I85 -> 2031-32 | G27: =CFs!I45 -> 5.12213e+09
B29: PRESENT VALUE OF FUTURE CASH FLOWS | G29: =NPV(Assumptions!I45,NPV!G13:G28) -> 2.342783e+10
B31: CASH OUTFLOWS | G31: =Assumptions!I41*100000 -> 57500000000
B33: NET PRESENT VALUE | G33: =G29-G31 -> -3.407217e+10
B36: Note :
B37: Cash flows Discounted at Bank Interest Rate.

Sheet Payback period I
C2: =Assumptions!I17 -> Doe Textiles
C3: =Assumptions!I8 -> John Doe
C4: =Assumptions!I16 -> 123 Industrial Area, City
C6: INVESTMENT PAYBACK PERIOD (SIMPLE METHOD)
B8: YEAR | C8: PARTICULARS | G8: Amount (Rs) | H8: Cummulative Cash flows (Rs)
B10: 0 | C10: CASH OUTFLOWS | G10: =-'project cost'!C20*100000 -> -57000000000
B11: 1 | C11: CASH INFLOWS | E11: =Assumptions!I78 -> 2024-25 | G11: =CFs!B45 -> 4680810000 | H11: =G11+G10 -> -52319190000
B12: 2 | E12: =Assumptions!I79 -> 2025-26 | G12: =CFs!C45 -> -6652740000 | H12: =H11+G12 -> -58971930000 | M12: If Excel 365/2021
B13: 3 | E13: =Assumptions!I80 -> 2026-27 | G13: =CFs!D45 -> 15844490000 | H13: =H12+G13 -> -43127440000 | M13: =LET(k,MATCH(TRUE,G1:G11>0,0),(k-1)+ABS(INDEX(G1:G11,k-1))/INDEX(F1:F11,k)) | V13: This formulae automatically detect k (the year of recovery).
B14: 4 | E14: =Assumptions!I81 -> 2027-28 | G14: =CFs!E45 -> 3.92005e+09 | H14: =H13+G14 -> -39207390000
B15: 5 | E15: =Assumptions!I82 -> 2028-29 | G15: =CFs!F45 -> 4210280000 | H15: =H14+G15 -> -34997110000 | Q15: OR
B16: 6 | E16: =Assumptions!I83 -> 2029-30 | G16: =CFs!G45 -> 5010100000 | H16: =H15+G16 -> -29987010000
B17: 7 | E17: =Assumptions!I84 -> 2030-31 | G17: =CFs!H45 -> 5.34169e+09 | H17: =H16+G17 -> -24645320000 | M17: If Excel 97-2003
B18: 8 | E18: =Assumptions!I85 -> 2031-32 | G18: =CFs!I45 -> 5.12213e+09 | H18: =H17+G18 -> -1.952319e+10 | M18: =(MATCH(TRUE,H11:H18>0,0)-1) + ABS(INDEX(H11:H18,MATCH(TRUE,H11:H18>0,0)-1))/INDEX(G10:G18,MATCH(TRUE,H11:H18>0,0))
M19: After typing the above, press CTRL+SHIFT+ENTER instead of just Enter.
C20: PAYBACK PERIOD (YEARS) | H20: {=(MATCH(TRUE,H10:H18>0,0)-1) + ABS(INDEX(H10:H18,MATCH(TRUE,H10:H18>0,0)-1))/INDEX(G10:G18,MATCH(TRUE,H10:H18>0,0))} -> #N/A

Sheet Payback period II
B2: =Assumptions!I17 -> Doe Textiles
B3: =Assumptions!I8 -> John Doe
B4: =Assumptions!I16 -> 123 Industrial Area, City
B6: INVESTMENT PAYBACK PERIOD (DISCOUNTED CASHFLOWS METHOD)
B8: YEAR | C8: PARTICULARS | F8: Amount (Rs) | G8: Discounted Cash Flows (Rs) | H8: Cummulative Discounted Cash flows (Rs)
B10: 0 | C10: CASH OUTFLOWS | F10: =-'project cost'!C20*100000 -> -57000000000 | G10: =F10 -> -57000000000
B11: 1 | C11: CASH INFLOWS | D11: =Assumptions!I78 -> 2024-25 | F11: =CFs!B45 -> 4680810000 | G11: =F11/POWER(1.1,B11) -> 4.2552818e+09 | H11: =G10+G11 -> -5.2744718e+10
B12: 2 | D12: =Assumptions!I79 -> 2025-26 | F12: =CFs!C45 -> -6652740000 | G12: =F12/POWER(1.1,B12) -> -5.4981322e+09 | H12: =H11+G12 -> -5.824285e+10
B13: 3 | D13: =Assumptions!I80 -> 2026-27 | F13: =CFs!D45 -> 15844490000 | G13: =F13/POWER(1.1,B13) -> 1.19042e+10 | H13: =H12+G13 -> -4.6338651e+10
B14: 4 | D14: =Assumptions!I81 -> 2027-28 | F14: =CFs!E45 -> 3.92005e+09 | G14: =F14/POWER(1.1,B14) -> 2.6774469e+09 | H14: =H13+G14 -> -4.3661204e+10 | K14: Excel 365/2021
B15: 5 | D15: =Assumptions!I82 -> 2028-29 | F15: =CFs!F45 -> 4210280000 | G15: =F15/POWER(1.1,B15) -> 2.6142526e+09 | H15: =H14+G15 -> -4.1046951e+10 | K15: =LET(k,MATCH(TRUE,G1:G11>0,0),(k-1)+ABS(INDEX(G1:G11,k-1))/INDEX(F1:F11,k)) | T15: This formulae automatically detect k (the year of recovery).
B16: 6 | D16: =Assumptions!I83 -> 2029-30 | F16: =CFs!G45 -> 5010100000 | G16: =F16/POWER(1.1,B16) -> 2.8280708e+09 | H16: =H15+G16 -> -3.821888e+10
B17: 7 | D17: =Assumptions!I84 -> 2030-31 | F17: =CFs!H45 -> 5.34169e+09 | G17: =F17/POWER(1.1,B17) -> 2.7411316e+09 | H17: =H16+G17 -> -3.5477749e+10 | O17: OR
B18: 8 | D18: =Assumptions!I85 -> 2031-32 | F18: =CFs!I45 -> 5.12213e+09 | G18: =F18/POWER(1.1,B18) -> 2.3895114e+09 | H18: =H17+G18 -> -3.3088237e+10
K19: FOR Excel 97-2003
C20: PAYBACK PERIOD (YEARS) | H20: {=(MATCH(TRUE,H10:H18>0,0)-1) + ABS(INDEX(H10:H18,MATCH(TRUE,H10:H18>0,0)-1))/INDEX(G10:G18,MATCH(TRUE,H10:H18>0,0))} -> #N/A | K20: =(MATCH(TRUE,H11:H18>0,0)-1) + ABS(INDEX(H11:H18,MATCH(TRUE,H11:H18>0,0)-1))/INDEX(G10:G18,MATCH(TRUE,H11:H18>0,0))
K21: After typing the above, press CTRL+SHIFT+ENTER instead of just Enter.

Sheet Sensitivity Analysis
B2: =Assumptions!I17 -> Doe Textiles
B3: =Assumptions!I8 -> John Doe
B4: =Assumptions!I16 -> 123 Industrial Area, City
B8: SENSITIVITY ANALYSIS
D10: EARNINGS BEFORE TAX
B11: Particulars | D11: If Selling Price decrease by | E11: If Direct Material / Expenses increase by
D12: ='Final workings'!I54 -> 0 | E12: ='Final workings'!I55 -> 0
B14: =Assumptions!I78 -> 2024-25 | D14: ='workings-Sensitivity Analysis1'!D37 -> 5.9592683e+09 | E14: ='Workings-Sensitivity Analysis2'!D37 -> 5.9592683e+09
B16: =Assumptions!I79 -> 2025-26 | D16: ='workings-Sensitivity Analysis1'!E37 -> 8.2995517e+09 | E16: ='Workings-Sensitivity Analysis2'!E37 -> 8.2995517e+09
B18: =Assumptions!I80 -> 2026-27 | D18: ='workings-Sensitivity Analysis1'!F37 -> 9316347500 | E18: ='Workings-Sensitivity Analysis2'!F37 -> 9316347500
B20: =Assumptions!I81 -> 2027-28 | D20: ='workings-Sensitivity Analysis1'!G37 -> 1.0284888e+10 | E20: ='Workings-Sensitivity Analysis2'!G37 -> 1.0284888e+10
B22: =Assumptions!I82 -> 2028-29 | D22: ='workings-Sensitivity Analysis1'!H37 -> 1.1220007e+10 | E22: ='Workings-Sensitivity Analysis2'!H37 -> 1.1220007e+10
B24: =Assumptions!I83 -> 2029-30 | D24: ='workings-Sensitivity Analysis1'!I37 -> 1.2029413e+10 | E24: ='Workings-Sensitivity Analysis2'!I37 -> 1.2029413e+10
B26: =Assumptions!I84 -> 2030-31 | D26: ='workings-Sensitivity Analysis1'!J37 -> 1.2804245e+10 | E26: ='Workings-Sensitivity Analysis2'!J37 -> 1.2804245e+10
B28: =Assumptions!I85 -> 2031-32 | D28: ='workings-Sensitivity Analysis1'!K37 -> 1.3567818e+10 | E28: ='Workings-Sensitivity Analysis2'!K37 -> 1.3567818e+10

Sheet BEP
A2: =Assumptions!I17 -> Doe Textiles
A3: =Assumptions!I8 -> John Doe
A4: =Assumptions!I16 -> 123 Industrial Area, City
A7: CALCULATION OF BREAK EVEN POINT (BEP)
A8: Particulars | B8: =IF('Final workings'!B7=0,"",Assumptions!I78) -> 2024-25 | C8: =IF('Final workings'!C7=0,"",Assumptions!I79) -> 2025-26 | D8: =Assumptions!I80 -> 2026-27 | E8: =Assumptions!I81 -> 2027-28 | F8: =Assumptions!I82 -> 2028-29 | G8: =Assumptions!I83 -> 2029-30 | H8: =Assumptions!I84 -> 2030-31 | I8: =Assumptions!I85 -> 2031-32
A10: Gross Revenue | B10: =IF('Final workings'!B7=0,"",'PL BS'!D14) -> 27534150000 | C10: =IF('Final workings'!C7=0,"",'PL BS'!E14) -> -8573600000 | D10: ='PL BS'!F14 -> 44750180000 | E10: ='PL BS'!G14 -> 46822650000 | F10: ='PL BS'!H14 -> 48895300000 | G10: ='PL BS'!I14 -> 50967900000 | H10: ='PL BS'!J14 -> 53040460000 | I10: ='PL BS'!K14 -> 55112960000
A12: Less : Cost of Goods Sold / Direct Costs | B12: =IF('Final workings'!B7=0,"",'PL BS'!D27) -> 15562780000 | C12: =IF('Final workings'!C7=0,"",'PL BS'!E27) -> -23713430000 | D12: ='PL BS'!F27 -> 28882870000 | E12: ='PL BS'!G27 -> 30227930000 | F12: ='PL BS'!H27 -> 31573080000 | G12: ='PL BS'!I27 -> 32918190000 | H12: ='PL BS'!J27 -> 34263230000 | I12: ='PL BS'!K27 -> 35608230000
A14: Total Contribution | B14: =IF('Final workings'!B7=0,"",B10-B12) -> 11971370000 | C14: =IF('Final workings'!C7=0,"",C10-C12) -> 15139830000 | D14: =D10-D12 -> 15867310000 | E14: =E10-E12 -> 16594720000 | F14: =F10-F12 -> 17322220000 | G14: =G10-G12 -> 18049710000 | H14: =H10-H12 -> 18777230000 | I14: =I10-I12 -> 19504730000
A16: Selling price per | B16: ='Final workings'!B70 -> 0 | C16: ='Final workings'!C70 -> 0 | D16: ='Final workings'!D70 -> 0 | E16: ='Final workings'!E70 -> 0 | F16: ='Final workings'!F70 -> 0 | G16: ='Final workings'!G70 -> 0 | H16: ='Final workings'!H70 -> 0 | I16: ='Final workings'!I70 -> 0
A18: Quantity Manufactured | B18: =IF('Final workings'!B7=0,"",B10/B16) -> #DIV/0! | C18: =IF(Assumptions!I63=0,"",C10/C16) -> #DIV/0! | D18: =D10/D16 -> #DIV/0! | E18: =E10/E16 -> #DIV/0! | F18: =F10/F16 -> #DIV/0! | G18: =G10/G16 -> #DIV/0! | H18: =H10/H16 -> #DIV/0! | I18: =I10/I16 -> #DIV/0!
A20: Contribution (Per) | B20: =IF('Final workings'!B7=0,"",B14/B18) -> #DIV/0! | C20: =IF(Assumptions!I63=0,"",C14/C18) -> #DIV/0! | D20: =D14/D18 -> #DIV/0! | E20: =E14/E18 -> #DIV/0! | F20: =F14/F18 -> #DIV/0! | G20: =G14/G18 -> #DIV/0! | H20: =H14/H18 -> #DIV/0! | I20: =I14/I18 -> #DIV/0!
A22: Fixed Costs | B22: ='Final workings'!B71 -> 0 | C22: ='Final workings'!C71 -> 0 | D22: ='Final workings'!D71 -> 0 | E22: ='Final workings'!E71 -> 0 | F22: ='Final workings'!F71 -> 0 | G22: ='Final workings'!G71 -> 0 | H22: ='Final workings'!H71 -> 0 | I22: ='Final workings'!I71 -> 0
A24: BREAK EVEN POINT (Quantity) | B24: =IF('Final workings'!B7=0,"",B22/B20) -> #DIV/0! | C24: =IF(Assumptions!I63=0,"",C22/C20) -> #DIV/0! | D24: =D22/D20 -> #DIV/0! | E24: =E22/E20 -> #DIV/0! | F24: =F22/F20 -> #DIV/0! | G24: =G22/G20 -> #DIV/0! | H24: =H22/H20 -> #DIV/0! | I24: =I22/I20 -> #DIV/0!
A26: Plant Installed capacity (Quantity) | B26: =IF('Final workings'!B7=0,"",'Final workings'!E68*12) -> 0 | C26: =IF(Assumptions!I63=0,"",'Final workings'!E68*12) -> 0 | D26: ='Final workings'!E68*12 -> 0 | E26: =D26 -> 0 | F26: =E26 -> 0 | G26: =F26 -> 0 | H26: =G26 -> 0 | I26: =H26 -> 0
A28: Plant Operating capacity (Quantity) | B28: =B18 -> #DIV/0! | C28: =C18 -> #DIV/0! | D28: =D18 -> #DIV/0! | E28: =E18 -> #DIV/0! | F28: =F18 -> #DIV/0! | G28: =G18 -> #DIV/0! | H28: =H18 -> #DIV/0! | I28: =I18 -> #DIV/0!
A30: Operating Capacity (%) | B30: =IF('Final workings'!B7=0,"",B28/B26*100*Assumptions!F130/Assumptions!I62) -> #DIV/0! | C30: =IF(Assumptions!I63=0,"",C28/C26*100*Assumptions!F130/Assumptions!I63) -> #DIV/0! | D30: =D28/D26*100 -> #DIV/0! | E30: =E28/E26*100 -> #DIV/0! | F30: =F28/F26*100 -> #DIV/0! | G30: =G28/G26*100 -> #DIV/0! | H30: =H28/H26*100 -> #DIV/0! | I30: =I28/I26*100 -> #DIV/0!
A33: CALCULATION OF MARGIN OF SAFETY (MOS)
A35: =A8 -> Particulars | B35: =B8 -> 2024-25 | C35: =C8 -> 2025-26 | D35: =D8 -> 2026-27 | E35: =E8 -> 2027-28 | F35: =F8 -> 2028-29 | G35: =G8 -> 2029-30 | H35: =H8 -> 2030-31 | I35: =I8 -> 2031-32
A37: Actual Sales | B37: =B10 -> 27534150000 | C37: =C10 -> -8573600000 | D37: =D10 -> 44750180000 | E37: =E10 -> 46822650000 | F37: =F10 -> 48895300000 | G37: =G10 -> 50967900000 | H37: =H10 -> 53040460000 | I37: =I10 -> 55112960000
A39: Break Even Sales | B39: =IF('Final workings'!B7=0,"",B24*B16) -> #DIV/0! | C39: =IF(Assumptions!I63=0,"",C24*C16) -> #DIV/0! | D39: =D24*D16 -> #DIV/0! | E39: =E24*E16 -> #DIV/0! | F39: =F24*F16 -> #DIV/0! | G39: =G24*G16 -> #DIV/0! | H39: =H24*H16 -> #DIV/0! | I39: =I24*I16 -> #DIV/0!
A41: MARGIN OF SAFETY:
A43: MOS Value | B43: =IF('Final workings'!B7=0,"",B37-B39) -> #DIV/0! | C43: =IF(Assumptions!I63=0,"",C37-C39) -> #DIV/0! | D43: =D37-D39 -> #DIV/0! | E43: =E37-E39 -> #DIV/0! | F43: =F37-F39 -> #DIV/0! | G43: =G37-G39 -> #DIV/0! | H43: =H37-H39 -> #DIV/0! | I43: =I37-I39 -> #DIV/0!
A45: MOS Ratio | B45: =IF('Final workings'!B7=0,"",B43/B37) -> #DIV/0! | C45: =IF(Assumptions!I63=0,"",C43/C37) -> #DIV/0! | D45: =D43/D37 -> #DIV/0! | E45: =E43/E37 -> #DIV/0! | F45: =F43/F37 -> #DIV/0! | G45: =G43/G37 -> #DIV/0! | H45: =H43/H37 -> #DIV/0! | I45: =I43/I37 -> #DIV/0!
A47: MOS Percentage | B47: =IF('Final workings'!B7=0,"",B45*100) -> #DIV/0! | C47: =IF(Assumptions!I63=0,"",C45*100) -> #DIV/0! | D47: =D45*100 -> #DIV/0! | E47: =E45*100 -> #DIV/0! | F47: =F45*100 -> #DIV/0! | G47: =G45*100 -> #DIV/0! | H47: =H45*100 -> #DIV/0! | I47: =I45*100 -> #DIV/0!

Sheet FA sch
B2: =Assumptions!I17 -> Doe Textiles
B3: =Assumptions!I8 -> John Doe
B4: =Assumptions!I16 -> 123 Industrial Area, City
B7: SCHEDULES TO FIXED ASSETS
D8: Rs in Lacs
B9: Particulars | C9: Amount (Rs) | D9: Amount (Rs)
B11: =Assumptions!B134 -> Plant and Machinery | D11: =SUM(C12:C17) -> 70000
B12: =Assumptions!D134 -> 0 | C12: =Assumptions!E134 -> 0
B13: =Assumptions!D135 -> Sewing Machine | C13: =Assumptions!E135 -> 50000
B14: =Assumptions!D136 -> Cutting Table | C14: =Assumptions!E136 -> 20000
B18: =Assumptions!B144 -> Service Equipment
B22: =Assumptions!B154 -> Shed Construction and Civil works
B26: =Assumptions!B164 -> Land
B30: =Assumptions!B167 -> Electrical Items & fittings
B34: =Assumptions!B177 -> Electronic Items
B39: =Assumptions!B187 -> Furniture and Fittings
B43: =Assumptions!B197 -> Vehicles
B47: =Assumptions!B206 -> Live stock
B51: =Assumptions!B216 -> Other Assets
B55: =Assumptions!C38 -> Other Assets (Nil Depreciation)
B60: TOTAL VALUE | D60: =SUM(D10:D58) -> 70000

Sheet Altman Z
B2: =Assumptions!I17 -> Doe Textiles
B3: =Assumptions!I8 -> John Doe
B4: =Assumptions!I16 -> 123 Industrial Area, City
B6: Calculation of Altman Z Score
B7: (To Determine the Financial Health of a Company)
B9: Particulars | C9: =IF('Final workings'!B7=0,"",'PL BS'!D7) -> 2024-25 | D9: =IF('Final workings'!C7=0,"",'PL BS'!E7) -> 2025-26 | E9: ='PL BS'!F7 -> 2026-27 | F9: ='PL BS'!G7 -> 2027-28 | G9: ='PL BS'!H7 -> 2028-29 | H9: ='PL BS'!I7 -> 2029-30 | I9: ='PL BS'!J7 -> 2030-31 | J9: ='PL BS'!K7 -> 2031-32
B11: Net Working capital | C11: =IF('Final workings'!B7=0,"",SUM('PL BS'!D75:D81)-SUM('PL BS'!D61:D65)) -> 6187280000 | D11: =IF('Final workings'!C7=0,"",SUM('PL BS'!E75:E81)-SUM('PL BS'!E61:E65)) -> 10824390000 | E11: =SUM('PL BS'!F75:F81)-SUM('PL BS'!F61:F65) -> 31480080000 | F11: =SUM('PL BS'!G75:G81)-SUM('PL BS'!G61:G65) -> 37387180000 | G11: =SUM('PL BS'!H75:H81)-SUM('PL BS'!H61:H65) -> 43631890000 | H11: =SUM('PL BS'!I75:I81)-SUM('PL BS'!I61:I65) -> 50023830000 | I11: =SUM('PL BS'!J75:J81)-SUM('PL BS'!J61:J65) -> 56794840000 | J11: =SUM('PL BS'!K75:K81)-SUM('PL BS'!K61:K65) -> 63393810000
B13: Total Assets | C13: =IF('Final workings'!B7=0,"",'PL BS'!D82) -> 2.0411973e+10 | D13: =IF('Final workings'!C7=0,"",'PL BS'!E82) -> 61289460000 | E13: ='PL BS'!F82 -> 82676642500 | F13: ='PL BS'!G82 -> 87182820625 | G13: ='PL BS'!H82 -> 9.2129891e+10 | H13: ='PL BS'!I82 -> 9.8012166e+10 | I13: ='PL BS'!J82 -> 1.0434846e+11 | J13: ='PL BS'!K82 -> 1.1057656e+11
B15: Earning before Tax | C15: =IF('Final workings'!B7=0,"",'PL BS'!D41) -> 5.3539283e+09 | D15: =IF('Final workings'!C7=0,"",'PL BS'!E41) -> 7.7095517e+09 | E15: ='PL BS'!F41 -> 8726347500 | F15: ='PL BS'!G41 -> 9.6948881e+09 | G15: ='PL BS'!H41 -> 1.0630007e+10 | H15: ='PL BS'!I41 -> 1.1439413e+10 | I15: ='PL BS'!J41 -> 1.2214245e+10 | J15: ='PL BS'!K41 -> 1.2977818e+10
B17: EBIT | C17: =IF('Final workings'!B7=0,"",'PL BS'!D37) -> 1.0448053e+10 | D17: =IF('Final workings'!C7=0,"",'PL BS'!E37) -> 1.3583677e+10 | E17: ='PL BS'!F37 -> 14453472500 | F17: ='PL BS'!G37 -> 15302148125 | G17: ='PL BS'!H37 -> 1.613285e+10 | H17: ='PL BS'!I37 -> 1.6948226e+10 | I17: ='PL BS'!J37 -> 1.7750602e+10 | J17: ='PL BS'!K37 -> 1.8541856e+10
B19: Net Equity (Net Capital) | C19: =IF('Final workings'!B7=0,"",'PL BS'!D54) -> 7987280000 | D19: =IF('Final workings'!C7=0,"",'PL BS'!E54) -> 1.3059807e+10 | E19: ='PL BS'!F54 -> 3.4293309e+10 | F19: ='PL BS'!G54 -> 4.0199487e+10 | G19: ='PL BS'!H54 -> 4.6546557e+10 | H19: ='PL BS'!I54 -> #VALUE! | I19: ='PL BS'!J54 -> #VALUE! | J19: ='PL BS'!K54 -> 6.5576564e+10
B21: Total Liabilities | C21: =IF('Final workings'!B7=0,"",SUM('PL BS'!D57:D65)) -> 1.2424693e+10 | D21: =IF('Final workings'!C7=0,"",SUM('PL BS'!E57:E65)) -> 4.8229653e+10 | E21: =SUM('PL BS'!F57:F65) -> 4.8383333e+10 | F21: =SUM('PL BS'!G57:G65) -> 4.6983333e+10 | G21: =SUM('PL BS'!H57:H65) -> 4.5583333e+10 | H21: =SUM('PL BS'!I57:I65) -> #VALUE! | I21: =SUM('PL BS'!J57:J65) -> #VALUE! | J21: =SUM('PL BS'!K57:K65) -> 45000000000
B23: Sales | C23: =IF('Final workings'!B7=0,"",'PL BS'!D14) -> 27534150000 | D23: =IF('Final workings'!C7=0,"",'PL BS'!E14) -> -8573600000 | E23: ='PL BS'!F14 -> 44750180000 | F23: ='PL BS'!G14 -> 46822650000 | G23: ='PL BS'!H14 -> 48895300000 | H23: ='PL BS'!I14 -> 50967900000 | I23: ='PL BS'!J14 -> 53040460000 | J23: ='PL BS'!K14 -> 55112960000
B26: A.Working capital / Total Assets | C26: =IF('Final workings'!B7=0,"",C11/C13) -> 0.30312013 | D26: =IF(Assumptions!I63=0,"",D11/D13) -> 0.17661095 | E26: =E11/E13 -> 0.38076147 | F26: =F11/F13 -> 0.42883655 | G26: =G11/G13 -> 0.47359103 | H26: =H11/H13 -> 0.51038388 | I26: =I11/I13 -> 0.54428059 | J26: =J11/J13 -> 0.5733024
B28: B.Earning / Total Assets | C28: =IF('Final workings'!B7=0,"",C15/C13) -> 0.26229352 | D28: =IF(Assumptions!I63=0,"",D15/D13) -> 0.12578919 | E28: =E15/E13 -> 0.10554792 | F28: =F15/F13 -> 0.11120182 | G28: =G15/G13 -> 0.11538065 | H28: =H15/H13 -> 0.11671421 | I28: =I15/I13 -> 0.11705247 | J28: =J15/J13 -> 0.11736499
B30: C.EBIT / Total Assets | C30: =IF('Final workings'!B7=0,"",C17/C13) -> 0.51185905 | D30: =IF(Assumptions!I63=0,"",D17/D13) -> 0.22163153 | E30: =E17/E13 -> 0.1748193 | F30: =F17/F13 -> 0.17551793 | G30: =G17/G13 -> 0.17510984 | H30: =H17/H13 -> 0.17291961 | I30: =I17/I13 -> 0.1701089 | J30: =J17/J13 -> 0.16768342
B32: D.Equity Capital / Total Liabilities | C32: =IF('Final workings'!B7=0,"",C19/C21) -> 0.6428553 | D32: =IF(Assumptions!I63=0,"",D19/D21) -> 0.27078376 | E32: =E19/E21 -> 0.70878352 | F32: =F19/F21 -> 0.85561165 | G32: =G19/G21 -> 1.0211311 | H32: =H19/H21 -> #VALUE! | I32: =I19/I21 -> #VALUE! | J32: =J19/J21 -> 1.457257
B34: E.Sales / Total Assets | C34: =IF('Final workings'!B7=0,"",C23/C13) -> 1.3489215 | D34: =IF(Assumptions!I63=0,"",D23/D13) -> -0.13988702 | E34: =E23/E13 -> 0.5412675 | F34: =F23/F13 -> 0.5370628 | G34: =G23/G13 -> 0.53072135 | H34: =H23/H13 -> 0.52001605 | I34: =I23/I13 -> 0.50830133 | J34: =J23/J13 -> 0.49841447
B37: Altman Z Score Formulae | C37: =IF('Final workings'!B7=0,"",1.2*C26+1.4*C28+3.3*C30+0.6*C32+1*C34) -> 4.1547247 | D37: =IF(Assumptions!I63=0,"",1.2*D26+1.4*D28+3.3*D30+0.6*D32+1*D34) -> 1.1420053 | E37: =1.2*E26+1.4*E28+3.3*E30+0.6*E32+1*E34 -> 2.1481221 | F37: =1.2*F26+1.4*F28+3.3*F30+0.6*F32+1*F34 -> 2.2999254 | G37: =1.2*G26+1.4*G28+3.3*G30+0.6*G32+1*G34 -> 2.4511046 | H37: =1.2*H26+1.4*H28+3.3*H30+0.6*H32+1*H34 -> #VALUE! | I37: =1.2*I26+1.4*I28+3.3*I30+0.6*I32+1*I34 -> #VALUE! | J37: =1.2*J26+1.4*J28+3.3*J30+0.6*J32+1*J34 -> 2.7783978
B38: (To Determine the financial health of a Company)

Sheet CF workings
A3: BACK GROUND CALCULATION . NOT TO BE VISIBLE TO CUSTOMER
A4: WORKINGS FOR CASH FLOW STATEMENTS
A5: Particulars | B5: ='Workings for PL BS 1'!D4 -> 2024-25 | C5: ='Workings for PL BS 1'!E4 -> 2025-26 | D5: ='Workings for PL BS 1'!F4 -> 2026-27 | E5: ='Workings for PL BS 1'!G4 -> 2027-28 | F5: ='Workings for PL BS 1'!H4 -> 2028-29 | G5: ='Workings for PL BS 1'!I4 -> 2029-30 | H5: ='Workings for PL BS 1'!J4 -> 2030-31 | I5: ='Workings for PL BS 1'!K4 -> 2031-32
A7: In flows:
A8: Profit before Bank Interest & Tax but after depreciation | B8: ='PL BS'!D37 -> 1.0448053e+10 | C8: ='PL BS'!E37 -> 1.3583677e+10 | D8: ='PL BS'!F37 -> 14453472500 | E8: ='PL BS'!G37 -> 15302148125 | F8: ='PL BS'!H37 -> 1.613285e+10 | G8: ='PL BS'!I37 -> 1.6948226e+10 | H8: ='PL BS'!J37 -> 1.7750602e+10 | I8: ='PL BS'!K37 -> 1.8541856e+10
A9: Increase in Depreciation | B9: ='WorKings for PL BS 2'!B21 -> 9.1666667e+08 | C9: ='WorKings for PL BS 2'!C21 -> 9.6458333e+08 | D9: ='WorKings for PL BS 2'!D21 -> 822187500 | E9: ='WorKings for PL BS 2'!E21 -> 700921875 | F9: ='WorKings for PL BS 2'!F21 -> 5.9763984e+08 | G9: ='WorKings for PL BS 2'!G21 -> 5.0966449e+08 | H9: ='WorKings for PL BS 2'!H21 -> 4.3471838e+08 | I9: ='WorKings for PL BS 2'!I21 -> 3.7086383e+08
A10: Increase in Term Loan | B10: =Assumptions!I43*100000 -> 6300000000 | C10: 0 | D10: 0 | E10: 0 | F10: 0 | G10: 0 | H10: 0 | I10: 0
A11: Increase in working capital loan | B11: ='PL BS'!D62 -> 6241360000 | C11: ='PL BS'!E62-'PL BS'!D62 -> 37204960000 | D11: ='PL BS'!F62-'PL BS'!E62 -> 1553680000 | E11: ='PL BS'!G62-'PL BS'!F62 -> 0 | F11: ='PL BS'!H62-'PL BS'!G62 -> 0 | G11: ='PL BS'!I62-'PL BS'!H62 -> 0 | H11: ='PL BS'!J62-'PL BS'!I62 -> 0 | I11: ='PL BS'!K62-'PL BS'!J62 -> 0
A12: Increase In Capital | B12: =Assumptions!I55*100000 -> 6200000000 | C12: 0 | D12: 0 | E12: 0 | F12: 0 | G12: 0 | H12: 0 | I12: 0
A13: Increase in Capital during the year
B15: =SUM(B8:B14) -> 30106080000 | C15: =SUM(C8:C14) -> 51753220000 | D15: =SUM(D8:D14) -> 16829340000 | E15: =SUM(E8:E14) -> 16003070000 | F15: =SUM(F8:F14) -> 16730490000 | G15: =SUM(G8:G14) -> 17457890000 | H15: =SUM(H8:H14) -> 18185320000 | I15: =SUM(I8:I14) -> 18912720000
A17: Outflows:
A19: Increase in Capital expenditure | B19: =SUM(Assumptions!I28:J37)*100000 -> 7500000000 | C19: 0 | D19: 0 | E19: 0 | F19: 0 | G19: 0 | H19: 0 | I19: 0
A20: Increase in Term Loan interest | B20: ='WorKings for PL BS 2'!B5 -> 5.94125e+08 | C20: ='Workings for PL BS 1'!E49 -> 4.47125e+08 | D20: ='Workings for PL BS 1'!F49 -> 3.00125e+08 | E20: ='Workings for PL BS 1'!G49 -> 1.53125e+08 | F20: ='Workings for PL BS 1'!H49 -> 21437500 | G20: ='Workings for PL BS 1'!I49 -> 0 | H20: ='Workings for PL BS 1'!J49 -> 0 | I20: ='Workings for PL BS 1'!K49 -> 0
A21: Increase in CC Loan interest | B21: ='WorKings for PL BS 2'!B6 -> 4500000000 | C21: ='Workings for PL BS 1'!E50 -> 5.427e+09 | D21: ='Workings for PL BS 1'!F50 -> 5.427e+09 | E21: ='Workings for PL BS 1'!G50 -> 5.454135e+09 | F21: ='Workings for PL BS 1'!H50 -> 5.4814057e+09 | G21: ='Workings for PL BS 1'!I50 -> 5.5088127e+09 | H21: ='Workings for PL BS 1'!J50 -> 5.5363568e+09 | I21: ='Workings for PL BS 1'!K50 -> 5.5640386e+09
A22: Decrease in Term Loan | B22: ='WorKings for PL BS 2'!B10 -> 1400000000 | C22: ='WorKings for PL BS 2'!C10 -> 1400000000 | D22: ='WorKings for PL BS 2'!D10 -> 1400000000 | E22: ='WorKings for PL BS 2'!E10 -> 1400000000 | F22: ='WorKings for PL BS 2'!F10 -> 700000000 | G22: ='WorKings for PL BS 2'!G10 -> 0 | H22: ='WorKings for PL BS 2'!H10 -> 0 | I22: ='WorKings for PL BS 2'!I10 -> 0
A23: Increase in Recievables | B23: ='PL BS'!D78 -> 2478070000 | C23: ='PL BS'!E78-'PL BS'!D78 -> -3335430000 | D23: ='PL BS'!F78-'PL BS'!E78 -> 5779880000 | E23: ='PL BS'!G78-'PL BS'!F78 -> 696200000 | F23: ='PL BS'!H78-'PL BS'!G78 -> 737670000 | G23: ='PL BS'!I78-'PL BS'!H78 -> 779120000 | H23: ='PL BS'!J78-'PL BS'!I78 -> 820560000 | I23: ='PL BS'!K78-'PL BS'!J78 -> 862000000
A24: Increase in Stock | B24: ='PL BS'!D76 -> 6669760000 | C24: ='PL BS'!E76-'PL BS'!D76 -> 51830240000 | D24: ='PL BS'!F76-'PL BS'!E76 -> 585000000 | E24: ='PL BS'!G76-'PL BS'!F76 -> 590850000 | F24: ='PL BS'!H76-'PL BS'!G76 -> 596760000 | G24: ='PL BS'!I76-'PL BS'!H76 -> 602720000 | H24: ='PL BS'!J76-'PL BS'!I76 -> 608760000 | I24: ='PL BS'!K76-'PL BS'!J76 -> 614840000
B26: =SUM(B19:B25) -> 23141955000 | C26: =SUM(C19:C25) -> 55768935000 | D26: =SUM(D19:D25) -> 13492005000 | E26: =SUM(E19:E25) -> 8.29431e+09 | F26: =SUM(F19:F25) -> 7.5372732e+09 | G26: =SUM(G19:G25) -> 6.8906527e+09 | H26: =SUM(H19:H25) -> 6.9656768e+09 | I26: =SUM(I19:I25) -> 7.0408786e+09
A28: Gross Surplus during the year | B28: =B15-B26 -> 6964125000 | C28: =C15-C26 -> -4015715000 | D28: =D15-D26 -> 3337335000 | E28: =E15-E26 -> 7.70876e+09 | F28: =F15-F26 -> 9.1932168e+09 | G28: =G15-G26 -> 1.0567237e+10 | H28: =H15-H26 -> 1.1219643e+10 | I28: =I15-I26 -> 1.1871841e+10
A29: Increase in Drawings
A30: Opening balance of cash | B30: 0 | C30: =+B32 -> 4680810000 | D30: =+C32 -> -1971930000 | E30: =+D32 -> 13872560000 | F30: =+E32 -> 17792610000 | G30: =+F32 -> 22002890000 | H30: =+G32 -> 27012990000 | I30: =+H32 -> 32354680000
A31: Net Surplus during the year | B31: =B28-B29 -> 6964125000 | C31: =C28-C29 -> -4015715000 | D31: =D28-D29 -> 3337335000 | E31: =E28-E29 -> 7.70876e+09 | F31: =F28-F29 -> 9.1932168e+09 | G31: =G28-G29 -> 1.0567237e+10 | H31: =H28-H29 -> 1.1219643e+10 | I31: =I28-I29 -> 1.1871841e+10
A32: Closing balance of cash | B32: ='PL BS'!D80 -> 4680810000 | C32: ='PL BS'!E80 -> -1971930000 | D32: ='PL BS'!F80 -> 13872560000 | E32: ='PL BS'!G80 -> 17792610000 | F32: ='PL BS'!H80 -> 22002890000 | G32: ='PL BS'!I80 -> 27012990000 | H32: ='PL BS'!J80 -> 32354680000 | I32: ='PL BS'!K80 -> 37476810000
B34: =B30+B31 -> 6964125000 | C34: =C30+C31 -> 665095000 | D34: =D30+D31 -> 1365405000 | E34: =E30+E31 -> 21581320000 | F34: =F30+F31 -> 2.6985827e+10 | G34: =G30+G31 -> 3.2570127e+10 | H34: =H30+H31 -> 3.8232633e+10 | I34: =I30+I31 -> 4.4226521e+10
B35: =B34-B32 -> 2283315000 | C35: =C34-C32 -> 2637025000 | D35: =D34-D32 -> -12507155000 | E35: =E34-E32 -> 3788710000 | F35: =F34-F32 -> 4.9829368e+09 | G35: =G34-G32 -> 5.5571373e+09 | H35: =H34-H32 -> 5.8779532e+09 | I35: =I34-I32 -> 6.7497114e+09
B36: =-IF(B35<0,B35,"0") -> 0 | C36: =-IF(C35<0,C35,"0") -> 0 | D36: =-IF(D35<0,D35,"0") -> 12507155000 | E36: =-IF(E35<0,E35,"0") -> 0 | F36: =-IF(F35<0,F35,"0") -> 0 | G36: =-IF(G35<0,G35,"0") -> 0 | H36: =-IF(H35<0,H35,"0") -> 0 | I36: =-IF(I35<0,I35,"0") -> 0
B37: =IF(B35>0,B35,"0") -> 2283315000 | C37: =IF(C35>0,C35,"0") -> 2637025000 | D37: =IF(D35>0,D35,"0") -> 0 | E37: =IF(E35>0,E35,"0") -> 3788710000 | F37: =IF(F35>0,F35,"0") -> 4.9829368e+09 | G37: =IF(G35>0,G35,"0") -> 5.5571373e+09 | H37: =IF(H35>0,H35,"0") -> 5.8779532e+09 | I37: =IF(I35>0,I35,"0") -> 6.7497114e+09

Sheet workings-Sensitivity Analysis1
A4: Back ground calculation (Not to be visible to customer)
A5: WORKINGS FOR CALCULATION OF SENSITIVITY ANALYSIS WHEN SALES DECREASE
A6: PARTICULARS | B6: Sch | D6: =Assumptions!J78 -> Estimated | E6: =Assumptions!J79 -> Projected | F6: =Assumptions!J80 -> Projected | G6: =Assumptions!J81 -> Projected | H6: =Assumptions!J82 -> Projected | I6: =Assumptions!J83 -> Projected | J6: =Assumptions!J84 -> Projected | K6: =Assumptions!J85 -> Projected
D7: =Assumptions!I78 -> 2024-25 | E7: =Assumptions!I79 -> 2025-26 | F7: =Assumptions!I80 -> 2026-27 | G7: =Assumptions!I81 -> 2027-28 | H7: =Assumptions!I82 -> 2028-29 | I7: =Assumptions!I83 -> 2029-30 | J7: =Assumptions!I84 -> 2030-31 | K7: =Assumptions!I85 -> 2031-32
A9: Gross reciepts
A14: Gross Revenue | D14: ='Final workings'!B7*(100%-'Final workings'!I54) -> 27534150000 | E14: ='Final workings'!C7*(100%-'Final workings'!I54) -> -8573600000 | F14: ='Final workings'!D7*(100%-'Final workings'!I54) -> 44750180000 | G14: ='Final workings'!E7*(100%-'Final workings'!I54) -> 46822650000 | H14: ='Final workings'!F7*(100%-'Final workings'!I54) -> 48895300000 | I14: ='Final workings'!G7*(100%-'Final workings'!I54) -> 50967900000 | J14: ='Final workings'!H7*(100%-'Final workings'!I54) -> 53040460000 | K14: ='Final workings'!I7*(100%-'Final workings'!I54) -> 55112960000
A16: Opening Stock | D16: 0 | E16: =D18 -> #REF! | F16: =E18 -> #REF! | G16: =F18 -> #REF! | H16: =G18 -> #REF! | I16: =H18 -> #REF! | J16: =I18 -> #REF! | K16: =J18 -> #REF!
A17: Direct expenses | D17: =D11*Assumptions!#REF! -> #REF! | E17: =E11*Assumptions!#REF! -> #REF! | F17: =F11*Assumptions!#REF! -> #REF! | G17: =G11*Assumptions!#REF! -> #REF! | H17: =H11*Assumptions!#REF! -> #REF! | I17: =I11*Assumptions!#REF! -> #REF! | J17: =J11*Assumptions!#REF! -> #REF! | K17: =J17*Assumptions!#REF! -> #REF!
A18: Closing Stock | D18: =Assumptions!#REF!*D11 -> #REF! | E18: =Assumptions!#REF!*E11 -> #REF! | F18: =Assumptions!#REF!*F11 -> #REF! | G18: =Assumptions!#REF!*G11 -> #REF! | H18: =Assumptions!#REF!*H11 -> #REF! | I18: =Assumptions!#REF!*I11 -> #REF! | J18: =Assumptions!#REF!*J11 -> #REF! | K18: =Assumptions!#REF!*K11 -> #REF!
A19: Less :Cost of Goods Sold / Direct Costs
A20: Opening Stock | D20: =Assumptions!F124 -> 0 | E20: =D22 -> 6669760000 | F20: =E22 -> 58500000000 | G20: =F22 -> 59085000000 | H20: =G22 -> 59675850000 | I20: =H22 -> 60272610000 | J20: =I22 -> 60875330000 | K20: =J22 -> 61484090000
A21: Direct Material/Expenses | D21: ='Final workings'!B8 -> 22232540000 | E21: ='Final workings'!C8 -> 28116810000 | F21: ='Final workings'!D8 -> 29467870000 | G21: ='Final workings'!E8 -> 30818780000 | H21: ='Final workings'!F8 -> 32169840000 | I21: ='Final workings'!G8 -> 33520910000 | J21: ='Final workings'!H8 -> 34871990000 | K21: ='Final workings'!I8 -> 36223070000
A22: Closing stock | D22: ='Final workings'!B9 -> 6669760000 | E22: ='Final workings'!C9 -> 58500000000 | F22: ='Final workings'!D9 -> 59085000000 | G22: ='Final workings'!E9 -> 59675850000 | H22: ='Final workings'!F9 -> 60272610000 | I22: ='Final workings'!G9 -> 60875330000 | J22: ='Final workings'!H9 -> 61484090000 | K22: ='Final workings'!I9 -> 62098930000
A23: Cost of Goods Sold / Direct Costs | D23: =D20+D21-D22 -> 15562780000 | E23: =E20+E21-E22 -> -23713430000 | F23: =F20+F21-F22 -> 28882870000 | G23: =G20+G21-G22 -> 30227930000 | H23: =H20+H21-H22 -> 31573080000 | I23: =I20+I21-I22 -> 32918190000 | J23: =J20+J21-J22 -> 34263230000 | K23: =K20+K21-K22 -> 35608230000
A25: Gross profit | D25: =D14-D23 -> 11971370000 | E25: =E14-E23 -> 15139830000 | F25: =F14-F23 -> 15867310000 | G25: =G14-G23 -> 16594720000 | H25: =H14-H23 -> 17322220000 | I25: =I14-I23 -> 18049710000 | J25: =J14-J23 -> 18777230000 | K25: =K14-K23 -> 19504730000
A27: Less:
A28: Administrative and Selling Expenses | B28: Sch 1 | D28: =D51 -> 1310000 | E28: =E51 -> 1570000 | F28: =F51 -> 1650000 | G28: =G51 -> 1650000 | H28: =H51 -> 1730000 | I28: =I51 -> 1820000 | J28: =J51 -> 1910000 | K28: =K51 -> 2010000
A30: EBDIT | D30: =D25-D28 -> 11970060000 | E30: =E25-E28 -> 15138260000 | F30: =F25-F28 -> 15865660000 | G30: =G25-G28 -> 16593070000 | H30: =H25-H28 -> 17320490000 | I30: =I25-I28 -> 18047890000 | J30: =J25-J28 -> 18775320000 | K30: =K25-K28 -> 19502720000
A32: Less : Depreciation | D32: ='Dep IT act'!M17*100000 -> 9.1666667e+08 | E32: ='Dep IT act'!M24*100000 -> 9.6458333e+08 | F32: ='Dep IT act'!M31*100000 -> 822187500 | G32: ='Dep IT act'!M38*100000 -> 700921875 | H32: ='Dep IT act'!M45*100000 -> 5.9763984e+08 | I32: ='Dep IT act'!M52*100000 -> 5.0966449e+08 | J32: ='Dep IT act'!M59*100000 -> 4.3471838e+08 | K32: ='Dep IT act'!M66*100000 -> 3.7086383e+08
A33: EBIT | D33: =D30-D32 -> 1.1053393e+10 | E33: =E30-E32 -> 1.4173677e+10 | F33: =F30-F32 -> 15043472500 | G33: =G30-G32 -> 15892148125 | H33: =H30-H32 -> 1.672285e+10 | I33: =I30-I32 -> 1.7538226e+10 | J33: =J30-J32 -> 1.8340602e+10 | K33: =K30-K32 -> 1.9131856e+10
A35: Less: Interest | B35: Sch 2 | D35: =D60 -> 5094125000 | E35: =E60 -> 5.874125e+09 | F35: =F60 -> 5.727125e+09 | G35: =G60 -> 5.60726e+09 | H35: =H60 -> 5.5028432e+09 | I35: =I60 -> 5.5088127e+09 | J35: =J60 -> 5.5363568e+09 | K35: =K60 -> 5.5640386e+09
A37: Earnings before Tax (EBT) | D37: =D33-D35 -> 5.9592683e+09 | E37: =E33-E35 -> 8.2995517e+09 | F37: =F33-F35 -> 9316347500 | G37: =G33-G35 -> 1.0284888e+10 | H37: =H33-H35 -> 1.1220007e+10 | I37: =I33-I35 -> 1.2029413e+10 | J37: =J33-J35 -> 1.2804245e+10 | K37: =K33-K35 -> 1.3567818e+10
A42: Administrative & Selling Expenses
D43: =Assumptions!I78 -> 2024-25 | E43: =Assumptions!I79 -> 2025-26 | F43: =Assumptions!I80 -> 2026-27 | G43: =Assumptions!I81 -> 2027-28 | H43: =Assumptions!I82 -> 2028-29 | I43: =Assumptions!I83 -> 2029-30 | J43: =Assumptions!I84 -> 2030-31 | K43: =Assumptions!I85 -> 2031-32
A45: ='Final workings'!A10 -> Employee Related Expenses (Editable) | D45: ='Final workings'!B10 -> 1310000 | E45: ='Final workings'!C10 -> 1570000 | F45: ='Final workings'!D10 -> 1650000 | G45: ='Final workings'!E10 -> 1650000 | H45: ='Final workings'!F10 -> 1730000 | I45: ='Final workings'!G10 -> 1820000 | J45: ='Final workings'!H10 -> 1910000 | K45: ='Final workings'!I10 -> 2010000
A46: ='Final workings'!A11 -> Administrative & Office Expenses (Editable) | D46: ='Final workings'!B11 -> 0 | E46: ='Final workings'!C11 -> 0 | F46: ='Final workings'!D11 -> 0 | G46: ='Final workings'!E11 -> 0 | H46: ='Final workings'!F11 -> 0 | I46: ='Final workings'!G11 -> 0 | J46: ='Final workings'!H11 -> 0 | K46: ='Final workings'!I11 -> 0
A47: ='Final workings'!A12 -> Selling and Distribution Expenses (Editable) | D47: ='Final workings'!B12 -> 0 | E47: ='Final workings'!C12 -> 0 | F47: ='Final workings'!D12 -> 0 | G47: ='Final workings'!E12 -> 0 | H47: ='Final workings'!F12 -> 0 | I47: ='Final workings'!G12 -> 0 | J47: ='Final workings'!H12 -> 0 | K47: ='Final workings'!I12 -> 0
A48: ='Final workings'!A13 -> General Overheads (Editable) | D48: ='Final workings'!B13 -> 0 | E48: ='Final workings'!C13 -> 0 | F48: ='Final workings'!D13 -> 0 | G48: ='Final workings'!E13 -> 0 | H48: ='Final workings'!F13 -> 0 | I48: ='Final workings'!G13 -> 0 | J48: ='Final workings'!H13 -> 0 | K48: ='Final workings'!I13 -> 0
A49: ='Final workings'!A14 -> Miscellaneous Expenses | D49: ='Final workings'!B14 -> 0 | E49: ='Final workings'!C14 -> 0 | F49: ='Final workings'!D14 -> 0 | G49: ='Final workings'!E14 -> 0 | H49: ='Final workings'!F14 -> 0 | I49: ='Final workings'!G14 -> 0 | J49: ='Final workings'!H14 -> 0 | K49: ='Final workings'!I14 -> 0
D51: =SUM(D44:D50) -> 1310000 | E51: =SUM(E44:E50) -> 1570000 | F51: =SUM(F44:F50) -> 1650000 | G51: =SUM(G44:G50) -> 1650000 | H51: =SUM(H44:H50) -> 1730000 | I51: =SUM(I44:I50) -> 1820000 | J51: =SUM(J44:J50) -> 1910000 | K51: =SUM(K44:K50) -> 2010000
A53: Interest Statement
D54: =Assumptions!I78 -> 2024-25 | E54: =Assumptions!I79 -> 2025-26 | F54: =Assumptions!I80 -> 2026-27 | G54: =Assumptions!I81 -> 2027-28 | H54: =Assumptions!I82 -> 2028-29 | I54: =Assumptions!I83 -> 2029-30 | J54: =Assumptions!I84 -> 2030-31 | K54: =Assumptions!I85 -> 2031-32
A57: Interest on Term Loan | D57: ='WorKings for PL BS 2'!B5 -> 5.94125e+08 | E57: ='WorKings for PL BS 2'!C5 -> 4.47125e+08 | F57: ='WorKings for PL BS 2'!D5 -> 3.00125e+08 | G57: ='WorKings for PL BS 2'!E5 -> 1.53125e+08 | H57: ='WorKings for PL BS 2'!F5 -> 21437500 | I57: ='WorKings for PL BS 2'!G5 -> 0 | J57: ='WorKings for PL BS 2'!H5 -> 0 | K57: ='WorKings for PL BS 2'!I5 -> 0
A58: Interest on CC Loan | D58: ='WorKings for PL BS 2'!B6 -> 4500000000 | E58: ='WorKings for PL BS 2'!C6 -> 5.427e+09 | F58: ='WorKings for PL BS 2'!D6 -> 5.427e+09 | G58: ='WorKings for PL BS 2'!E6 -> 5.454135e+09 | H58: ='WorKings for PL BS 2'!F6 -> 5.4814057e+09 | I58: ='WorKings for PL BS 2'!G6 -> 5.5088127e+09 | J58: ='WorKings for PL BS 2'!H6 -> 5.5363568e+09 | K58: ='WorKings for PL BS 2'!I6 -> 5.5640386e+09
D60: =SUM(D56:D58) -> 5094125000 | E60: =SUM(E56:E58) -> 5.874125e+09 | F60: =SUM(F56:F58) -> 5.727125e+09 | G60: =SUM(G56:G58) -> 5.60726e+09 | H60: =SUM(H56:H58) -> 5.5028432e+09 | I60: =SUM(I56:I58) -> 5.5088127e+09 | J60: =SUM(J56:J58) -> 5.5363568e+09 | K60: =SUM(K56:K58) -> 5.5640386e+09

Sheet Graph
A1: Years | B1: Gross Revenue | C1: Earnings before Tax (EBT)
A2: =Assumptions!I78 -> 2024-25 | B2: ='workings-Sensitivity Analysis1'!D14 -> 27534150000 | C2: ='workings-Sensitivity Analysis1'!D37 -> 5.9592683e+09
A3: =Assumptions!I79 -> 2025-26 | B3: ='workings-Sensitivity Analysis1'!E14 -> -8573600000 | C3: ='workings-Sensitivity Analysis1'!E37 -> 8.2995517e+09
A4: =Assumptions!I80 -> 2026-27 | B4: ='workings-Sensitivity Analysis1'!F14 -> 44750180000 | C4: ='workings-Sensitivity Analysis1'!F37 -> 9316347500
A5: =Assumptions!I81 -> 2027-28 | B5: ='workings-Sensitivity Analysis1'!G14 -> 46822650000 | C5: ='workings-Sensitivity Analysis1'!G37 -> 1.0284888e+10
A6: =Assumptions!I82 -> 2028-29 | B6: ='workings-Sensitivity Analysis1'!H14 -> 48895300000 | C6: ='workings-Sensitivity Analysis1'!H37 -> 1.1220007e+10
A7: =Assumptions!I83 -> 2029-30 | B7: ='workings-Sensitivity Analysis1'!I14 -> 50967900000 | C7: ='workings-Sensitivity Analysis1'!I37 -> 1.2029413e+10
A8: =Assumptions!I84 -> 2030-31 | B8: ='workings-Sensitivity Analysis1'!J14 -> 53040460000 | C8: ='workings-Sensitivity Analysis1'!J37 -> 1.2804245e+10
A9: =Assumptions!I85 -> 2031-32 | B9: ='workings-Sensitivity Analysis1'!K14 -> 55112960000 | C9: ='workings-Sensitivity Analysis1'!K37 -> 1.3567818e+10

Sheet Workings-Sensitivity Analysis2
A4: Back ground calculation (Not to be visible to customer)
A5: WORKINGS FOR CALCULATION OF SENSITIVITY ANALYSIS WHEN DIRECT EXPENSES INCREASE
A6: PARTICULARS | B6: Sch | D6: =Assumptions!J78 -> Estimated | E6: =Assumptions!J79 -> Projected | F6: =Assumptions!J80 -> Projected | G6: =Assumptions!J81 -> Projected | H6: =Assumptions!J82 -> Projected | I6: =Assumptions!J83 -> Projected | J6: =Assumptions!J84 -> Projected | K6: =Assumptions!J85 -> Projected
D7: =Assumptions!I78 -> 2024-25 | E7: =Assumptions!I79 -> 2025-26 | F7: =Assumptions!I80 -> 2026-27 | G7: =Assumptions!I81 -> 2027-28 | H7: =Assumptions!I82 -> 2028-29 | I7: =Assumptions!I83 -> 2029-30 | J7: =Assumptions!I84 -> 2030-31 | K7: =Assumptions!I85 -> 2031-32
A9: Gross reciepts
A14: Gross Revenue | D14: ='Final workings'!B7 -> 27534150000 | E14: ='Final workings'!C7 -> -8573600000 | F14: ='Final workings'!D7 -> 44750180000 | G14: ='Final workings'!E7 -> 46822650000 | H14: ='Final workings'!F7 -> 48895300000 | I14: ='Final workings'!G7 -> 50967900000 | J14: ='Final workings'!H7 -> 53040460000 | K14: ='Final workings'!I7 -> 55112960000
A16: Opening Stock | D16: 0 | E16: =D18 -> #REF! | F16: =E18 -> #REF! | G16: =F18 -> #REF! | H16: =G18 -> #REF! | I16: =H18 -> #REF! | J16: =I18 -> #REF! | K16: =J18 -> #REF!
A17: Direct expenses | D17: =D11*Assumptions!#REF! -> #REF! | E17: =E11*Assumptions!#REF! -> #REF! | F17: =F11*Assumptions!#REF! -> #REF! | G17: =G11*Assumptions!#REF! -> #REF! | H17: =H11*Assumptions!#REF! -> #REF! | I17: =I11*Assumptions!#REF! -> #REF! | J17: =J11*Assumptions!#REF! -> #REF! | K17: =J17*Assumptions!#REF! -> #REF!
A18: Closing Stock | D18: =Assumptions!#REF!*D11 -> #REF! | E18: =Assumptions!#REF!*E11 -> #REF! | F18: =Assumptions!#REF!*F11 -> #REF! | G18: =Assumptions!#REF!*G11 -> #REF! | H18: =Assumptions!#REF!*H11 -> #REF! | I18: =Assumptions!#REF!*I11 -> #REF! | J18: =Assumptions!#REF!*J11 -> #REF! | K18: =Assumptions!#REF!*K11 -> #REF!
A19: Less : Cost of Goods Sold / Direct Costs
A20: Opening Stock | D20: =Assumptions!F124 -> 0 | E20: =D22 -> 6669760000 | F20: =E22 -> 58500000000 | G20: =F22 -> 59085000000 | H20: =G22 -> 59675850000 | I20: =H22 -> 60272610000 | J20: =I22 -> 60875330000 | K20: =J22 -> 61484090000
A21: Direct Material/Expenses | D21: ='Final workings'!B8*(100%+'Final workings'!I55) -> 22232540000 | E21: ='Final workings'!C8*(100%+'Final workings'!I55) -> 28116810000 | F21: ='Final workings'!D8*(100%+'Final workings'!I55) -> 29467870000 | G21: ='Final workings'!E8*(100%+'Final workings'!I55) -> 30818780000 | H21: ='Final workings'!F8*(100%+'Final workings'!I55) -> 32169840000 | I21: ='Final workings'!G8*(100%+'Final workings'!I55) -> 33520910000 | J21: ='Final workings'!H8*(100%+'Final workings'!I55) -> 34871990000 | K21: ='Final workings'!I8*(100%+'Final workings'!I55) -> 36223070000
A22: Closing stock | D22: ='Final workings'!B9 -> 6669760000 | E22: ='Final workings'!C9 -> 58500000000 | F22: ='Final workings'!D9 -> 59085000000 | G22: ='Final workings'!E9 -> 59675850000 | H22: ='Final workings'!F9 -> 60272610000 | I22: ='Final workings'!G9 -> 60875330000 | J22: ='Final workings'!H9 -> 61484090000 | K22: ='Final workings'!I9 -> 62098930000
A23: Cost of Goods Sold / Direct Costs | D23: =D20+D21-D22 -> 15562780000 | E23: =E20+E21-E22 -> -23713430000 | F23: =F20+F21-F22 -> 28882870000 | G23: =G20+G21-G22 -> 30227930000 | H23: =H20+H21-H22 -> 31573080000 | I23: =I20+I21-I22 -> 32918190000 | J23: =J20+J21-J22 -> 34263230000 | K23: =K20+K21-K22 -> 35608230000
A25: Gross profit | D25: =D14-D23 -> 11971370000 | E25: =E14-E23 -> 15139830000 | F25: =F14-F23 -> 15867310000 | G25: =G14-G23 -> 16594720000 | H25: =H14-H23 -> 17322220000 | I25: =I14-I23 -> 18049710000 | J25: =J14-J23 -> 18777230000 | K25: =K14-K23 -> 19504730000
A27: Less:
A28: Administrative and Selling Expenses | B28: Sch 1 | D28: =D52 -> 1310000 | E28: =E52 -> 1570000 | F28: =F52 -> 1650000 | G28: =G52 -> 1650000 | H28: =H52 -> 1730000 | I28: =I52 -> 1820000 | J28: =J52 -> 1910000 | K28: =K52 -> 2010000
A30: EBDIT | D30: =D25-D28 -> 11970060000 | E30: =E25-E28 -> 15138260000 | F30: =F25-F28 -> 15865660000 | G30: =G25-G28 -> 16593070000 | H30: =H25-H28 -> 17320490000 | I30: =I25-I28 -> 18047890000 | J30: =J25-J28 -> 18775320000 | K30: =K25-K28 -> 19502720000
A32: Less : Depreciation | D32: ='Dep IT act'!M17*100000 -> 9.1666667e+08 | E32: ='Dep IT act'!M24*100000 -> 9.6458333e+08 | F32: ='Dep IT act'!M31*100000 -> 822187500 | G32: ='Dep IT act'!M38*100000 -> 700921875 | H32: ='Dep IT act'!M45*100000 -> 5.9763984e+08 | I32: ='Dep IT act'!M52*100000 -> 5.0966449e+08 | J32: ='Dep IT act'!M59*100000 -> 4.3471838e+08 | K32: ='Dep IT act'!M66*100000 -> 3.7086383e+08
A33: EBIT | D33: =D30-D32 -> 1.1053393e+10 | E33: =E30-E32 -> 1.4173677e+10 | F33: =F30-F32 -> 15043472500 | G33: =G30-G32 -> 15892148125 | H33: =H30-H32 -> 1.672285e+10 | I33: =I30-I32 -> 1.7538226e+10 | J33: =J30-J32 -> 1.8340602e+10 | K33: =K30-K32 -> 1.9131856e+10
A35: Less: Interest | B35: Sch 2 | D35: =D61 -> 5094125000 | E35: =E61 -> 5.874125e+09 | F35: =F61 -> 5.727125e+09 | G35: =G61 -> 5.60726e+09 | H35: =H61 -> 5.5028432e+09 | I35: =I61 -> 5.5088127e+09 | J35: =J61 -> 5.5363568e+09 | K35: =K61 -> 5.5640386e+09
A37: Earnings before Tax (EBT) | D37: =D33-D35 -> 5.9592683e+09 | E37: =E33-E35 -> 8.2995517e+09 | F37: =F33-F35 -> 9316347500 | G37: =G33-G35 -> 1.0284888e+10 | H37: =H33-H35 -> 1.1220007e+10 | I37: =I33-I35 -> 1.2029413e+10 | J37: =J33-J35 -> 1.2804245e+10 | K37: =K33-K35 -> 1.3567818e+10
A42: Administrative & Selling Expenses
D43: =Assumptions!I78 -> 2024-25 | E43: =Assumptions!I79 -> 2025-26 | F43: =Assumptions!I80 -> 2026-27 | G43: =Assumptions!I81 -> 2027-28 | H43: =Assumptions!I82 -> 2028-29 | I43: =Assumptions!I83 -> 2029-30 | J43: =Assumptions!I84 -> 2030-31 | K43: =Assumptions!I85 -> 2031-32
A45: ='workings-Sensitivity Analysis1'!A45 -> Employee Related Expenses (Editable) | D45: ='Final workings'!B10 -> 1310000 | E45: ='Final workings'!C10 -> 1570000 | F45: ='Final workings'!D10 -> 1650000 | G45: ='Final workings'!E10 -> 1650000 | H45: ='Final workings'!F10 -> 1730000 | I45: ='Final workings'!G10 -> 1820000 | J45: ='Final workings'!H10 -> 1910000 | K45: ='Final workings'!I10 -> 2010000
A46: ='workings-Sensitivity Analysis1'!A46 -> Administrative & Office Expenses (Editable) | D46: ='Final workings'!B11 -> 0 | E46: ='Final workings'!C11 -> 0 | F46: ='Final workings'!D11 -> 0 | G46: ='Final workings'!E11 -> 0 | H46: ='Final workings'!F11 -> 0 | I46: ='Final workings'!G11 -> 0 | J46: ='Final workings'!H11 -> 0 | K46: ='Final workings'!I11 -> 0
A47: ='workings-Sensitivity Analysis1'!A47 -> Selling and Distribution Expenses (Editable) | D47: ='Final workings'!B12 -> 0 | E47: ='Final workings'!C12 -> 0 | F47: ='Final workings'!D12 -> 0 | G47: ='Final workings'!E12 -> 0 | H47: ='Final workings'!F12 -> 0 | I47: ='Final workings'!G12 -> 0 | J47: ='Final workings'!H12 -> 0 | K47: ='Final workings'!I12 -> 0
A48: ='workings-Sensitivity Analysis1'!A48 -> General Overheads (Editable) | D48: ='Final workings'!B13 -> 0 | E48: ='Final workings'!C13 -> 0 | F48: ='Final workings'!D13 -> 0 | G48: ='Final workings'!E13 -> 0 | H48: ='Final workings'!F13 -> 0 | I48: ='Final workings'!G13 -> 0 | J48: ='Final workings'!H13 -> 0 | K48: ='Final workings'!I13 -> 0
A49: ='workings-Sensitivity Analysis1'!A49 -> Miscellaneous Expenses | D49: ='Final workings'!B14 -> 0 | E49: ='Final workings'!C14 -> 0 | F49: ='Final workings'!D14 -> 0 | G49: ='Final workings'!E14 -> 0 | H49: ='Final workings'!F14 -> 0 | I49: ='Final workings'!G14 -> 0 | J49: ='Final workings'!H14 -> 0 | K49: ='Final workings'!I14 -> 0
D52: =SUM(D44:D51) -> 1310000 | E52: =SUM(E44:E51) -> 1570000 | F52: =SUM(F44:F51) -> 1650000 | G52: =SUM(G44:G51) -> 1650000 | H52: =SUM(H44:H51) -> 1730000 | I52: =SUM(I44:I51) -> 1820000 | J52: =SUM(J44:J51) -> 1910000 | K52: =SUM(K44:K51) -> 2010000
A54: Interest Statement
D55: =Assumptions!I78 -> 2024-25 | E55: =Assumptions!I79 -> 2025-26 | F55: =Assumptions!I80 -> 2026-27 | G55: =Assumptions!I81 -> 2027-28 | H55: =Assumptions!I82 -> 2028-29 | I55: =Assumptions!I83 -> 2029-30 | J55: =Assumptions!I84 -> 2030-31 | K55: =Assumptions!I85 -> 2031-32
A58: Interest on Term Loan | D58: ='WorKings for PL BS 2'!B5 -> 5.94125e+08 | E58: ='WorKings for PL BS 2'!C5 -> 4.47125e+08 | F58: ='WorKings for PL BS 2'!D5 -> 3.00125e+08 | G58: ='WorKings for PL BS 2'!E5 -> 1.53125e+08 | H58: ='WorKings for PL BS 2'!F5 -> 21437500 | I58: ='WorKings for PL BS 2'!G5 -> 0 | J58: ='WorKings for PL BS 2'!H5 -> 0 | K58: ='WorKings for PL BS 2'!I5 -> 0
A59: Interest on CC Loan | D59: ='WorKings for PL BS 2'!B6 -> 4500000000 | E59: ='WorKings for PL BS 2'!C6 -> 5.427e+09 | F59: ='WorKings for PL BS 2'!D6 -> 5.427e+09 | G59: ='WorKings for PL BS 2'!E6 -> 5.454135e+09 | H59: ='WorKings for PL BS 2'!F6 -> 5.4814057e+09 | I59: ='WorKings for PL BS 2'!G6 -> 5.5088127e+09 | J59: ='WorKings for PL BS 2'!H6 -> 5.5363568e+09 | K59: ='WorKings for PL BS 2'!I6 -> 5.5640386e+09
D61: =SUM(D57:D59) -> 5094125000 | E61: =SUM(E57:E59) -> 5.874125e+09 | F61: =SUM(F57:F59) -> 5.727125e+09 | G61: =SUM(G57:G59) -> 5.60726e+09 | H61: =SUM(H57:H59) -> 5.5028432e+09 | I61: =SUM(I57:I59) -> 5.5088127e+09 | J61: =SUM(J57:J59) -> 5.5363568e+09 | K61: =SUM(K57:K59) -> 5.5640386e+09
