Workbook

Sheet Assumptions.1
B2: Section | C2: Question | D2: Question Type | E2: Editable | F2: Options | G2: Min - Max | H2: Details which are required to be given by Customer | I2: Answer | J2: Particulars
B4: General Information | C4: Name of Firm | D4: Manual entry | E4: No
C5: Status of Concern | D5: Dropdown options to be provided | E5: No | F5: Soleproprietorship,Partnership,LLP,Company
C6: Proprietor / MP / MD Name | D6: Manual entry | E6: No
C7: Firm address | D7: Manual entry | E7: No
C8: Sector | D8: Dropdown options to be provided | E8: No | F8: Manufacturing sector / Service sector (with stock) / Trading sector
C9: Nature of Business | D9: Manual entry | E9: No
B11: Means of Finance details | C11: Do you have working capital limit at present ? | D11: Dropdown options to be provided | E11: Yes | F11: Yes,No
C12: Working capital Loan requirement | D12: Manual entry | E12: Yes | J12: Loan amount
C13: Working capital loan interest | D13: Manual entry | E13: Yes | I13: =H13*1/100 -> 0 | J13: per annum
C14: Processing fees (Inclusing GST) | D14: Manual entry | E14: Yes | I14: =(H14+H14*18/100)*1/100 -> 0 | J14: of loan amount
C15: Working capital (% on Turnover) | D15: Manual entry | E15: Yes | G15: 15% or more than 15% | I15: =H15*1/100 -> 0 | J15: on Sales
B17: Financial Year | C17: 1st Financial year | D17: Dropdown options to be provided | E17: Yes | F17: 2024 - 25 to provide 10 years with Start Month to End Month | J17: Audited | K17: Audited / Provisional
C18: 2nd Financial year | D18: Dropdown options to be provided | E18: Yes | F18: 2024 - 25 to provide 10 years with Start Month to End Month | J18: Estimated
C19: 3rd Financial year | D19: Dropdown options to be provided | E19: Yes | F19: 2024 - 25 to provide 10 years with Start Month to End Month | J19: Projected
C20: 4th Financial year | D20: Dropdown options to be provided | E20: Yes | F20: 2024 - 25 to provide 10 years with Start Month to End Month | J20: Projected
C21: =I17 -> 0
B22: Audited or Provisional financial figures | C22: Turnover | D22: Manual entry | E22: Yes
C23: Opening Stock | D23: Manual entry | E23: Yes
A24: STEP 1 | C24: Direct Material & Expenses | D24: Manual entry | E24: Yes | I24: =9559250+1200000 -> 10759250
C25: Closing Stock | D25: Manual entry | E25: Yes
C26: Non Operating Income | D26: Manual entry | E26: Yes
C27: Electricity | D27: Manual entry | E27: Yes
C28: Depreciation | D28: Manual entry | E28: Yes
C29: Rent | D29: Manual entry | E29: Yes
C30: Salaries & Wages | D30: Manual entry | E30: Yes
C31: Interest on Other loans | D31: Manual entry | E31: Yes
C32: Net Profit Before tax | D32: Manual entry | E32: Yes
C33: Office Admin, Marketing and Miscelleneous Expenses | D33: Autogenerated | E33: NA | I33: =I22+I25+I26-I23-I24-I27-I28-I29-I30-I31-I32 -> -10759250
C34: Net Capital (Opening capital +Net Profit -Drawings) | D34: Manual entry | E34: Yes
C35: Term Loans (Secured and Unsecured Loans Total) | D35: Manual entry | E35: Yes
C36: Current Liabilities | D36: Manual entry | E36: Yes
C37: Net Total Fixed Assets | D37: Autogenerated | E37: Yes | F37: Autogenerated from Schedule for FIXED ASSETS | I37: =F197 -> 0
C38: Depreciation | D38: Autogenerated | E38: NA | I38: =I28 -> 0
C39: Gross Total Fixed Assets | D39: Autogenerated | E39: NA | I39: =I37+I38 -> 0
C40: Investments | D40: Manual entry | E40: Yes
C41: Debtors | D41: Manual entry | E41: Yes
C42: Cash and Cash Equivalents | D42: Manual entry | E42: Yes
C43: Other Current Assets if any | D43: Manual entry | E43: Yes
B45: ASSUMPTIONS | C45: Sales | D45: Auto Generated and Predefined , hence cannot be Edited (Only Admin to be given right to Edit these) | I45: =100/I15/100 -> #DIV/0! | J45: times of Working capital
C46: Sales growth | I46: 1.05 | J46: compared to previous year
C47: Growth of WC interest | I47: 1.005 | J47: compared to previous year
C48: If Non Operating income exists in Provisional , then growth of it to be | I48: 1.05 | J48: compared to previous year
C49: Stock value | I49: 1.3 | J49: of working capital limit
C50: Stock growth every year | I50: 1.01 | J50: of previous year stock
C52: Turnover as per Working Capital to sales Ideal ratio (A) | I52: =I12/I15 -> #DIV/0!
C53: Audited period sale | I53: =I22 -> 0
C54: Estimated period sale based on Audited performance at 20% growth (B) | I54: =I53*120/100 -> 0
C55: Arrived sale for Estimated year (Higher of A / B) | I55: =MAX(I52,I54) -> #DIV/0!
C57: Stock as per WC Loan (A) | I57: =I12*I49 -> 0
C58: Stock as per Audited financial statements (B) | I58: =I25 -> 0
C59: Arrived stock in estimated (A) or (B) Which ever is higher | I59: =MAX(I57:I58) -> 0
C61: Are there any Other Term loans as per Audited financial statements? | I61: =I35 -> 0
C62: Loan repayment term period | I62: 4
C63: Yearly pricipal deduction | I63: =I61/I62 -> 0
C64: Depreciation Schedule | I64: Depreciation rates
C65: Plant and Machinery | I65: 0.15
C66: Service Equipment | I66: 0.15
C67: Shed and Civil works | I67: 0.1
C68: Land | I68: 0
C69: Furniture and Fittings | I69: 0.1
C70: Electrical Items | I70: 0.15
C71: Electronic Items | I71: 0.15
C72: Vehicle | I72: 0.15
C73: Live stock | I73: 0
C74: Other Assets (Nil Depreciation) | I74: 0
C75: Other Assets | I75: 0.1
C76: GROSS PROFIT RATIO
C77: =I17 -> 0 | I77: =wp!C22/wp!C11 -> #DIV/0!
C78: =I18 -> 0 | I78: =I77*100.5/100 -> #DIV/0!
C79: =I19 -> 0 | I79: =I78*100.5/100 -> #DIV/0!
C80: =I20 -> 0 | I80: =I79*100.5/100 -> #DIV/0!
C81: DEBTORS TURNOVER RATIO
C82: =C77 -> 0 | I82: As per Audited figures
C83: =C78 -> 0 | I83: 30
C84: =C79 -> 0 | I84: 35
C85: =C80 -> 0 | I85: 40
C86: CASH AND CASH EQUIVALENTS
C87: =C82 -> 0 | I87: As per Audited figures
C88: =C83 -> 0 | I88: 0.05
C89: =C84 -> 0 | I89: 0.07
C90: =C85 -> 0 | I90: 0.1
B94: SCHEDULE FOR ASSETS: (31.03.2025)
B95: Asset Category | C95: Sl.No | D95: Component | E95: Gross Amount (Rs in Lacs) | F95: Net Amount (Rs in Lacs)
B96: Plant and Machinery | C96: 1 | F96: =SUM(E96:E105) -> 0
C97: 2
C98: 3
C99: 4
C100: 5
C101: 6
C102: 7
C103: 8
C104: 9
C105: 10
B106: Service Equipment | C106: 1 | F106: =SUM(E106:E115) -> 0
C107: 2
C108: 3
C109: 4
C110: 5
C111: 6
...

Sheet wp
A3: STEP 2 : BACK GROUND CALCULATION . NOT TO BE VISIBLE TO CUSTOMER
A4: WORKINGS FOR PROFIT AND LOSS ACCOUNT
A5: PARTICULARS | B5: Schedules | C5: =Assumptions.1!J17 -> Audited | D5: =Assumptions.1!J18 -> Estimated | E5: =Assumptions.1!J19 -> Projected | F5: =Assumptions.1!J20 -> Projected
C6: =Assumptions.1!I17 -> 0 | D6: =Assumptions.1!I18 -> 0 | E6: =Assumptions.1!I19 -> 0 | F6: =Assumptions.1!I20 -> 0
A9: Gross Reciepts:
A11: Turnover (A1) | C11: =Assumptions.1!I22 -> 0 | D11: =Assumptions.1!I55 -> #DIV/0! | E11: =D11*Assumptions.1!I46 -> #DIV/0! | F11: =E11*Assumptions.1!I46 -> #DIV/0!
C13: =SUM(C11:C12) -> 0 | D13: =SUM(D11:D12) -> #DIV/0! | E13: =SUM(E11:E12) -> #DIV/0! | F13: =SUM(F11:F12) -> #DIV/0!
A15: Cost of Goods Sold:
A17: Opening Stock | C17: =Assumptions.1!I23 -> 0 | D17: =C19 -> 0 | E17: =D19 -> 0 | F17: =E19 -> 0
A18: Direct Material & Expenses | C18: =Assumptions.1!I24 -> 10759250 | D18: =D20-D17+D19 -> #DIV/0! | E18: =E20-E17+E19 -> #DIV/0! | F18: =F20-F17+F19 -> #DIV/0!
A19: Closing Stock | C19: =Assumptions.1!I25 -> 0 | D19: =Assumptions.1!I59 -> 0 | E19: =D19*Assumptions.1!I50 -> 0 | F19: =E19*Assumptions.1!I50 -> 0
A20: Operating Expenses | C20: =C17+C18-C19 -> 10759250 | D20: =D11-D22 -> #DIV/0! | E20: =E13-E22 -> #DIV/0! | F20: =F13-F22 -> #DIV/0!
A22: Gross Profit ( D = A1- A- B+ C) | C22: =C13-C20 -> -10759250 | D22: =D11*Assumptions.1!I78 -> #DIV/0! | E22: =E11*Assumptions.1!I79 -> #DIV/0! | F22: =F11*Assumptions.1!I80 -> #DIV/0!
A24: Non Operating Income (E) | C24: =Assumptions.1!I26 -> 0 | D24: =C24*Assumptions.1!I48 -> 0 | E24: =D24*Assumptions.1!I48 -> 0 | F24: =E24*Assumptions.1!I48 -> 0
A26: Adm & Selling Expenses(F) | C26: =C89 -> -10759250 | D26: =D89 -> #DIV/0! | E26: =E89 -> #DIV/0! | F26: =F89 -> #DIV/0!
A28: EBDIT(G = D+ E- F) | C28: =C22+C24-C26 -> 0 | D28: =D22+D24-D26 -> #DIV/0! | E28: =E22+E24-E26 -> #DIV/0! | F28: =F22+F24-F26 -> #DIV/0!
A30: Less : Depreciation (H) | C30: =Assumptions.1!I28 -> 0 | D30: =Depsch!M19 -> 0 | E30: =Depsch!M26 -> 0 | F30: =Depsch!M33 -> 0
A32: EBIT( I = G - H ) | C32: =C28-C30 -> 0 | D32: =D28-D30 -> #DIV/0! | E32: =E28-E30 -> #DIV/0! | F32: =F28-F30 -> #DIV/0!
A34: Less: Interest (J) | C34: =C99 -> 0 | D34: =D99 -> #DIV/0! | E34: =E99 -> #DIV/0! | F34: =F99 -> #DIV/0!
A36: EBT(K = I - J) | C36: =C32-C34 -> 0 | D36: =D32-D34 -> #DIV/0! | E36: =E32-E34 -> #DIV/0! | F36: =F32-F34 -> #DIV/0!
C38: When ever editing is done , this totally must be calculated automatically
A41: WORKINGS FOR BALANCE SHEET
A42: Particulars | B42: Schedules | C42: =C5 -> Audited | D42: =D5 -> Estimated | E42: =E5 -> Projected | F42: =F5 -> Projected
C43: =C6 -> 0 | D43: =D6 -> 0 | E43: =E6 -> 0 | F43: =F6 -> 0
A45: SOURCES OF FUNDS:
A47: Net Capital | C47: =Assumptions.1!I34 -> 0 | D47: =D58-D56-D55-D54-D50 -> #DIV/0! | E47: =E58-E56-E55-E54-E50 -> #DIV/0! | F47: =F58-F56-F55-F54-F50 -> #DIV/0!
A48: (Opening capital + Net profit -Drawings)
A49: TERM LOANS:
A50: Secured and Unsecured Loans | C50: =Assumptions.1!I35 -> 0 | D50: =C50-Assumptions.1!I63 -> 0 | E50: =D50-Assumptions.1!I63 -> 0 | F50: =E50-Assumptions.1!I63 -> 0
A53: CURRENT LIABILITIES:
A54: Bank CC/OD loan | C54: 0 | D54: =IF(D110<D105,D110,Assumptions.1!I12) -> #DIV/0! | E54: =IF(E110<E105,E110,E105) -> #DIV/0! | F54: =IF(F110<F105,F110,F105) -> #DIV/0!
A55: Other current liabilities | C55: =Assumptions.1!I36 -> 0 | D55: 0 | E55: 0 | F55: 0
C58: =SUM(C47:C57) -> 0 | D58: =D73 -> #DIV/0! | E58: =E73 -> #DIV/0! | F58: =F73 -> #DIV/0!
C60: When ever editing is done , this totally must be calculated automatically
A61: APPLICATION OF FUNDS:
A63: FIXED ASSETS: | C63: =Assumptions.1!I37 -> 0 | D63: =Depsch!M20 -> 0 | E63: =Depsch!M27 -> 0 | F63: =Depsch!M34 -> 0
A65: INVESTMENTS: | C65: =Assumptions.1!I40 -> 0 | D65: =C65 -> 0 | E65: =D65 -> 0 | F65: =E65 -> 0
A67: CURRENT ASSETS:
A68: Other current Assets | C68: =Assumptions.1!I43 -> 0 | D68: 0 | E68: 0 | F68: 0
A69: =A19 -> Closing Stock | C69: =C19 -> 0 | D69: =D19 -> 0 | E69: =E19 -> 0 | F69: =F19 -> 0
A70: Debtors | C70: =Assumptions.1!I41 -> 0 | D70: =D11*Assumptions.1!I83/365 -> #DIV/0! | E70: =E11*Assumptions.1!I84/365 -> #DIV/0! | F70: =F11*Assumptions.1!I85/365 -> #DIV/0!
A71: Cash and Cash Equivalents | C71: =Assumptions.1!I42 -> 0 | D71: =D54*Assumptions.1!I88 -> #DIV/0! | E71: =E54*Assumptions.1!I89 -> #DIV/0! | F71: =F54*Assumptions.1!I90 -> #DIV/0!
C73: =SUM(C63:C72) -> 0 | D73: =SUM(D63:D72) -> #DIV/0! | E73: =SUM(E63:E72) -> #DIV/0! | F73: =SUM(F63:F72) -> #DIV/0!
C74: =C58-C73 -> 0 | D74: =D58-D73 -> #DIV/0! | E74: =E58-E73 -> #DIV/0! | F74: =F58-F73 -> #DIV/0!
C76: When ever editing is done , this totally must be calculated automatically
A78: Workings for Administrative & Selling Expenses
C79: =C43 -> 0 | D79: =D43 -> 0 | E79: =E43 -> 0 | F79: =F43 -> 0
A81: Electricity | C81: =Assumptions.1!I27 -> 0 | D81: =C81*D11/C11 -> #DIV/0! | E81: =D81*E11/D11 -> #DIV/0! | F81: =E81*F11/E11 -> #DIV/0!
A82: Rent | C82: =Assumptions.1!I29 -> 0 | D82: =C82 -> 0 | E82: =D82 -> 0 | F82: =E82 -> 0
A83: Salaries & Wages | C83: =Assumptions.1!I30 -> 0 | D83: =C83*D11/C11 -> #DIV/0! | E83: =D83*E11/D11 -> #DIV/0! | F83: =E83*F11/E11 -> #DIV/0!
A84: Processing Charges | C84: 0 | D84: =Assumptions.1!I12*Assumptions.1!I14 -> 0 | E84: =D84 -> 0 | F84: =E84 -> 0
A85: Off Admin and Marketing Expenses | C85: =Assumptions.1!I33 -> -10759250 | D85: =C85*D11/C11 -> #DIV/0! | E85: =D85*E11/D11 -> #DIV/0! | F85: =E85*F11/E11 -> #DIV/0!
C89: =SUM(C81:C87) -> -10759250 | D89: =SUM(D81:D87) -> #DIV/0! | E89: =SUM(E81:E87) -> #DIV/0! | F89: =SUM(F81:F87) -> #DIV/0!
C91: When ever editing is done , this totally must be calculated automatically
A92: Workings for Interest Statement
C93: =C79 -> 0 | D93: =D79 -> 0 | E93: =E79 -> 0 | F93: =F79 -> 0
A95: Interest on Other loans | C95: =Assumptions.1!I31 -> 0 | D95: =C95*D50/C50 -> #DIV/0! | E95: =IF(D50=0,0,D95*E50/D50) -> 0 | F95: =IF(E50=0,0,E95*F50/E50) -> 0
A96: Interest on CC/OD Loan | C96: 0 | D96: =Assumptions.1!I13*wp!D54 -> #DIV/0! | E96: =D96*Assumptions.1!I47 -> #DIV/0! | F96: =E96*Assumptions.1!I47 -> #DIV/0!
C99: =SUM(C95:C98) -> 0 | D99: =SUM(D95:D98) -> #DIV/0! | E99: =SUM(E95:E98) -> #DIV/0! | F99: =SUM(F95:F98) -> #DIV/0!
C101: When ever editing is done , this totally must be calculated automatically
A103: WORKING CAPITAL CALCULATION:
A105: Required WC Limit | C105: =Assumptions.1!I12 -> 0 | D105: =Assumptions.1!I12 -> 0 | E105: =Assumptions.1!I12 -> 0 | F105: =Assumptions.1!I12 -> 0
A107: Closing stock | B107: 0.75 | C107: =B107*C69 -> 0 | D107: =B107*D69 -> 0 | E107: =B107*E69 -> 0 | F107: =B107*F69 -> 0
A108: Debtors | B108: 0.5 | C108: =B108*C70 -> 0 | D108: =B108*D70 -> #DIV/0! | E108: =B108*E70 -> #DIV/0! | F108: =B108*F70 -> #DIV/0!
A110: Eligible Working capital limit | C110: =C107+C108 -> 0 | D110: =D107+D108 -> #DIV/0! | E110: =E107+E108 -> #DIV/0! | F110: =F107+F108 -> #DIV/0!

Sheet FinalWorkings
A2: STEP 3 : DISPLAY TO CUSTOMER FOR MAKING EDITING
A4: Financials and Ratios at a Glance
A5: PARTICULARS | B5: =Assumptions.1!J17 -> Audited | C5: =Assumptions.1!J18 -> Estimated | D5: =Assumptions.1!J19 -> Projected | E5: =Assumptions.1!J20 -> Projected
B6: =Assumptions.1!I17 -> 0 | C6: =Assumptions.1!I18 -> 0 | D6: =Assumptions.1!I19 -> 0 | E6: =Assumptions.1!I20 -> 0
B7: Audited, Hence Not editable | C7: All Items Editable | D7: All Items Editable | E7: All Items Editable
A8: Profit and Loss Items at a Glance :
A9: Gross Revenue / Turnover | B9: =wp!C11 -> 0 | C9: =wp!D11 -> #DIV/0! | D9: =wp!E11 -> #DIV/0! | E9: =wp!F11 -> #DIV/0!
A10: Direct Material & Expenses | B10: =wp!C18 -> 10759250 | C10: =wp!D18 -> #DIV/0! | D10: =wp!E18 -> #DIV/0! | E10: =wp!F18 -> #DIV/0!
A11: Closing Stock / WIP | B11: =wp!C19 -> 0 | C11: =wp!D19 -> 0 | D11: =wp!E19 -> 0 | E11: =wp!F19 -> 0
A12: Non Operating Income | B12: =wp!C24 -> 0 | C12: =wp!D24 -> 0 | D12: =wp!E24 -> 0 | E12: =wp!F24 -> 0
A13: Electricity | B13: =wp!C81 -> 0 | C13: =wp!D81 -> #DIV/0! | D13: =wp!E81 -> #DIV/0! | E13: =wp!F81 -> #DIV/0!
A14: Rent | B14: =wp!C82 -> 0 | C14: =wp!D82 -> 0 | D14: =wp!E82 -> 0 | E14: =wp!F82 -> 0
A15: Salaries & Wages | B15: =wp!C83 -> 0 | C15: =wp!D83 -> #DIV/0! | D15: =wp!E83 -> #DIV/0! | E15: =wp!F83 -> #DIV/0!
A16: Off Admin and Marketing Expenses | B16: =wp!C85 -> -10759250 | C16: =wp!D85 -> #DIV/0! | D16: =wp!E85 -> #DIV/0! | E16: =wp!F85 -> #DIV/0!
A17: Interest on Other Loans | B17: =wp!C95 -> 0 | C17: =B17*C22/B22 -> #DIV/0! | D17: =IF(C22=0,0,C17*D22/C22) -> 0 | E17: =IF(D22=0,0,D17*E22/D22) -> 0
A18: Interest on CC/OD Loan | B18: =wp!C96 -> 0 | C18: =wp!D96 -> #DIV/0! | D18: =wp!E96 -> #DIV/0! | E18: =wp!F96 -> #DIV/0!
A19: Earnings Before Tax (Not Editable) | B19: =PLBS!C35 -> 0 | C19: =PLBS!D35 -> #DIV/0! | D19: =PLBS!E35 -> #DIV/0! | E19: =PLBS!F35 -> #DIV/0!
A21: Balance Sheet Items at a Glance:
A22: Term Loans(Secured and Unsecured) | B22: =wp!C50 -> 0 | C22: =wp!D50 -> 0 | D22: =wp!E50 -> 0 | E22: =wp!F50 -> 0
A23: Other current liabilities | B23: =wp!C55 -> 0 | C23: =wp!D55 -> 0 | D23: =wp!E55 -> 0 | E23: =wp!F55 -> 0
A24: Investments | B24: =wp!C65 -> 0 | C24: =wp!D65 -> 0 | D24: =wp!E65 -> 0 | E24: =wp!F65 -> 0
A25: Other current Assets | B25: =wp!C68 -> 0 | C25: =wp!D68 -> 0 | D25: =wp!E68 -> 0 | E25: =wp!F68 -> 0
A26: Debtors | B26: =wp!C70 -> 0 | C26: =wp!D70 -> #DIV/0! | D26: =wp!E70 -> #DIV/0! | E26: =wp!F70 -> #DIV/0!
A27: Cash and Cash Equivalents | B27: =wp!C71 -> 0 | C27: =wp!D71 -> #DIV/0! | D27: =wp!E71 -> #DIV/0! | E27: =wp!F71 -> #DIV/0!
A29: RATIO ANALYSIS at a Glance: (Not Editable but displayed)
A30: Gross profit ratio (%) | B30: =RATIO!C37 -> #DIV/0! | C30: =RATIO!D37 -> #DIV/0! | D30: =RATIO!E37 -> #DIV/0! | E30: =RATIO!F37 -> #DIV/0!
A31: Net Profit Ratio (%) | B31: =RATIO!C45 -> #DIV/0! | C31: =RATIO!D45 -> #DIV/0! | D31: =RATIO!E45 -> #DIV/0! | E31: =RATIO!F45 -> #DIV/0!
A32: Debtors Turonver Ratio (Days) | B32: =RATIO!C28 -> #DIV/0! | C32: =RATIO!D28 -> #DIV/0! | D32: =RATIO!E28 -> #DIV/0! | E32: =RATIO!F28 -> #DIV/0!
A33: Current Ratio | B33: =RATIO!C11 -> #DIV/0! | C33: =RATIO!D11 -> #DIV/0! | D33: =RATIO!E11 -> #DIV/0! | E33: =RATIO!F11 -> #DIV/0!
A34: Total outside Liabilities to Total Networth | B34: =RATIO!C95 -> #DIV/0! | C34: =RATIO!D95 -> #DIV/0! | D34: =RATIO!E95 -> #DIV/0! | E34: =RATIO!F95 -> #DIV/0!
A36: MAXIMUM PERMISSABLE BANK FINANCE:
A37: Method 1 : Working capital Method | C37: ='MPBF '!B28 -> #DIV/0! | D37: ='MPBF '!C28 -> #DIV/0! | E37: ='MPBF '!D28 -> #DIV/0!
A38: Method 1 : Current Assets Method | C38: ='MPBF '!B62 -> #DIV/0! | D38: ='MPBF '!C62 -> #DIV/0! | E38: ='MPBF '!D62 -> #DIV/0!
A39: Method 3 : Nayak Committee | C39: =nayak!C23 -> #DIV/0! | D39: =nayak!D23 -> #DIV/0! | E39: =nayak!E23 -> #DIV/0!

Sheet coverpage
D7: PROJECTIONS AND ESTIMATIONS
D9: OF
D11: =Assumptions.1!I4 -> 0
D13: =Assumptions.1!I6 -> 0
D17: =Assumptions.1!I9 -> 0
D21: =Assumptions.1!I7 -> 0
D26: Working Capital (CC) Loan | H26: =Assumptions.1!I12 -> 0
D30: PREPARED BY
D32: FINVOIS OPEN BUSINESS SOLUTIONS LLP
D33: MSME & DPR Consultants
D34: Contact : 9618221011

Sheet PLBS
A1: =Assumptions.1!I4 -> 0
A2: =Assumptions.1!I6 -> 0
A3: =Assumptions.1!I7 -> 0
A4: TRADING, PROFIT & LOSS ACCOUNT FOR YEAR ENDED
A5: PARTICULARS | B5: Schedules | C5: =Assumptions.1!J17 -> Audited | D5: =Assumptions.1!J18 -> Estimated | E5: =Assumptions.1!J19 -> Projected | F5: =Assumptions.1!J20 -> Projected
C6: =Assumptions.1!I17 -> 0 | D6: =Assumptions.1!I18 -> 0 | E6: =Assumptions.1!I19 -> 0 | F6: =Assumptions.1!I20 -> 0
A8: Gross Revenue / Turnover:
A10: Revenue | C10: =wp!C11 -> 0 | D10: =ROUND(FinalWorkings!C9,-4) -> #DIV/0! | E10: =ROUND(FinalWorkings!D9,-4) -> #DIV/0! | F10: =ROUND(FinalWorkings!E9,-4) -> #DIV/0!
C12: =SUM(C10:C11) -> 0 | D12: =SUM(D10:D11) -> #DIV/0! | E12: =SUM(E10:E11) -> #DIV/0! | F12: =SUM(F10:F11) -> #DIV/0!
A14: Cost of Goods Sold:
A16: Opening Stock | C16: =wp!C17 -> 0 | D16: =wp!D17 -> 0 | E16: =wp!E17 -> 0 | F16: =wp!F17 -> 0
A17: Direct Material & Expenses | C17: =wp!C18 -> 10759250 | D17: =ROUND(FinalWorkings!C10,-4) -> #DIV/0! | E17: =ROUND(FinalWorkings!D10,-4) -> #DIV/0! | F17: =ROUND(FinalWorkings!E10,-4) -> #DIV/0!
A18: Closing Stock / WIP | C18: =wp!C19 -> 0 | D18: =ROUND(FinalWorkings!C11,-3) -> 0 | E18: =ROUND(FinalWorkings!D11,-3) -> 0 | F18: =ROUND(FinalWorkings!E11,-3) -> 0
A19: Operating Expenses | C19: =C16+C17-C18 -> 10759250 | D19: =D16+D17-D18 -> #DIV/0! | E19: =E16+E17-E18 -> #DIV/0! | F19: =F16+F17-F18 -> #DIV/0!
A21: Gross Profit | C21: =C12-C19 -> -10759250 | D21: =D12-D19 -> #DIV/0! | E21: =E12-E19 -> #DIV/0! | F21: =F12-F19 -> #DIV/0!
A23: Non Operating Income | C23: =wp!C24 -> 0 | D23: =ROUND(FinalWorkings!C12,-3) -> 0 | E23: =ROUND(FinalWorkings!D12,-3) -> 0 | F23: =ROUND(FinalWorkings!E12,-3) -> 0
A25: Less :Admintrative & Selling Expenses | B25: Sch 1 | C25: =C87 -> -10759250 | D25: =D87 -> #DIV/0! | E25: =E87 -> #DIV/0! | F25: =F87 -> #DIV/0!
A27: EBDIT | C27: =C21+C23-C25 -> 0 | D27: =D21+D23-D25 -> #DIV/0! | E27: =E21+E23-E25 -> #DIV/0! | F27: =F21+F23-F25 -> #DIV/0!
A29: Less : Depreciation | C29: =wp!C30 -> 0 | D29: =wp!D30 -> 0 | E29: =wp!E30 -> 0 | F29: =wp!F30 -> 0
A31: EBIT | C31: =C27-C29 -> 0 | D31: =D27-D29 -> #DIV/0! | E31: =E27-E29 -> #DIV/0! | F31: =F27-F29 -> #DIV/0!
A33: Less: Interest | B33: Sch 2 | C33: =C96 -> 0 | D33: =D96 -> #DIV/0! | E33: =E96 -> #DIV/0! | F33: =F96 -> #DIV/0!
A35: EBT | C35: =C31-C33 -> 0 | D35: =D31-D33 -> #DIV/0! | E35: =E31-E33 -> #DIV/0! | F35: =F31-F33 -> #DIV/0!
A39: =A1 -> 0
A40: =A2 -> 0
A41: =A3 -> 0
A43: BALANCE SHEET AS ON
A44: Particulars | B44: Schedules | C44: =C5 -> Audited | D44: =D5 -> Estimated | E44: =E5 -> Projected | F44: =F5 -> Projected
C45: =C6 -> 0 | D45: =D6 -> 0 | E45: =E6 -> 0 | F45: =F6 -> 0
A47: SOURCES OF FUNDS:
A49: Net Capital Including Net Reserves & Surplus | C49: =C58-SUM(C52:C57) -> 0 | D49: =D58-SUM(D52:D57) -> #DIV/0! | E49: =E58-SUM(E52:E57) -> #DIV/0! | F49: =F58-SUM(F52:F57) -> #DIV/0!
A50: (Opening capital + Net profit -Drawings)
A51: TERM LOANS:
A52: Secured and Unsecured Loans | C52: =wp!C50 -> 0 | D52: =ROUND(FinalWorkings!C22,-4) -> 0 | E52: =ROUND(FinalWorkings!D22,-4) -> 0 | F52: =ROUND(FinalWorkings!E22,-4) -> 0
A54: CURRENT LIABILITIES:
A55: Bank CC/OD loan | C55: =wp!C54 -> 0 | D55: =wp!D54 -> #DIV/0! | E55: =wp!E54 -> #DIV/0! | F55: =wp!F54 -> #DIV/0!
A56: Other current liabilities | C56: =wp!C55 -> 0 | D56: =ROUND(FinalWorkings!C23,-4) -> 0 | E56: =ROUND(FinalWorkings!D23,-4) -> 0 | F56: =ROUND(FinalWorkings!E23,-4) -> 0
C58: =C72 -> 0 | D58: =D72 -> #DIV/0! | E58: =E72 -> #DIV/0! | F58: =F72 -> #DIV/0!
A60: APPLICATION OF FUNDS:
A62: FIXED ASSETS: | C62: =Assumptions.1!I37 -> 0 | D62: =wp!D63 -> 0 | E62: =wp!E63 -> 0 | F62: =wp!F63 -> 0
A64: INVESTMENTS: | C64: =wp!C65 -> 0 | D64: =ROUND(FinalWorkings!C24,-4) -> 0 | E64: =ROUND(FinalWorkings!D24,-4) -> 0 | F64: =ROUND(FinalWorkings!E24,-4) -> 0
A66: CURRENT ASSETS:
A67: Other current Assets | C67: =wp!C68 -> 0 | D67: =ROUND(FinalWorkings!C25,-4) -> 0 | E67: =ROUND(FinalWorkings!D25,-4) -> 0 | F67: =ROUND(FinalWorkings!E25,-4) -> 0
A68: =A18 -> Closing Stock / WIP | C68: =wp!C69 -> 0 | D68: =D18 -> 0 | E68: =E18 -> 0 | F68: =F18 -> 0
A69: Debtors | C69: =wp!C70 -> 0 | D69: =ROUND(FinalWorkings!C26,-4) -> #DIV/0! | E69: =ROUND(FinalWorkings!D26,-4) -> #DIV/0! | F69: =ROUND(FinalWorkings!E26,-4) -> #DIV/0!
A70: Cash and Cash Equivalents | C70: =wp!C71 -> 0 | D70: =ROUND(FinalWorkings!C27,-4) -> #DIV/0! | E70: =ROUND(FinalWorkings!D27,-4) -> #DIV/0! | F70: =ROUND(FinalWorkings!E27,-4) -> #DIV/0!
C72: =SUM(C62:C71) -> 0 | D72: =SUM(D62:D71) -> #DIV/0! | E72: =SUM(E62:E71) -> #DIV/0! | F72: =SUM(F62:F71) -> #DIV/0!
A76: Schedule 1 - Explanation for Administrative & Selling Expenses
C77: =C45 -> 0 | D77: =D45 -> 0 | E77: =E45 -> 0 | F77: =F45 -> 0
A79: Electricity | C79: =wp!C81 -> 0 | D79: =ROUND(FinalWorkings!C13,-4) -> #DIV/0! | E79: =ROUND(FinalWorkings!D13,-4) -> #DIV/0! | F79: =ROUND(FinalWorkings!E13,-4) -> #DIV/0!
A80: Rent | C80: =wp!C82 -> 0 | D80: =ROUND(FinalWorkings!C14,-4) -> 0 | E80: =ROUND(FinalWorkings!D14,-4) -> 0 | F80: =ROUND(FinalWorkings!E14,-4) -> 0
A81: Salaries & Wages | C81: =wp!C83 -> 0 | D81: =ROUND(FinalWorkings!C15,-4) -> #DIV/0! | E81: =ROUND(FinalWorkings!D15,-4) -> #DIV/0! | F81: =ROUND(FinalWorkings!E15,-4) -> #DIV/0!
A82: Processing Charges | C82: =wp!C84 -> 0 | D82: =wp!D84 -> 0 | E82: =wp!E84 -> 0 | F82: =wp!F84 -> 0
A83: Office Admin and Marketing Expenses | C83: =wp!C85 -> -10759250 | D83: =ROUND(FinalWorkings!C16,-4) -> #DIV/0! | E83: =ROUND(FinalWorkings!D16,-4) -> #DIV/0! | F83: =ROUND(FinalWorkings!E16,-4) -> #DIV/0!
C87: =SUM(C79:C86) -> -10759250 | D87: =SUM(D79:D86) -> #DIV/0! | E87: =SUM(E79:E86) -> #DIV/0! | F87: =SUM(F79:F86) -> #DIV/0!
A89: Schedule 2 - Interest Statement
C90: =C77 -> 0 | D90: =D77 -> 0 | E90: =E77 -> 0 | F90: =F77 -> 0
A92: Interest on Other Loans | C92: =wp!C95 -> 0 | D92: =ROUND(FinalWorkings!C17,-4) -> #DIV/0! | E92: =ROUND(FinalWorkings!D17,-4) -> 0 | F92: =ROUND(FinalWorkings!E17,-4) -> 0
A93: Interest on CC/OD loan | C93: =wp!C96 -> 0 | D93: =ROUND(FinalWorkings!C18,-3) -> #DIV/0! | E93: =ROUND(FinalWorkings!D18,-3) -> #DIV/0! | F93: =ROUND(FinalWorkings!E18,-3) -> #DIV/0!
C96: =SUM(C91:C95) -> 0 | D96: =SUM(D91:D95) -> #DIV/0! | E96: =SUM(E91:E95) -> #DIV/0! | F96: =SUM(F91:F95) -> #DIV/0!

Sheet RATIO
A1: =Assumptions.1!I4 -> 0
A2: =Assumptions.1!I6 -> 0
A3: =Assumptions.1!I7 -> 0
A5: RATIO ANALYSIS
A7: A . CURRENT RATIO
D8: IDEAL RATIO > 1.33
A9: Particulars | C9: =C84 -> 0 | D9: =D84 -> 0 | E9: =E84 -> 0 | F9: =F84 -> 0
A11: Current Assets / Current Liabilities | C11: =C13/C14 -> #DIV/0! | D11: =D13/D14 -> #DIV/0! | E11: =E13/E14 -> #DIV/0! | F11: =F13/F14 -> #DIV/0!
A13: Current Assets | C13: =SUM(PLBS!C67:C71) -> 0 | D13: =SUM(PLBS!D67:D71) -> #DIV/0! | E13: =SUM(PLBS!E67:E71) -> #DIV/0! | F13: =SUM(PLBS!F67:F71) -> #DIV/0!
A14: Current Liabilities | C14: =SUM(PLBS!C55:C57) -> 0 | D14: =SUM(PLBS!D55:D57) -> #DIV/0! | E14: =SUM(PLBS!E55:E57) -> #DIV/0! | F14: =SUM(PLBS!F55:F57) -> #DIV/0!
A16: NOTES : Indicates Ability to repay short term commitments promptly .
A19: B . DEBTORS TURNOVER RATIO
A20: Particulars | C20: =C72 -> 0 | D20: =D72 -> 0 | E20: =E72 -> 0 | F20: =F72 -> 0
A22: Credit sales / Average debtors | C22: =PLBS!C10/PLBS!C69 -> #DIV/0! | D22: =PLBS!D10/PLBS!D69 -> #DIV/0! | E22: =PLBS!E10/PLBS!E69 -> #DIV/0! | F22: =PLBS!F10/PLBS!F69 -> #DIV/0!
A23: *Sales assumed as credit sales
A25: NOTES : It indicates velocity of debt collection. Higer the DTR indicates good vellocity of debt
A26: collection.
A28: DEBTORS COLLECTION PERIOD : | C28: =B31/C22 -> #DIV/0! | D28: =B31/D22 -> #DIV/0! | E28: =B31/E22 -> #DIV/0! | F28: =B31/F22 -> #DIV/0!
A29: (No of days/debtor turnover ratio)
A31: * No. of Days Assumed as | B31: 365
A33: C . GROSS PROFIT RATIO
A35: Particulars | C35: =C51 -> 0 | D35: =D51 -> 0 | E35: =E51 -> 0 | F35: =F51 -> 0
A37: Gross profit / Sales * 100 | C37: =PLBS!C21/PLBS!C10*100 -> #DIV/0! | D37: =PLBS!D21/PLBS!D10*100 -> #DIV/0! | E37: =PLBS!E21/PLBS!E10*100 -> #DIV/0! | F37: =PLBS!F21/PLBS!F10*100 -> #DIV/0!
A39: NOTES : Indicates Basic Profitability of the Business.
A41: D . NETPROFIT RATIO
A43: Particulars | C43: =C35 -> 0 | D43: =D35 -> 0 | E43: =E35 -> 0 | F43: =F35 -> 0
A45: Netprofit / Sales * 100 | C45: =PLBS!C35/PLBS!C10*100 -> #DIV/0! | D45: =PLBS!D35/PLBS!D10*100 -> #DIV/0! | E45: =PLBS!E35/PLBS!E10*100 -> #DIV/0! | F45: =PLBS!F35/PLBS!F10*100 -> #DIV/0!
A47: NOTES : Indicates overall Profitability of the Business.
A49: E . INTEREST COVERAGE RATIO
E50: IDEAL RATIO - > 1
A51: Partiiculars | C51: =wp!C6 -> 0 | D51: =wp!D6 -> 0 | E51: =wp!E6 -> 0 | F51: =wp!F6 -> 0
A53: E B I / Interest | C53: =C55/C56 -> #DIV/0! | D53: =D55/D56 -> #DIV/0! | E53: =E55/E56 -> #DIV/0! | F53: =F55/F56 -> #DIV/0!
A55: EBI | C55: =PLBS!C31 -> 0 | D55: =PLBS!D31 -> #DIV/0! | E55: =PLBS!E31 -> #DIV/0! | F55: =PLBS!F31 -> #DIV/0!
A56: Interest | C56: =PLBS!C33 -> 0 | D56: =PLBS!D33 -> #DIV/0! | E56: =PLBS!E33 -> #DIV/0! | F56: =PLBS!F33 -> #DIV/0!
A58: NOTE : Indicates ability to meet Interest Obligation of the current year .
A60: F . WORKING CAPITAL TURNOVER RATIO :
A62: Particulars | C62: =C43 -> 0 | D62: =D43 -> 0 | E62: =E43 -> 0 | F62: =F43 -> 0
A64: Networking capital (CA - CL) | C64: =C13-C14 -> 0 | D64: =D13-D14 -> #DIV/0! | E64: =E13-E14 -> #DIV/0! | F64: =F13-F14 -> #DIV/0!
A66: Sales / Networking Capital | C66: =wp!C11/RATIO!C64 -> #DIV/0! | D66: =wp!D11/RATIO!D64 -> #DIV/0! | E66: =wp!E11/RATIO!E64 -> #DIV/0! | F66: =wp!F11/RATIO!F64 -> #DIV/0!
A68: NOTE : Ability to generate sales per Rupee of Working Capital
A70: G . STOCK TURNOVER RATIO
A72: Particulars | C72: =C62 -> 0 | D72: =D62 -> 0 | E72: =E62 -> 0 | F72: =F62 -> 0
A74: COGS | C74: =PLBS!C19 -> 10759250 | D74: =PLBS!D19 -> #DIV/0! | E74: =PLBS!E19 -> #DIV/0! | F74: =PLBS!F19 -> #DIV/0!
A75: AVERAGE STOCK | C75: =(PLBS!C16+PLBS!C18)/2 -> 0 | D75: =(PLBS!D16+PLBS!D18)/2 -> 0 | E75: =(PLBS!E16+PLBS!E18)/2 -> 0 | F75: =(PLBS!F16+PLBS!F18)/2 -> 0
A76: STR = (COGS / AVRG STOCK) | C76: =C74/C75 -> #DIV/0! | D76: =D74/D75 -> #DIV/0! | E76: =E74/E75 -> #DIV/0! | F76: =F74/F75 -> #DIV/0!
A78: NOTES : Stock turn over ratio anaysis helps us to understand business performance of the company.
A79: It Indicates Inventory Management . It shows how offten company sells it inventory.
A80: Higher the ratio indicates good performance of the company. Lower ratio indicates poor performance.
A82: H . CAPITAL TURNOVER RATIO
A84: Particulars | C84: =C20 -> 0 | D84: =D20 -> 0 | E84: =E20 -> 0 | F84: =F20 -> 0
A86: Sales / (Capital+Long Term Loan) | C86: =PLBS!C10/(PLBS!C49+PLBS!C52) -> #DIV/0! | D86: =PLBS!D10/(PLBS!D49+PLBS!D52) -> #DIV/0! | E86: =PLBS!E10/(PLBS!E49+PLBS!E52) -> #DIV/0! | F86: =PLBS!F10/(PLBS!F49+PLBS!F52) -> #DIV/0!
A89: NOTE : Ability to generate Sales per Rupee of Long term Investment
A91: I . TOTAL OUTSIDE LIABILITIES TO TOTAL NETWORTH RATIO :
A93: Particulars | C93: =C9 -> 0 | D93: =D9 -> 0 | E93: =E9 -> 0 | F93: =F9 -> 0
A95: TOL / TW | C95: =SUM(PLBS!C51:C57)/PLBS!C49 -> #DIV/0! | D95: =SUM(PLBS!D51:D57)/PLBS!D49 -> #DIV/0! | E95: =SUM(PLBS!E51:E57)/PLBS!E49 -> #DIV/0! | F95: =SUM(PLBS!F51:F57)/PLBS!F49 -> #DIV/0!
A97: NOTES : Indicates Extent of own funds used in business.
A99: J . RETURN ON CAPITAL EMPLOYED
A101: Particulars | C101: =C93 -> 0 | D101: =D93 -> 0 | E101: =E93 -> 0 | F101: =F93 -> 0
A103: PAT / (Capital+Long Term loan) | C103: =PLBS!C35/(PLBS!C49+PLBS!C52) -> #DIV/0! | D103: =PLBS!D35/(PLBS!D49+PLBS!D52) -> #DIV/0! | E103: =PLBS!E35/(PLBS!E49+PLBS!E52) -> #DIV/0! | F103: =PLBS!F35/(PLBS!F49+PLBS!F52) -> #DIV/0!
A105: NOTE : Indicates overall profitability of Business for capital employed .

Sheet MPBF 
A1: =Assumptions.1!I4 -> 0
A2: =Assumptions.1!I6 -> 0
A3: =Assumptions.1!I7 -> 0
A5: CALCULATION OF MAXIMUM PERMISSIBLE BANK FINANCE
A7: MPBF - Method 1 - 25%(Working Capital Gap)
A8: Particulars | B8: =wp!D5 -> Estimated | C8: =wp!E5 -> Projected | D8: =wp!F5 -> Projected
B9: =wp!D6 -> 0 | C9: =wp!E6 -> 0 | D9: =wp!F6 -> 0
A11: 1. Total current assets | B11: =SUM(PLBS!D67:D71) -> #DIV/0! | C11: =SUM(PLBS!E67:E71) -> #DIV/0! | D11: =SUM(PLBS!F67:F71) -> #DIV/0!
A13: 2. Other current liabilities | B13: =RATIO!D14-wp!D54 -> #DIV/0! | C13: =RATIO!E14-wp!E54 -> #DIV/0! | D13: =RATIO!F14-wp!F54 -> #DIV/0!
A14: (Other than bank borrowings )
A16: 3. Working capital gap | B16: =+B11-B13 -> #DIV/0! | C16: =+C11-C13 -> #DIV/0! | D16: =+D11-D13 -> #DIV/0!
A18: 4. Min. stipulated Networking capital
A19: (25% of WCG excluding export | B19: =+B16*0.25 -> #DIV/0! | C19: =+C16*0.25 -> #DIV/0! | D19: =+D16*0.25 -> #DIV/0!
A20: receivables)
A22: 5. Actual/projected net working capital | B22: =RATIO!D13-RATIO!D14 -> #DIV/0! | C22: =RATIO!E13-RATIO!E14 -> #DIV/0! | D22: =RATIO!F13-RATIO!F14 -> #DIV/0!
A24: 6.Item 3 minus item 4 | B24: =+B16-B19 -> #DIV/0! | C24: =+C16-C19 -> #DIV/0! | D24: =+D16-D19 -> #DIV/0!
A26: 7.Item 3 minus item 5 | B26: =B16-B22 -> #DIV/0! | C26: =C16-C22 -> #DIV/0! | D26: =D16-D22 -> #DIV/0!
A28: 8. Maximum permissible bank | B28: =IF(B24<B26,B24,B26) -> #DIV/0! | C28: =IF(C24<C26,C24,C26) -> #DIV/0! | D28: =IF(D24<D26,D24,D26) -> #DIV/0!
A29: finance(lower of 6 or 7 )
A42: MPBF - Method 2 - 25%(Current Assets)
A43: Particulars | B43: =B8 -> Estimated | C43: =C8 -> Projected | D43: =D8 -> Projected
B44: =B9 -> 0 | C44: =C9 -> 0 | D44: =D9 -> 0
A46: 1. Total current assets | B46: =B11 -> #DIV/0! | C46: =C11 -> #DIV/0! | D46: =D11 -> #DIV/0!
A48: 2. Other current liabilities | B48: =B13 -> #DIV/0! | C48: =C13 -> #DIV/0! | D48: =D13 -> #DIV/0!
A49: (Other than bank borrowings )
A51: 3. Working capital gap | B51: =+B46-B48 -> #DIV/0! | C51: =+C46-C48 -> #DIV/0! | D51: =+D46-D48 -> #DIV/0!
A53: 4. Min. stipulated Networking capital
A54: (25% of Current Assets) | B54: =25/100*B46 -> #DIV/0! | C54: =25/100*C46 -> #DIV/0! | D54: =25/100*D46 -> #DIV/0!
A56: 5. Actual/projected net working capital | B56: =B22 -> #DIV/0! | C56: =C22 -> #DIV/0! | D56: =D22 -> #DIV/0!
A58: 6.Item 3 minus item 4 | B58: =+B51-B54 -> #DIV/0! | C58: =+C51-C54 -> #DIV/0! | D58: =+D51-D54 -> #DIV/0!
A60: 7.Item 3 minus item 5 | B60: =B51-B56 -> #DIV/0! | C60: =C51-C56 -> #DIV/0! | D60: =D51-D56 -> #DIV/0!
A62: 8. Maximum permissible bank | B62: =IF(B58<B60,B58,B60) -> #DIV/0! | C62: =IF(C58<C60,C58,C60) -> #DIV/0! | D62: =IF(D58<D60,D58,D60) -> #DIV/0!
A63: finance(lower of 6 or 7 )

Sheet nayak
A2: =Assumptions.1!I4 -> 0
A3: =Assumptions.1!I6 -> 0
A4: =Assumptions.1!I7 -> 0
A6: WORKING CAPITAL ASSESSMENT - TURNOVER METHOD
A8: NAYAK COMMITTEE RECOMONDATIONS
A10: PARTICULARS | C10: ='MPBF '!B8 -> Estimated | D10: ='MPBF '!C8 -> Projected | E10: ='MPBF '!D8 -> Projected
C11: ='MPBF '!B9 -> 0 | D11: ='MPBF '!C9 -> 0 | E11: ='MPBF '!D9 -> 0
A13: Turnover | C13: =PLBS!D10 -> #DIV/0! | D13: =PLBS!E10 -> #DIV/0! | E13: =PLBS!F10 -> #DIV/0!
A15: Working Capital Requirement | C15: =C13*25/100 -> #DIV/0! | D15: =D13*25/100 -> #DIV/0! | E15: =E13*25/100 -> #DIV/0!
A16: (25% of Turnover)
A18: Minimum Working Capital Limit | C18: =C15*80/100 -> #DIV/0! | D18: =D15*80/100 -> #DIV/0! | E18: =E15*80/100 -> #DIV/0!
A19: (80% of Working Capital Requirment)
A21: Drawing Power | C21: =Assumptions.1!I12 -> 0 | D21: =C21 -> 0 | E21: =D21 -> 0
A23: Maximum Bank CC Loan | C23: =IF(C18<C21,C18,C21) -> #DIV/0! | D23: =IF(D18<D21,D18,D21) -> #DIV/0! | E23: =IF(E18<E21,E18,E21) -> #DIV/0!
A27: Notes :
A28: 1. Maximum Working capital Limit Must not exceed Drawing power .
A29: 2. Four Operating cycles per Annum is Assumed.

Sheet Depsch
A1: =Assumptions.1!I4 -> 0
A2: =Assumptions.1!I6 -> 0
A3: =Assumptions.1!I7 -> 0
A5: CALCULATION OF DEPRECIATION AS PER INCOME TAX ACT
M7: Rs in lacs
B9: =Assumptions.1!B96 -> Plant and Machinery | C9: =Assumptions.1!B106 -> Service Equipment | D9: =Assumptions.1!B116 -> Shed and Civil works | E9: =Assumptions.1!B126 -> Land | F9: =Assumptions.1!B129 -> Electrical Items | G9: =Assumptions.1!B138 -> Electronic items | H9: =Assumptions.1!B148 -> Furniture and Fittings | I9: =Assumptions.1!B158 -> Vehicles | J9: =Assumptions.1!B168 -> Live stock | K9: =Assumptions.1!B177 -> Other Assets | L9: =Assumptions.1!B187 -> Other Assets (Nil Depreciation)
M11: Total
B12: =Assumptions.1!I65 -> 0.15 | C12: =Assumptions.1!I66 -> 0.15 | D12: =Assumptions.1!I67 -> 0.1 | E12: =Assumptions.1!I68 -> 0 | F12: =Assumptions.1!I70 -> 0.15 | G12: =Assumptions.1!I71 -> 0.15 | H12: =Assumptions.1!I69 -> 0.1 | I12: =Assumptions.1!I72 -> 0.15 | J12: =Assumptions.1!I73 -> 0 | K12: =Assumptions.1!I75 -> 0.1 | L12: =Assumptions.1!I74 -> 0
A15: =PLBS!D45 -> 0
A16: WDV at the beginging of year | B16: =Assumptions.1!F96 -> 0 | C16: =Assumptions.1!F106 -> 0 | D16: =Assumptions.1!F116 -> 0 | E16: =Assumptions.1!F126 -> 0 | F16: =Assumptions.1!F129 -> 0 | G16: =Assumptions.1!F138 -> 0 | H16: =Assumptions.1!F148 -> 0 | I16: =Assumptions.1!F158 -> 0 | J16: =Assumptions.1!F168 -> 0 | K16: =Assumptions.1!F177 -> 0 | L16: =Assumptions.1!F187 -> 0 | M16: =B16+C16+D16+E16+F16+G16+H16+I16+J16+K16+L16 -> 0
A17: Add Additions | B17: 0 | C17: 0 | D17: 0 | E17: 0 | F17: 0 | G17: 0 | H17: 0 | I17: 0 | J17: 0 | K17: 0 | L17: 0 | M17: =B17+C17+D17+E17+F17+G17+H17+I17+J17+K17+L17 -> 0
A18: Total | B18: =B16+B17 -> 0 | C18: =C16+C17 -> 0 | D18: =D16+D17 -> 0 | E18: =E16+E17 -> 0 | F18: =F16+F17 -> 0 | G18: =G16+G17 -> 0 | H18: =H16+H17 -> 0 | I18: =I16+I17 -> 0 | ... L18: =L16+L17 -> 0 | M18: =B18+C18+D18+E18+F18+G18+H18+I18+J18+K18+L18 -> 0
A19: Depreciation | B19: =B18*B12 -> 0 | C19: =C18*C12 -> 0 | D19: =D18*D12 -> 0 | E19: =E18*E12 -> 0 | F19: =F18*F12 -> 0 | G19: =G18*G12 -> 0 | H19: =H18*H12 -> 0 | I19: =I18*I12 -> 0 | ... L19: =L18*L12 -> 0 | M19: =B19+C19+D19+E19+F19+G19+H19+I19+J19+K19+L19 -> 0
A20: WDV at the End of Year | B20: =B18-B19 -> 0 | C20: =C18-C19 -> 0 | D20: =D18-D19 -> 0 | E20: =E18-E19 -> 0 | F20: =F18-F19 -> 0 | G20: =G18-G19 -> 0 | H20: =H18-H19 -> 0 | I20: =I18-I19 -> 0 | ... L20: =L18-L19 -> 0 | M20: =B20+C20+D20+E20+F20+G20+H20+I20+J20+K20+L20 -> 0
M21: =B21+C21+D21+E21+F21+G21+H21+I21+J21+K21+L21 -> 0
A22: =PLBS!E45 -> 0 | M22: =B22+C22+D22+E22+F22+G22+H22+I22+J22+K22+L22 -> 0
A23: WDV at the beginging of year | B23: =B20 -> 0 | C23: =C20 -> 0 | D23: =D20 -> 0 | E23: =E20 -> 0 | F23: =F20 -> 0 | G23: =G20 -> 0 | H23: =H20 -> 0 | I23: =I20 -> 0 | ... L23: =L20 -> 0 | M23: =B23+C23+D23+E23+F23+G23+H23+I23+J23+K23+L23 -> 0
A24: Add Additions | B24: 0 | C24: 0 | D24: 0 | E24: 0 | F24: 0 | G24: 0 | H24: 0 | I24: 0 | J24: 0 | K24: 0 | L24: 0 | M24: =B24+C24+D24+E24+F24+G24+H24+I24+J24+K24+L24 -> 0
A25: Total | B25: =B23+B24 -> 0 | C25: =C23+C24 -> 0 | D25: =D23+D24 -> 0 | E25: =E23+E24 -> 0 | F25: =F23+F24 -> 0 | G25: =G23+G24 -> 0 | H25: =H23+H24 -> 0 | I25: =I23+I24 -> 0 | ... L25: =L23+L24 -> 0 | M25: =B25+C25+D25+E25+F25+G25+H25+I25+J25+K25+L25 -> 0
A26: Depreciation | B26: =B25*B12 -> 0 | C26: =C25*C12 -> 0 | D26: =D25*D12 -> 0 | E26: =E25*E12 -> 0 | F26: =F25*F12 -> 0 | G26: =G25*G12 -> 0 | H26: =H25*H12 -> 0 | I26: =I25*I12 -> 0 | ... L26: =L25*L12 -> 0 | M26: =B26+C26+D26+E26+F26+G26+H26+I26+J26+K26+L26 -> 0
A27: WDVat the end of Year | B27: =B25-B26 -> 0 | C27: =C25-C26 -> 0 | D27: =D25-D26 -> 0 | E27: =E25-E26 -> 0 | F27: =F25-F26 -> 0 | G27: =G25-G26 -> 0 | H27: =H25-H26 -> 0 | I27: =I25-I26 -> 0 | ... L27: =L25-L26 -> 0 | M27: =B27+C27+D27+E27+F27+G27+H27+I27+J27+K27+L27 -> 0
M28: =B28+C28+D28+E28+F28+G28+H28+I28+J28+K28+L28 -> 0
A29: =PLBS!F45 -> 0 | M29: =B29+C29+D29+E29+F29+G29+H29+I29+J29+K29+L29 -> 0
A30: WDV at the beginging of year | B30: =B27 -> 0 | C30: =C27 -> 0 | D30: =D27 -> 0 | E30: =E27 -> 0 | F30: =F27 -> 0 | G30: =G27 -> 0 | H30: =H27 -> 0 | I30: =I27 -> 0 | ... L30: =L27 -> 0 | M30: =B30+C30+D30+E30+F30+G30+H30+I30+J30+K30+L30 -> 0
A31: Add Additions | B31: 0 | C31: 0 | D31: 0 | E31: 0 | F31: 0 | G31: 0 | H31: 0 | I31: 0 | J31: 0 | K31: 0 | L31: 0 | M31: =B31+C31+D31+E31+F31+G31+H31+I31+J31+K31+L31 -> 0
A32: Total | B32: =B30+B31 -> 0 | C32: =C30+C31 -> 0 | D32: =D30+D31 -> 0 | E32: =E30+E31 -> 0 | F32: =F30+F31 -> 0 | G32: =G30+G31 -> 0 | H32: =H30+H31 -> 0 | I32: =I30+I31 -> 0 | ... L32: =L30+L31 -> 0 | M32: =B32+C32+D32+E32+F32+G32+H32+I32+J32+K32+L32 -> 0
A33: Depreciation | B33: =B32*B12 -> 0 | C33: =C32*C12 -> 0 | D33: =D32*D12 -> 0 | E33: =E32*E12 -> 0 | F33: =F32*F12 -> 0 | G33: =G32*G12 -> 0 | H33: =H32*H12 -> 0 | I33: =I32*I12 -> 0 | ... L33: =L32*L12 -> 0 | M33: =B33+C33+D33+E33+F33+G33+H33+I33+J33+K33+L33 -> 0
A34: WDVat the end of Year | B34: =B32-B33 -> 0 | C34: =C32-C33 -> 0 | D34: =D32-D33 -> 0 | E34: =E32-E33 -> 0 | F34: =F32-F33 -> 0 | G34: =G32-G33 -> 0 | H34: =H32-H33 -> 0 | I34: =I32-I33 -> 0 | ... L34: =L32-L33 -> 0 | M34: =B34+C34+D34+E34+F34+G34+H34+I34+J34+K34+L34 -> 0
